{
    "00640=0065B": "_____カ-リオン城會議室",
    "0065D=006BA": "アレス:「諸君、集ってもらったのは、ほかでもない。私は、バルシア王ゼネルを葬る計畵をしている」",
    "006BC=00743": "エクタ-:「その仕事なら、ぜひ私にまかせてもらいたい。あの男は魔法の力で强力な軍を組織した。ほっておけばログリスを滅ぼしてしまうだろう」",
    "00745=00780": "コンラッド:「しかり!_ゼネルは我らにおまかせいただきたい」",
    "00782=007FD": "アレス:「いや、今やゼネルのまわりは嚴重なガ-ドがなされている。私ならば直接會見できるから、やつを倒す機會を得られるだろう」",
    "007FF=00828": "コンラッド:「ならば、優秀な兵士を護衛に」",
    "0082A=008A1": "アレス:「その必要はない。エクタ-、君には國境の警備をたのみたい。コンラッド、君は私にもしもの事があれば後をたのみたい」",
    "008A3=00914": "コンラッド:「何と!_主君にもしもの事あらば、後に續くは家臣の定め、全軍あげてバルシアを、木端微塵にしてくれん!」",
    "00916=00991": "アレス:「早まるな、我が軍にそれほどの力はない。それに私は簡單には死なない、きっと■って來る。それまでしっかりと守ってくれ」",
    "00993=009B6": "大司敎:「神のご加護のあらんことを」",
    "009B8=009C3": "エレイン:「",
    "009C8=009DF": "待って、わたしも行くわ」",
    "009E1=00A3A": "アレス:「君は無鐵砲だからお留守番だよ、エレイン。君がいては余計心配なんだ。わかってくれ」",
    "00A3C=00A57": "_____バルシア城、王の間",
    "00A59=00ADC": "アレス:「...と言うわけで、バルシア王よ、神の攝理に從い、あなたの手によって造られた兵士達を出來るだけ早く、處分していただきたい」",
    "00ADE=00B6D": "ゼネル:「成る程、カ-リオンの意見は■聽した。しかし、我が兵は我が子も同じ、處分せよとは無理な話。もし、必要とあらば我が兵をお分けしてもよいぞ」",
    "00B6F=00BF6": "「■れっ!_貴樣の造った魔物のために貴樣の臣民も苦しんでおるのだ!_人■を追い出し、ログリスの地を貴樣のガラクタで埋めつくすつもりか!」",
    "00BF8=00C0D": "「かっ、■が動かん!」",
    "00C0F=00C6E": "ゼネル:「馬鹿め!_貴樣のやりそうな事など見えすいておるわ!_あらかじめ結界を張っておいたのだ。",
    "00C70=00CA7": "我が牢獄でゆっくり頭を冷やすがよい。處刑はその後じゃ!」",
    "00CA9=00CFE": "ゼネル:「ただちにカ-リオンに兵を送れ!_アレスがいなくなっては簡單に我が物となろう」",
    "00D00=00D0F": "武將:「御意!」",
    "00D11=00D7C": "敵將:「あきらめろ!_貴樣らの王アレスは我が軍に捕らえられている。ジタバタすればやつの命が短くなるだけだ!」",
    "00D7E=00D89": "エクタ-:「",
    "00D8E=00DD9": "くっ!!_皆は引け!_だが、私は引かんぞ。ここで果てるとも、悔いはないわ!」",
    "00DDB=00DE2": "兵士:「",
    "00DE7=00DF8": "我らとて同じ心!」",
    "00DFA=00E17": "_____カ-リオン城、王の間",
    "00E19=00E24": "エレイン:「",
    "00E29=00E76": "サ-.コンラッド。私はただちに王を救出に向かうつもりです。後をお願いしますよ」",
    "00E78=00ED7": "コンラッド:「王の命令にそむかれるおつもりか。王は必ず■って來られると言っておられたではないか」",
    "00ED9=00F5C": "エレイン:「■って見ていろとおっしゃるの。この城の守りはあなた方で大丈夫でしょう。でも、王を救いに行けるのは、私以外にいるかしら?」",
    "00F5E=00FC3": "コンラッド:「...あなたが强い事はわかっている。よろしい、が、我が軍の特殊部隊を護衛につけさせよう」",
    "00FC5=00FF4": "エレイン:「その必要はないわ。一人の方が氣樂よ」",
    "00FF6=0104D": "コンラッド:「王と同じ事を言う。しかし、護衛はつけるったらつける。影の部隊、出ませい!」",
    "0104F=0108A": "エレイン:「まあ、[カラス]たちね。いいわ、すぐに行くわよ」",
    "0108C=010A5": "_____バルシア城、牢獄",
    "010A7=010C4": "牢番:「止れ!_何者だ貴樣は」",
    "010C6=01129": "男:「さあて私は誰なんだろうねえ。それより、私はその牢の中の男に用があるのだ。さあ、開けてくれんか」",
    "0112B=0116C": "牢番:「何をボケた事いっているんだ。みんな、この男を捕まえてくれ」",
    "0116E=011B1": "男:「おやまあ、チョロチョロうるさい連中だ。ネズミにでもなるかい?」",
    "011B3=0120E": "男:「アレス..._おやまあ、隨分とはでに痛めつけられておる。どりゃ、藥をきかせたろうかい」",
    "01210=01219": "アレス:「",
    "0121D=01226": "ぐわっ!」",
    "01228=0126F": "アレス:「お、おお!_■の痛みが消えている!_あなたは?_施術師か!?」",
    "01271=012BC": "男:「いや何、ちょっと神■をマヒさせただけじゃよ。起きてもらわんと困るでな。",
    "012BE=012D7": "アレス:「あ、あれは!?」",
    "012D9=0135A": "男:「バルシア軍のグリフォンライダ-じゃ。お前さんにこの藥をあげよう。動物を意のままに操れる藥じゃ。ネ-チャンに使ってはならんぞ。",
    "0135C=013B9": "この牢を出た所にやつらが寢ておる。そいつを使ってグリフォンに乘り、カ-リオンの城に歸るのじゃ」",
    "013BB=013E0": "アレス:「あなたは我■の味方なのか?」",
    "013E2=01423": "男:「そう思って結構じゃ。さ、早く魔法が切れんうちに行くのじゃ!」",
    "01425=0143E": "______カ-リオンの城",
    "01440=0144D": "コンラッド:「",
    "01452=01475": "ア、アレス王!_よくぞご無事で!!」",
    "01477=0149C": "アレス:「約束したはずだ、必ず歸ると」",
    "0149E=014C1": "コンラッド:「どうやって敵の城を?」",
    "014C3=01536": "アレス:「魔法を使う男に助け出された。グリフォンに乘って■って來たが、途中痛みがぶりかえして、何度も氣を失いかけた。",
    "01538=01585": "今度あの男にあったらよく■を言わねばならない。で、バルシア軍の樣子はどうだ?」",
    "01587=0160A": "コンラッド:「申し譯ござらん!_バルシアの軍はマ-シア付近に大勢力を展開し、その强力な軍に攻め立てられ、領地の大半は敵の手に...」",
    "0160C=0164B": "アレス:「仕方のない事だ。皆が無事なら領地はまた取り返せばよい」",
    "0164D=0169A": "コンラッド:「それが..._殘念ながら、主だった者は戰場から■って來ず...」",
    "0169C=016A9": "コンラッド:「",
    "016AD=016E2": "智惠者ラモラックも戰場に出たまま行方不明になっておる」",
    "016E4=016ED": "アレス:「",
    "016F2=01731": "何っ!_...そうか、皆の消息がわからぬのだな。エレインもか?」",
    "01733=01796": "コンラッド:「彼女は王を救出に行くと言って出て行かれた。影の部隊を護衛につけたので大丈夫とは存ずる」",
    "01798=01831": "アレス:「私の命令にそむき、城を出た者に護衛までつける事もなかろう..._まあ、よい。今はこれからの事を考えなければ。さっそく諸公に手紙を書く事にしよう」",
    "01833=01840": "コンラッド:「",
    "01845=01886": "お待ち下され。ガイアより加勢がまいっております。ぜひお目通りを!」",
    "01888=01891": "アレス:「",
    "01896=018BF": "それは!_もしかしてギルフォ-ドかっ!?」",
    "018C1=018CA": "ラルフ:「",
    "018CF=0193A": "アレス殿、心配していたが、無事でなにより。急を聞き、とにかくかけつけて來た所だ。追ってトリスラムもまいろう。",
    "0193F=019C0": "我が息子ギルフォ-ドもいっしょに來たのだが、いつの間にかいなくなってしまった。例によってどこかに潛り■んで寢ているのではないかな」",
    "019C2=01A0B": "アレス:「ラルフ殿、あなたがいらして下さっただけで十分!_そちらの方は?」",
    "01A0D=01A7C": "ラルフ:「ガイアの女王、アイラ樣の三男アルフレッド殿だ。實は今度の戰いが、先のガイアでの戰鬪と關係があるらしい。",
    "01A7E=01AA3": "詳しくはアルフレッド殿から聞いてくれ」",
    "01AA5=01AB4": "アルフレッド:「",
    "01AB9=01B24": "初めまして。私は、幼い頃よりカディラに修業に出され、今までお目にかかれませんでした。母もよろしくとの事です」",
    "01B26=01B75": "アルフレッド:「昔、ガイア大陸では異次元の魔物ガロアと人■との戰いがありました。",
    "01B77=01BEA": "その後、ガロアの出生をさぐるため、多くの神■が異世界へと旅立たれました。しかし、ガロアは滅びてはいなかったようです」",
    "01BEC=01C67": "アルフレッド:「[術者]達はガロアの魂がログリスへと運ばれたと言います。おそらく、それがゼネルに大きな力を■えているのです。",
    "01C6D=01CBA": "ガロアを完全に滅ぼす方法は私たちにはわかりません。が、まずはゼネルを倒さねば」",
    "01CBC=01D2B": "コンラッド:「その通り!_敵の軍は町の近くまで迫っている樣子。今しがたリオスの町より助けを求める使者がまいった」",
    "01D2D=01D66": "アレス:「まずは失地を回復せねば。よし、兵を擧げるぞ!!」",
    "01D68=01D81": "______ノ-フォ-ク城",
    "01D83=01DEA": "オラシラン:「何、カ-リオンの使者だと?追い返せ、わしゃ知らんぞ。我が國は、バルシアと同盟を結んでおる」",
    "01DEC=01E07": "_____エドウィン城、王室",
    "01E09=01E3A": "マレイ:「カ-リオンからの使者か?_追い返すのだ!",
    "01E3C=01E61": "...で、よいですかな、スリフト殿?」",
    "01E63=01ECE": "スリフト:「エドウィン王、それでよい。バルシア四將の一人として、今後ともこの國の行き方を御指導申し上げよう」",
    "01ED0=01EED": "____水上城塞都市ミュルトン",
    "01EEF=01F68": "ウォラス:「ふむ、カ-リオンが窮地に陷ったか。しかし、いきなりバルシア王を殺そうとしたのは愚かだ。まず、足元を固めねばな。",
    "01F6A=01FA9": "者共!_我らは[プライ]の町を奪うぞ。南下して勢力を擴大する!」",
    "01FAB=01FD2": "武將マ-ク:「ただちに、兵を送ります!」",
    "01FD4=01FED": "______■山國グレイス",
    "01FEF=0206C": "マンティス:「カ-リオンの王アレスからの親書だと?_それどころではないわ。腹黑いミュルトンの連中がこちらをうかがっているのだ。",
    "0206E=020BB": "今すぐに兵を北上させ、[ウェルズ]を手にいれる。ミュルトンに先を越されるな!」",
    "020BD=020E2": "クレイ:「すでに手配はすんでおります」",
    "020E4=0213D": "マンティス:「それから、三人の娘達にも勝手な行動をせんようにとくれぐれも言っておいてくれ。",
    "0213F=02186": "ジイの言う事なら少しは聞くだろう。敵よりも我が娘の方がよほどやっかいだ」",
    "02188=021A1": "______水上城ベニック",
    "021A3=021DA": "ゲルグ:「フッフッ、ゼネルに敎わった通り、魔王を呼出せた",
    "021DC=02231": "なあに、今はゼネルに協力しているが、あいつの力を利用するだけしたら寢首をかいてやるさ」",
    "02233=0228C": "ゲルグ:「者共、準備はよいか。强い者だけがこの地の支配者として生き殘るのだ!_出擊せよ!」",
    "0228E=022A7": "______森林國レスタ-",
    "022A9=0231A": "ウォルタ-:「アレスも馬鹿なやつよのう。バルシア相手に勝てるわけがないではないか。領地を廣げるにはよい機會である。",
    "0231C=02369": "まず、サネット、ヒュリアをいただく!__バルシアとの戰いはその後でよかろうぞ」",
    "0236B=023A8": "武將:「それがよいでしょう。準備のほどは順調に進んでおります」",
    "023AA=023C5": "_____エルフの國サネット",
    "023C7=0244E": "エルフガンド:「カ-リオンの王アレスも何を血迷ったのか。我らは隣國レスタ-と戰わねばならない。バルシアとは互いに戰わない約束をしている」",
    "02450=024AB": "武將:「そのレスタ-の樣子ですが、兵を集め、我が國に向け、今にも侵攻を始めようとしています」",
    "024AD=0251A": "エルフガンド:「よし、レスタ-が出兵したら、ただちにこちらも兵を擧げよ!_やつらを我が森から叩き出してやれ!」",
    "0251C=02535": "______平地國ヒュリア",
    "02537=02574": "ミラン:「若君、バルシアがカ-リオンに攻め入ったそうですぞ!」",
    "02576=025CB": "レクス王子:「知っている。だが、我らはノ-フォ-クやレスタ-の軍を何とかせねばならん」",
    "025CD=0262C": "グラン王子:「レスタ-の軍は部下が追い返す。バルシアに味方したノ-フォ-クのブタ共は始末惡いが。",
    "0262E=02669": "そんな事より兄上に早く王位についてもらわねばこの國が治らん」",
    "0266B=026D6": "レクス王子:「弟よ、王位はお前が■げばよい。亡き父もそれを望んでおられたはずだ。今は力の强い男が必要なのだ」",
    "026D8=02725": "グラン王子:「何を言われる。オレは戰いが好きなだけだ。王位なんざあ、いらない」",
    "02727=02786": "ミラン:「また始まったか、いいかげんになされ!_そんな事では亡きヒュリア王はお嘆きになりますぞ!",
    "02788=027C3": "とりあえずはこの戰亂の世を治めて、ごゆっくりお決め下され!」",
    "027C5=027F4": "グラン王子:「その通りだ。城はたのんだぜ、兄上」",
    "027F6=02853": "バルシア王_ゼネル:「諸君、私はログリスの國■の代表として、今日まで多くの困難を克服してきた。",
    "02855=028C6": "だが、最近、己れの權力欲を抑え切れず、我らが友情を裏切る者が現れた。しかし、私の軍隊は必ず、諸公の國を守るだろう」",
    "028C8=02931": "もちろん、一度そむいた國でも、行いを改めるならば、いつでも暖かく迎えるつもりだ。それが、私の使命だと思う」",
    "02933=029A4": "ベニック王_ゲルグ:「おお、何と廣いお心か!_しかし、南の連中や周■の田舍者は何を考えているやらわかりませんぞ!」",
    "029A6=02A13": "マ-シア王_ガ-ビン:「もし南のやつらが攻めて來ても、このわしとルシアスで、マ-シアの台地を越えさせはせぬ!」",
    "02A15=02A7E": "ノ-フォ-ク王_オラシラン:「マ-シアの左右はベニック城とノ-フォ-ク城でがっちり固めておる。安心されよ」",
    "02A80=02AFB": "リスレイ王_ライオス:「マ-シアの後には、我がリスレイ城やベルダの三つ首城がひかえている。バルシアまで來れる軍隊はいない!」",
    "02AFD=02B6C": "アルカナイヤ王_ミ-ゼル:「ゼネル樣の魔法でドラゴンも思いのまま、强力なグリフォンライダ-部隊も我が手中にある」",
    "02B6E=02BCB": "エドウィン王_マレイ:「バルシア王よ、ゴ-レムの力を借りんでもバルシアは安泰だと思うが...」",
    "02BCD=02BD6": "ゼネル:「",
    "02BDA=02C43": "■れっ!_戰いで貴重な人命を落とさせるは忍びがたいからこそ、このゾンの力を借りてゴ-レムを造りだしたのだ!",
    "02C48=02C6D": "貴樣までも裏切者と同じ事を言うのか!」",
    "02C6F=02CE6": "セバ-ト王_サグ:「エドウィンは南の影響を受けやすい所。バルシア王よ、たよりになる者をエドウィンに送った方がよいかもな」",
    "02CE8=02D15": "風の將軍_スリフト:「ならば、わたしが行こう」",
    "02D17=02D2E": "地の將軍_マクガイア:「",
    "02D33=02D68": "ライオス殿が良ければ、わしはリスレイ城にいたいのだが」",
    "02D6A=02DB5": "ゼネル:「皆も知っていると思うが、我が腹心の部下だ。たよりにしてやってくれ。",
    "02DB7=02E40": "先日、不幸にして、モロシア王とベルダ王が相次いで亡くなってしまわれた。いたましい事だ。跡■ぎが決まるまでオ-グとモルドレッドに守らせよう」",
    "02E42=02E6B": "水の將軍_オ-グ:「では私は、モロシアへ」",
    "02E6D=02E9C": "火の將軍_モルドレッド:「ベルダ城は、お任せを」",
    "02E9E=02F17": "學者:「中立國の王と話をされるなら、[外交]をされるとよいでしょう。いきなり部隊を城に乘■ませては話し合いになりますまい。",
    "02F19=02F78": "また、戰鬪中に敵リ-ダ-と[交涉]できるのは一度だけですが、うまく行く割合はかなり低いでしょう」",
    "02F7A=02FF1": "學者:「部隊のいるエリアではキャンプできません。[城の中]にいる部隊は見えませんから、城の中を探らなければなりませんよ」",
    "02FF3=03032": "兵士:「兵舍では兵員の補充ができます。キャンプする事もできます。",
    "03034=0306F": "兵舍、牢屋など、特別な部屋ではキャンプする事ができるのです。",
    "03071=030AE": "ここでキャンプすればこの兵舍にいる仲間をいれる事ができますよ」",
    "030B0=0310F": "兵士:「[城]でキャンプが出來るようになるのは、城の中にいる[城主]を倒すなどの條件が必要です。",
    "03111=03154": "[城の前]の部隊を倒しただけでは、城を手にいれた事にはなりませんよ」",
    "03156=031BD": "兵士:「兵士の能力を■えたければ、武器屋で裝備を■えさせて下さい。クラスを■えた方がよいとは限りませんよ",
    "031BF=0321E": "一つの部隊にいる、兵士の種類が多いのは困りものです。種類をまとめるために武器屋を利用して下さい。",
    "03220=03279": "弓を裝備すると、攻擊力や防御力は下がります。一度、弓をはずしたら、また買わねばなりません」",
    "0327B=032E2": "兵士:「部隊を[脫出]させると、元いたエリアに■るとは限りません。退却に適したエリアに行く事があります。",
    "032E4=03355": "誤って[脫出]させないように氣をつけて下さい。[脫出します]のメッセ-ジが出た時、右クリックでキャンセルできます」",
    "03357=033D0": "兵士:「部隊をつくるにはリ-ダ-が必要です。リ-ダ-の資格の無い者をリ-ダ-にすると、とても弱いチ-ムになってしまいます」",
    "033D2=03453": "兵士:「こんな事を言っては大■失■ですが、兵を生かすも殺すもリ-ダ-次第。うまく地形、相性、援軍を使って戰いを有利に進めて下さい」",
    "03455=034C0": "兵士:「フィ-ルドにアイテムが落ちている事もありますから、敵やモンスタ-を倒したあと、よく探してみて下さい」",
    "034C2=03523": "兵士:「モンスタ-も金を隱し持っているそうですよ。偉そうじゃありませんか。私なんか一文も無いのに」",
    "03525=0357C": "兵士:「ヒュリアで馬を買えば、ナイトは騎兵になれるそうです。馬はとても强いらしいですよ」",
    "0357E=035F1": "兵士:「コントロ-ルしているキャラクタ-なら、アイテムを使ったり、弓、マジックの發射をマウスで直接行う事ができます。",
    "035F3=03660": "マウスカ-ソルをキャラクタ-に合せて左クリックして下さい。危ないアイテムを持たせている時は氣をつけて下さいね。",
    "03662=036AD": "魔法使いそれぞれにウインドウを開いてやれば、魔法使用の指示を出しやすいです」",
    "036AF=0372A": "學者:「我■はバルシアのゴ-レムを硏究しております。造られた物は、およそ、[火][水][土][風]の4元素からなっています」",
    "0372C=03773": "學者:「4元素から造られた物は大抵どれかの元素にかたよりがあるものじゃ。",
    "03775=037B8": "我■人間は[土]の性質を持ち、[火]には弱いので氣をつけねばならん」",
    "037BA=0381D": "學者:「精靈も4元素からなるという。この地にも4元素を司どる精靈や、その[王]がいると言われておる」",
    "0381F=03870": "學者:「魔物やゴ-レムの中には、■れただけで[石化]や[毒]を受ける事があります。",
    "03872=038D3": "[毒]は生命力が減るので怖いですよ。時間が立つと消えますが、[藥]で早目に治した方がよいでしょう」",
    "038D5=03940": "學者:「精靈同士は、[火]は[水]に弱く、[水]は[風]に弱く、[風]は[土]に弱く、[土]は[火]に弱い。",
    "03942=03975": "魔法はこの限りではないが、覺えておくとよいでしょう」",
    "03977=039CC": "「ゼネル王はいきなり大きな魔力を持つようになったと言う。普通の人間には考えられん事だ」",
    "039CE=03A49": "「バルシア城の中で何が起きているのか、占いによって透視しようとしましたがだめでした。何かとても邪惡な物が感じられるだけです」",
    "03A4B=03AD4": "「遠くへでかけていても、[外交]を使えば、すぐにこの城に顔を出す事ができる。ここで■■をもらい、ヒュリアで馬を買えば[騎兵隊]ができるぞ」",
    "03AD6=03B45": "大司敎:「神の名において、すぐれた勇士に■■を■えるのは私の役目。少しでも、兵士達のはげみになればと思いますぞ」",
    "03B47=03BAE": "大司敎:「レベルが50以上になったカ-リオンの兵士がいたらおいでなさい。[騎士]にしてさしあげましょう」",
    "03BB0=03BE9": "大司敎:「おお、すばらしき勇者よ!_新しい■■を授けよう」",
    "03BEB=03C3C": "大司敎:「神と聖ミカエルの名において、汝に■■を■える。忠誠、豪■、幸運であれ!」",
    "03C3E=03C6F": "「カ-リオンの■けらどもめ、蹴散らしてくれるわ!」",
    "03C71=03C98": "「待っていたぞ。刀のサビにしてくれる!」",
    "03C9A=03CE9": "ラモラック:「おお、助けにきてくれたか。わしはカ-リオンの參謀[ラモラック]だ。",
    "03CEB=03D42": "我が友、エクタ-は殘念ながら深手を負ってしまった。わしは、エクタ-の敵を擊たねばならん」",
    "03D44=03D7F": "ラモラック:「あ、あなたは、アレス王!_よくぞご無事で!!」",
    "03D81=03DB2": "アレス:「ラモラックか!_お前も無事でよかった!」",
    "03DB4=03E27": "エルフガンド:「すぐにでも、我らの敵[レスタ-]を攻め滅ぼしてもらいたい。我が軍に直接指揮を下してもらっても結構だ」",
    "03E29=03E50": "エルフガンド:「エルフの活躍を期待する」",
    "03E52=03E91": "エルフガンド:「これは、大陸より仲間が持ってきてくれた[笛]だ。",
    "03E93=03ED2": "バ-ドマンと心を通わせる事ができるらしい。持って行くがよかろう」",
    "03ED4=03F1D": "エルフガンド:「まさか、アレス王ともあろう者が、我が國を敵に回すとは!!」",
    "03F1F=03F78": "武將:「レスタ-は混亂に乘じて、領地を廣げようとしている。バルシア王よりずっと惡い奴らだ」",
    "03F7A=03FC5": "兵士:「我らは人間達のやる事に興味はない。ただ靜かに暮していたいだけなのだ」",
    "03FC7=03FEC": "兵士:「人間達の欲の深さにはあきれる」",
    "03FEE=04037": "武將:「他の者なら許さないが、人間でもアレス王の命令にならば從ってもよい」",
    "04039=040AC": "兵士:「指導者達はレスタ-にばかり氣をとられているが、バルシアの連中は妖精をとらえているらしい。とても危險な連中だ」",
    "040AE=0411F": "兵士:「バルシアの王は人造人間を造りだしているようだが、技術が進めばもっと强力なゴ-レムも造れるようになるだろう」",
    "04121=0413E": "兵士:「よろしい。どうぞ中へ」",
    "04140=0419D": "マレイ:「わ、わたしが惡いのではない。バルシアにおどされていただけなのだ!_殺さないでくれ!」",
    "0419F=04204": "スリフト:「ようこそ!_エドウィンの城に_この城にはもう興味がなくなった。わしは[アルカナイヤ]へ行く",
    "04206=04249": "君たちは、我が下部に歡迎させよう..._いでよ!_風のバンパイア!」",
    "0424B=04278": "エクタ-:「わしはカ-リオンの武將エクタ-だ」",
    "0427A=0429F": "アレス:「エクタ-!_しっかりしろ!」",
    "042A1=0432A": "エクタ-:「殘念ながらこのエクタ-、ここを動けぬ。長い命ではないのだ。敵將スリフトは風の魔物を從えている。氣をつけろ。後はたのんだ...」",
    "0432C=0435B": "「!_こと切れたか!_...必ずカタキは擊つ!」",
    "0435D=043BA": "ウンディ-ネ:「やっと自由になれた、ありがとう!_水の王のお呼びがあればいつでもまいります!」",
    "043BC=04441": "ガレス:「遠い所御苦勞にござる。それがし、バルシア軍南部方面隊、カ-リオン進行作戰部隊、後方支援隊、第2食料調達隊指揮官ガレスと申す。",
    "04443=0447C": "それがし、かねてより我が王の行動には疑念をいだいておった」",
    "0447E=04513": "ガレス:「魔法を用いて人心をたぶらかし、ケッタイな泥人形どもを造り、それを敎練して兵隊に仕立てるなど、神を恐れぬフラチなヤロウとはあの方の事でござる!",
    "04515=0454C": "わしは斷じて人形を動かすために軍人になったのではない!」",
    "0454E=045A3": "ガレス:「ご依賴の內容はわかった。我らはこれより、カ-リオンに忠誠をお誓い申し上げる」",
    "045A5=04602": "ワイルド:「おお、カ-リオンの使者か!_拙者、バルシアの用兵にはホトホト嫌氣がさしておった所だ",
    "04604=04649": "何が悲しゅうて、このわしが、ブタどもといっしょにいなければならんのだ?",
    "0464B=0468E": "我らはこれよりカ-リオンの部隊として戰う_我らの戰いを見るがよい!」",
    "04690=04701": "ウォルタ-:「何と!_カ-リオンが我が國に加勢して良いと!_それは賢明と申すもの。何せ我が國は財政豊か、人材豊富。",
    "04703=0473E": "我が國とカ-リオンが手を結べば、バルシアなどなにするものぞ。",
    "04740=0478B": "ゼネルの人形など子供のママゴト遊びにすぎぬわ。我が武將を好きに使うがよいぞ」",
    "0478D=047B6": "ウォルタ-:「勝利の日まで共に戰おうぞ!」",
    "047B8=04805": "ウォルタ-:「ええい、こうなれば私が相手だ!_どこからでかかって來るがよい!」",
    "04807=04858": "武將:「この國の繁榮はウォルタ-王がもたらしたもの、私はどこまでも王について行く」",
    "0485A=048BF": "武將:「カ-リオンの王が指揮をとっていただけるとはありがたい!_正直な話、ウォルタ-王では心配だった」",
    "048C1=04900": "武將:「この國の財産は、今こそ皆のためにつかわれるべきである!」",
    "04902=04925": "兵士:「ようこそ、レスタ-の城へ!」",
    "04927=04984": "兵士:「エルフ、ヒュリアを一度に相手にしてはさすがに苦しい。どうも王のお考えはよくわからない」",
    "04986=049DD": "兵士:「エルフなんかがいては我が國にとっていい事はない、早目に滅ぼしちまうのがいいのさ」",
    "049DF=04A30": "兵士:「ヒュリアの國は跡■ぎがいなくてもめているそうです。トルなら今のうちですよ」",
    "04A32=04A85": "兵士:「ヒュリアの騎兵は我が弓隊でなんとかなるが、森でエルフと戰うのはキツイですよ」",
    "04A87=04ABE": "兵士:「エルフと戰って下さるのですね!_ありがとう!!」",
    "04AC0=04B23": "シルビア:「あ、ありがとう。モンスタ-なんかなんともないけど、突然材木が降ってきたのにはまいったわ。",
    "04B25=04B7E": "あなた方は?_カ-リオンの人達なの!_グレイス王に會って下さい。案內するわよ。私の父なの」",
    "04B80=04BE7": "ビリアン:「お姉樣達はいいわよ。好き勝手に外に出ているのですもの。わたしはお父樣のそばにいてあげるのよ」",
    "04BE9=04C54": "マンティス:「娘を助けていただきかたじけないが、今は敵同志。いずれ戰わねばならんのが悲しい。お引取り願おう」",
    "04C56=04CCD": "マンティス:「カ-リオンには、我が娘の危ない所を助けていただき、感謝の言葉もない。この國は小さいながらもモノは豊かじゃ。",
    "04CCF=04D04": "よく鍛えられた兵士もおる。喜んで協力させていただこう」",
    "04D06=04D65": "マンティス:「我が娘達じゃが、わしの言う事をきかんで困っておる。よければ面倒をみていただきたい」",
    "04D67=04D88": "マンティス:「首尾はどうじゃな?」",
    "04D8A=04DB9": "シルビア:「わたしでよければ、手■ってあげるわ」",
    "04DBB=04DF6": "マンティス:「な、なんだなんだなんだ、おまえたちは何者だ!」",
    "04DF8=04E29": "マンティス:「ろうぜき者じゃ!_者共、出會え!!」",
    "04E2B=04E62": "武將:「我が國にとって、脅威はベニック城とミュルトンだ」",
    "04E64=04ED9": "武將:「ミュルトンのやつらは、我らから鐵やミスリルを買っていたのだが、直接原料を手に入れるためこの國を狙っているのだ」",
    "04EDB=04F4E": "武將:「たとえバルシアと手を結ぼうと、ミュルトンには負けたくないと思っていた所だ。お力添えいただけるとはありがたい」",
    "04F50=04F9B": "「ミュルトンのやつらは掠奪者ですよ。あんなやつらをほっておいてはいけない!」",
    "04F9D=05008": "「ベニックのゲルグ王は、大陸からリザ-ドマンを連れてきて兵士にしているんだ。水■じゃやつらにはかなわないよ」",
    "0500A=05061": "「ベニックの王はゼネル王から魔法を敎わり、魔王を呼出したって■だ。本■ならえらい事だぞ」",
    "05063=05098": "「このままではいずれミュルトンかベニックにやられる!」",
    "0509A=050C9": "「王女樣を助けていただき、ありがとうございます」",
    "050CB=0510E": "「この國の何がいいって、三人の王女樣の元で戰えるのが一番うれしい!」",
    "05110=05175": "武將:「我が國は助けを求める程、窮しておらんし、またお主らを助ける義理もない。今の所はお引取り願おう」",
    "05177=051A4": "「カ-リオンの使者か?_ならば通ってもよいぞ」",
    "051A6=051F9": "プリセン:「何と、重裝備でおしかけて來るとは無■な者達!_ここは通さぬ、歸るがよい」",
    "051FB=0523A": "プリセン:「女と思って甘く見ると命を落とすぞ!_いざ、勝負!!」",
    "0523C=052A1": "ゲルグ:「こんな姿では、もう王とは言えん。お願いだ。わしも連れて行ってくれ。ゼネルをおどかしてやる!」",
    "052A3=0530E": "ゲルグ:「グッ!_い、いかん、敵が我が城にのりこんで來る!_と、とにかくこうしちゃおれん。早く手をうたんと」",
    "05310=0533D": "ゲルグ:「そ、そうじゃ、魔王を呼出すのじゃ!」",
    "0533F=05362": "ゲルグ:「い、いでよ、大いなる力!」",
    "05364=053DD": "魔王:「わしを呼出したのはお前か。...おや?_お前は以前にわしを呼出し、城を修理しろだの何だのと命じた者ではないか!?」",
    "053DF=0543C": "ゲルグ:「その通り!_魔王よ、我が命に從え。敵の軍が我が城に侵入した。すぐに追い拂うのじゃ!」",
    "0543E=054A1": "魔王:「愚か者め、わしがたのみを聞くのは一度だけだ!_貴樣をその根性にふさわしい姿にしてやろう!!」",
    "054A3=054C0": "ゲルグ:「ゲ、ゲゲゲゲ!!!」",
    "054C2=054DD": "リザ-ドマン:「.....」",
    "054DF=05512": "「おお、頭の中のモヤモヤがすっきりと晴れた氣分だ!」",
    "05514=05573": "「くそっ!_ゲルグのやつ、俺たちをコキ使いやがって!_だが、これで自由になれた。今に見ていろ!」",
    "05575=055B6": "「俺達はバルシアに恨みがある。あんた達といっしょに戰ってもいいぜ」",
    "055B8=05607": "「本■に惡い奴はゼネルだ。あいつの魔法で、俺たちは自由をうばわれたのだからな!」",
    "05609=05664": "魔王:「なんだ、つまらぬやつらには興味はない。[アレス]はどこにいる?_やつをつれて來い!」",
    "05666=056DD": "魔王:「[アレス]よ待っていた。神■の意志により、わしはお前の力を解き放たなければならん。自分の使命を重く受け止めよ!」",
    "056DF=05750": "魔王:「わしはしばらく、お前達のやる事を見物させてもらおう。どうなろうと、死者がでれば、わしは仕事に困らんからな」",
    "05752=057E9": "魔王:「お前は火の妖精王、眞の名を[ゴルド]。今お前の能力、火の精靈召喚はモロシア城のオ-グに封じられている。だが、この地の災厄を救えるのはお前だけだ」",
    "057EB=05842": "魔王:「おや、[アイラ]の息子がいるのか。よし、お前ももう少しはましな姿にしてやろう!」",
    "05844=0585D": "_______西マ-シア城",
    "0585F=058EA": "ルシアス:「カ-リオンの軍が動き出したか。だが、このマ-シアの台地に上がってこれるかな?_我が軍の攻擊はこれから始まる、存分に見るがよい!」",
    "058EC=0594F": "ルシアス:「何?_この私にバルシアを裏切れと!?_たわけた事を!_ゼネル樣は確かにかわってしまった。",
    "05951=0599E": "しかし、この西マ-シアを治めているのはこの私とバルシアなのだ。國は捨てない!」",
    "059A0=059FD": "レ.ジンプ:「我が殿、カ-リオンの軍は想像以上に强力。この■子城の守りに過信されてはいけない。",
    "059FF=05A3C": "ここは樣子を見ながらリスレイまで退却するのが良いかと思います」",
    "05A3E=05A87": "ルシアス:「何を申す!_ガ-ビンの守る東マ-シアある限りここを死守する!」",
    "05A89=05AEC": "ルシアス:「どうした事だ!_東マ-シアから援軍が來ないではないか!_まさか、東の城が落ちたのか!?」",
    "05AEE=05B63": "ルシアス:「ええい、この城はくれてやる!_だが、これで終わったわけではない!_下がれ下郞!_近寄るとたたっ切るぞ!!」",
    "05B65=05BD0": "レ.ジンプ:「わしは、マ-シアの軍師。この國はもはやわしを必要としていない。あなた方のお役に立てるなら幸い。",
    "05BD2=05C3F": "北のベルダ城はマ-シア最强の城。うかつに近寄ってはならん。强い[騎兵]をそろえるなど作戰を立てる必要があろう」",
    "05C41=05C5A": "_______東マ-シア城",
    "05C5C=05CCF": "ガ-ビン:「このマ-シアの■子城は不落の城だ。どちらを攻めても峽擊にあうだけだ。わきだす程の兵力を見せつけてやろう」",
    "05CD1=05D0E": "武將:「殿っ!_一大事にござる。若樣が敵の手に落ちました!!」",
    "05D10=05D6B": "ガ-ビン:「何っ!_我が息子、コルビンが敵の手に落ちたと!!!_まだ、生きておるのかっ!?」",
    "05D6D=05D90": "ガ-ビン:「おお!_そちは無事か!」",
    "05D92=05DF7": "コルビン:「カ-リオンの軍は私を捕らえようとはしませんでした。私には、彼らにこそ正義があると思います。",
    "05DF9=05E18": "これ以上彼らとは戰いたくない!」",
    "05E1A=05E65": "武將:「ルシアス樣に援軍を差し向けねば、若樣は助かります。ここはご決斷を!」",
    "05E67=05E96": "ガ-ビン:「むうぅぅぅ_...許せ、ルシアス!」",
    "05E98=05EB9": "兵士:「若樣!_よくぞご無事で!」",
    "05EBB=05F22": "ガ-ビン:「...お前の言う通りだ。もともと、この戰いは我らがゼネル王を止めなかったのが間違いの始まり。",
    "05F24=05F7F": "城はカ-リオンに明け渡す。しかし、一國の將として、敗戰の責任はとらねばならん。さらばじゃ!」",
    "05F81=05F94": "コルビン:「父上!」",
    "05F96=06003": "武將:「若、ご心配なく、我らが殿を死なしたりはいたしません。それより若はカ-リオンに從い、ゼネルと戰うのです。",
    "06005=0605C": "もとよりそれが正しい道であった。我らの過ちを繰り返さぬようたのみましたぞ。では、ご免!」",
    "0605E=060A1": "コルビン:「...父を追うのはやめよう。ゼネルを倒す事が私の務めだ」",
    "060A3=060D6": "兵士:「これから我らは誰に從えばよいのでしょうか?」",
    "060D8=0611F": "兵士:「バルシアについてたんじゃ、いずれはやられちゃうと思ってましたよ」",
    "06121=06168": "兵士:「死んだ兵士の魂がこの城の中をさまよっています。氣をつけて下さい」",
    "0616A=061BB": "コルビン:「城はカ-リオンに明渡す。わたしもバルシアと戰おう。ログリスのために!」",
    "061BD=061F8": "コルビン:「もはやこれまでか、煮るなり燒くなり好きにせい!」",
    "061FA=06241": "「殺すつもりはない。お前達の王はゼネルに操られているのだ。目をさませ!」",
    "06243=06274": "コルビン:「その通りだ。だが、私になにが出來る?」",
    "06276=0629D": "「父王を說得するのだ。それしか道は無い」",
    "0629F=062D8": "コルビン:「...わかった。その仕事確かに私にしかできん」",
    "062DA=0634D": "オラシラン:「とうとう敵軍がこの城まで來たぞい!_全軍迎擊するだ!_バルシアの援軍はどうした?_誰か知らんかい!?」",
    "0634F=063BC": "オラシラン:「何をしとる。敵がやって來る。ほらもう目の前に來とる。みんなワシを守るのだ。逃げるんじゃねえぞお」",
    "063BE=0643F": "オラシラン:「まいった!_カ-リオンは想像以上に强いわい。これ以上はもちこたえられん。降伏する、勘弁してくれ、殺さんといてくれ!」",
    "06441=0649E": "「ええい、こうなった以上しかたがねぃ。オウ、野郞ども、かまうこたねえから、たたんじまえ!!!」",
    "064A0=06519": "「いや、まったくヒュリアは手ごわいわい。何度攻めても攻めきれん。せめてこちらに出てくれば、弓隊のエジキにしてやれるのだが」",
    "0651B=06558": "「オ、オレ達まで敵に回すとは愚かな!_皆、逃げずに戰うのだ!」",
    "0655A=065C9": "「この塔には[風の王]が住んでいる。■みの人間にはとても會いに行けるものではないが、行くなら氣をつけて行かれよ」",
    "065CB=06610": "「あなた方と戰おうとは思わなかったが、これも定めよ。覺悟するがいい!」",
    "06612=0664F": "「よくぞ、この塔に巢くう魔物を倒した!_わしは風の王バルドル」",
    "06651=066B4": "バルドル:「わしの力を借りたいのか?_今のわしは無力じゃ。我が下部シルフがリスレイ城に捕らわれてな。",
    "066B6=066ED": "シルフを開放してくれるのなら、大きな力が出せるであろう」",
    "066EF=0672E": "バルドル:「シルフもわが手にもどった!_わしもひと暴れせねばな」",
    "06730=0677B": "「どうやら敵ではないようだな。だが、あやしい者は一人たりともここを通さん!」",
    "0677D=067D4": "「冥土の土産に聞くが良い。我こそはヒュリアの王子グラン。我が手にかかる事を光榮と思え!」",
    "067D6=06841": "レクス王子:「おお!_我がヒュリアに手を貸していただけるのか!_それはありがたい、我が騎士■も喜ぶであろう」",
    "06843=068C0": "レクス王子:「ところで、戰には私も參加させてもらいたい。城でのんびりしている場合でもない狀況だ。私には道士としての心得がある」",
    "068C2=0692B": "グラン王子:「我が方に加勢していただけるとの事、聞き及び飛んでまいった。ぜひ、私を連れて行ってもらいたい」",
    "0692D=06954": "レクス王子:「弟よ、お前は國を守るのだ」",
    "06956=069B7": "グラン王子:「何を言われる。オレはとにかく戰いが好きなのだ。バルシアと戰えば强いやつも出てこよう」",
    "069B9=06A24": "ミラン:「また始まったか、いいかげんにしなさい!!_どちらが役に立つかカ-リオンに決めてもらえばよかろう!」",
    "06A26=06A9D": "レクスとグランどちらを仲間にしますか?_________道士レクス_______________勇者グラン_______",
    "06A9F=06AEC": "レクス王子:「私を選べば間違いない。弟よ、後はたのむぞ。早く國位につくのだよ」",
    "06AEE=06B69": "「私の友人、[イゾルデ]がいればもっと賴りになるのだが、バルシアに連れ去られたようなのだ。彼女を救うためにも、國を離れたい」",
    "06B6B=06BD2": "グラン王子:「やっぱり實戰で選ぶならこのオレだ。兄上、內政はおまかせする。王になるのはやっぱりあなただ」",
    "06BD4=06C2F": "レクス王子:「我がヒュリアの地をよくも踏みにじってくれた。わしがゆっくりと相手をいたそう!」",
    "06C31=06C72": "武將:「我が王子は二人とも立派な方なのに、喧■ばかりしておられる」",
    "06C74=06CC3": "武將:「王子のうち一人が王座につけば、この國も少しは靜かになろうと言うものだが」",
    "06CC5=06D08": "「使者も立てずに、押■むとはなんと無■な!_早■に引き上げられよ!」",
    "06D0A=06D43": "「いきなり城に乘■めば、敵とみなされてもしかたがないぞ!」",
    "06D45=06DCA": "「この城の北にある[リンカ-の町]には、我が國の部隊が雇われている。恥かしい話だが、彼らはあの町に身賣りしたのだ。我らとは關係がない」",
    "06DCC=06E15": "「[リンカ-の町]に入れなければ、北の城[モロシア]を攻める事はできない」",
    "06E17=06E90": "兵士:「我らが南に氣をとられているうちに、北の方が手薄になっております。[ゼム]に住むゴブリンも不穩な動きをしている樣子」",
    "06E92=06F07": "兵士:「ノ-フォ-クの瀧には、不思議な種族が住んでいると聞きます。あまり人前に姿を見せませんが、妖精とも違うようです」",
    "06F09=06F60": "兵士:「北の自由都市リンカ-は大丈夫だろうか?_ゴブリンやモロシアからの攻擊が心配です」",
    "06F62=06F9F": "兵士:「バルシアと戰うには、我が騎兵がきっと役に立つでしょう」",
    "06FA1=07002": "モルドレッド:「ふんっ、この三つ首の城に攻め■める者がいようとは!_おめおめと捕まってたまるか!」",
    "07004=0704F": "モルドレッド:「馬鹿め、バルシアへは行かせぬ。我が火に燒かれて死ぬが良い!」",
    "07051=070C0": "ニミュ-:「[炎]の力は本來[アレス]のもの。彼が精靈の王として目覺めなければ、ゼネルの力を防ぎきれないでしょう",
    "070C2=0711F": "アレスの力の元[サラマンダ-]はモロシア城に封じ■められています。早く助けださねばなりません!",
    "07121=07144": "これからは、わたしも共に戰います!」",
    "07146=071BD": "ニミュ-:「カ-リオンの王[アレス]には重大な使命があります。ベニック城にいる[魔王]に力をかしてもらうと良いでしょう」",
    "071BF=071FA": "ニミュ-:「大きい者が强い者ではない!_いでよ、水の守り!」",
    "071FC=0723F": "「ばぁかぁめが、わしに勝てると思うのか。どこからでもかかって來い!」",
    "07241=07264": "「ええい、■ケラめ!_消え失せろ!」",
    "07266=0728B": "「來たか。我が刃の餌食となるがよい!」",
    "0728D=072A6": "_______リスレイの城",
    "072A8=07321": "ライオス:「カ-リオンの軍勢が何千人こようが、この城を落とせるものか!_わしの目の黑いうちは一步たりともこの城を通さぬ!」",
    "07323=0737E": "ライオス:「うろたえるな!_マ-シア、ベルダどちらかの城が殘っていれば、リスレイは安全だ!」",
    "07380=073CB": "マクガイア:「さよう、ゼネル樣の名譽にかけても、ここはわしが守ってみせるわ」",
    "073CD=0744C": "ライオス:「何と!_マ-シアもベルダも落ちてしまったのか!_お、恐れるべきやつらだ!_オルニックに入られてはもはや補給もならぬ。",
    "0744E=0748F": "わしの民を飢えで殺すにはしのびない。城はカ-リオンにくれてやる!」",
    "07491=074E0": "ライオス:「マクガイアよ、お主の武運もこれまでだ。この城はカ-リオンに明渡した」",
    "074E2=074EF": "マクガイア:「",
    "074F4=07549": "おのれライオス!_バルシアを裏切る者には[死]あるのみ、わしをあなどってはいかんぞ!」",
    "0754B=075A2": "ライオス:「うおぉぉっ!_リスレイの國は化物に支配されておったのか、む、無念じゃ...」",
    "075A4=075B1": "マクガイア:「",
    "075B6=0760B": "我こそは、バルシア四將、土のマクガイア。貴樣らなど、わし一人で充分だ。さあ、來いっ!」",
    "0760D=07694": "武將:「まさか、マクガイアが化物であろうとは!_ゼネルのやつ、何をたくらんでいるんだ?_我が國が一時とはいえゼネルに加■したとは不覺!」",
    "07696=07707": "武將:「この城は外から侵入する事はほとんど不可能なのですが、あなた方より前に、カ-リオンの軍が侵入しているのです。",
    "07709=07752": "リ-ダ-の女性は大■勇敢で、風のように我が城の中を驅け拔けて行きましたよ」",
    "07754=07781": "兵士:「ここを拔けると、リスレイの町に出ます」",
    "07783=0780C": "兵士:「しかし、カ-リオンにはかないませんよ。あんなきれいな人が戰士なんだもの。我らが見とれている間にオルニックの方へ行ってしまいました」",
    "0780E=07837": "シルフ:「ああ、ようやく廣い空へ■れる!」",
    "07839=078A6": "ミ-ゼル:「せっかくゼネル樣より賜ったこの城。むざむざ貴樣達に渡してなるものか!_みなの者、やっておしまい!」",
    "078A8=07913": "スリフト:「くそっ!_俺の可愛い部下をむざむざ殺させやがって!_バルシアの領主はどいつもこいつも能無しだ!」",
    "07915=07958": "ミ-ゼル:「何を言う!_早くカ-リオンを倒し、わしを助けるのだ!!」",
    "0795A=07983": "スリフト:「助からないよ、お前なんぞは!」",
    "07985=079AA": "ミ-ゼル:「や、やめっ、し、死むっ!」",
    "079AC=07A03": "スリフト:「えええい、どうせこの戰は負け戰だ!_わしにはもう、戰う氣力が無くなったわ!」",
    "07A05=07A54": "イゾルデ:「私がいる限り、ここは通せないわ。私の魔法をゆっくりと味わうがいい!」",
    "07A56=07AAF": "レクス:「イゾルデ!_僕だ、レクスだよ!ゼネルに魔法をかけられているな、僕が解いてやる!」",
    "07AB1=07AF2": "イゾルデ:「...レクス!_私は一■__...どうしたのかしら?」",
    "07AF4=07B3B": "レクス:「どうやら惡い夢を見ていたようだね。僕らといっしょに來るんだ!」",
    "07B3D=07BA4": "オ-グ:「私はバルシア四將、水のオ-グ。カ-リオンの武將に物申す。わが王ゼネル樣こそ神の存在を越える者」",
    "07BA6=07BE5": "オ-グ:「決着をつける時が來たようだな。見せてやろう、水の力!」",
    "07BE7=07C6E": "サラマンダ-:「FUUU..._これでシャバに■れるぜ。っと、待った。まだゼネルに■を返さなければいけねえ。大將のお呼びを待つとするか」",
    "07C70=07CE1": "アグラベイン:「よくぞ我が軍を敗った。ここに、たどり着いただけでも大したものだ。だが、この砦の門を通る事はできん。",
    "07CE3=07D0C": "セバ-ト、モロシアある限り先へは進めんぞ」",
    "07D0E=07D47": "アグラベイン:「グオオオ、このわしまでが敗れるとは..._",
    "07D49=07D86": "グリフォン騎兵よ。セバ-トの城へ行け!_最後の反擊をたのむ!」",
    "07D88=07DB9": "アグラベイン:「くっ!_この砦の秘密悟られたか!」",
    "07DBB=07E0A": "ガラ-ド:「ホッホッホ、來なすったか。今ゴ-レム達に人の道を說いておった所じゃ」",
    "07E0C=07E91": "ガラ-ド:「何?_意味がわからんかな。つまり、このゴ-レム達に人の心を植え付け、ゼネルが何をしようとしているのか、話してやったんじゃ。",
    "07E93=07EC4": "ゴ-レム達は惱んでおるよ。自分達の境遇を知ってな」",
    "07EC6=07F03": "「皆で話をしました。そして、ゼネルに反抗する事を決めたのです。",
    "07F05=07F68": "師、ガラ-ドは私たちが本■の命を得るためには、この■を捨て去らなければならないとおっしゃっています」",
    "07F6A=07FD9": "「私たちの生みの親に反抗する事は辛いのですが、このままでは希望が見えない。どうか、私たちも共に戰わせて下さい!」",
    "07FDB=08020": "ガラ-ド:「どうじゃ?_疲れているかな?_いっちょう回復してやろうか」",
    "08022=0806F": "ガラ-ド:「この城の奧深くに、この騷ぎの元、大陸から來た魔導士[ゾン]がおる。",
    "08071=080C6": "やつの本性は異次元の魔物[ガロア]。なんとも手ごわい相手じゃ。ゼネルとて油斷が出來ん。",
    "080C8=0811D": "やつらと渡りあうのは[アレス]の使命じゃ。これより先はアレスに從って進まねばならんぞ」",
    "0811F=08194": "スリフト:「...俺は、望んでこんな姿になったわけじゃない。部下といっしょに羽根をつけられて、そのあげくがこのザマだ。",
    "08196=081D1": "こんな仕打を受けるなら、あんた達に協力してやろうじゃないか。",
    "081D3=08236": "クリスタルを壞すんだ。魔法でも、矢でもいい。王室に出られたら、そこからさらに地下へ通じる入口がある」",
    "08238=0828B": "ゼネル:「よくぞここまで來た。私はバルシアの王にして魔法使い、天才科學者のゼネルだ」",
    "0828D=082C4": "ゼネル:「違う!_私が本物、そっちは僞物だ、ロボットだ」",
    "082C6=0831B": "ゼネル:「いや、こっちが本物のゼネルだ。あっちのやつはわたしのクロ-ンだ、コピ-だ!」",
    "0831D=0838E": "ゼネル:「このわたしがゼネルだ。よっく見てくれ。このわたしが、正眞正銘、本物間違いなしのゼネルだ。そいつらは幻だ」",
    "08390=083F7": "ゼネル:「こっちだ、わたしこそ世界一の魔法使いゼネル。そっちはわたしの造った人造人間だ、ゴ-レムなのだ」",
    "083F9=0842C": "「うるさいっ!!_なんでも良い!_全員倒してやる!」",
    "0842E=08475": "ゼネルみんないっしょに:「いい度胸だ。私に勝てるものならかかって來い!」",
    "08477=08496": "「これが人造人間の[卵]か!?」",
    "08498=084EF": "「我■はこの[卵]から生まれたのです。_人を殺すために。我■は生まれるべきではなかった」",
    "084F1=0851E": "「これを破壞すれば、あなた方は滅びてしまう!」",
    "08520=0855D": "「なんの!_我らは必ず生まれ■わる。そのために破壞するのだ!」",
    "0855F=085B8": "「ようこそ、ここが私たちの生まれた所。私たちは今からここを破壞するのです。どうぞこちらへ」",
    "085BA=0860B": "「ゾンはこの中にいるはず。あなたなら彼を倒せるに違いない。どうか、お願いします!」",
    "0860D=08640": "ゾン:「よくぞここまで、さすがは妖精の王[ゴルド]」",
    "08642=08697": "ゼネル:「わたしの僞物ですら、あれ程の力を持っている。ゾンと二人なら負けはせぬわい!」",
    "08699=086F8": "ゾン:「おや?_それは違うぞ、ゼネルよ。お前はカ-リオンに負けたのだ。責任はとってもらわねばな」",
    "086FA=08727": "ゼネル:「!な、何と!?_どうするつもりだ!」",
    "08729=0875A": "ゾン:「さて、貴樣達もゼネルと共に溶けてもらおう」",
    "0875C=08791": "アレス:「うわっ、い、いかんっ!_溶岩にとかされる!」",
    "08793=087F8": "アレス:「おや??_熱くないぞ?_いや、何だかとてもいい氣持ちだ。まるで母の腕の中にいるような...」",
    "087FA=0886F": "「_...アレス__...アレス_いや、[火の妖精王ゴルド]あなたの[炎]は何にも負けはしません、心を强く持つのです」",
    "08871=088A8": "アレス:「..だ、誰だ、私を呼ぶのは?_ニミュ-か??」",
    "088AA=088E1": "「早くしてくれゴルド!_俺に命じるんだ、ゾンを倒せと!」",
    "088E3=0891C": "アレス:「その聲は..._サラマンダ-_我が守り[火龍]!",
    "0891E=08945": "妖精王の名において、いでよサラマンダ-」",
    "08947=089BA": "ゾン:「ははははは..._馬鹿めっ!_思うツボと言うものよ。そうだ、もっと熱を出すのだ。我が魂にふりそそげ、炎よ!」",
    "089BC=08A07": "ゾン:「ありがとよ。■中に力がみなぎるわい。さて、わしが相手をしてあげよう」",
    "08A09=08A7C": "ゾン:「ア、アヂッ!_ね、熱がすご過ぎる、_わ、わたしが解ける程の熱が、_や、やめろ-やめてくれぇぇぇぇ-っ!!!」",
    "08A7E=08ADF": "「ムウウウウウウウゥゥゥゥ、ゴ.ル.ドオオオォォォ..._コノママスマセテナルモノカアアアァァ!」",
    "08AE1=08B06": "「ゴ、ゴアアアアアアアァァァァ...」",
    "08B08=08B47": "ドレイク:「おおい、そこの。ちょっとここから出してくれねえかい」",
    "08B49=08BC0": "牢屋の男を助けますか?__________________助けだす。_______________ほっておく。_____",
    "08BC2=08C6F": "ドレイク:「ありがとよ。おれは海賊稼業をしていた[ドレイク]ってんだ。ここのやつらとモメ事を起こしてつかまっちまったのよ。どうせ船も沈んでしまったし、俺も連れて行ってくれや」",
    "08C71=08CA2": "ウォラス:「戰況はどうじゃ、ゆっくりして行かれよ」",
    "08CA4=08D05": "ウォラス:「ついにここまで來おったか!_カ-リオンもバルシアも同じ、力で我らを押さえつけるのみだ」",
    "08D07=08D66": "武將:「どうやらバルシアは新たな人造人間の製造にとりかかった樣子。まだまだ油斷はできませんぞ!」",
    "08D68=08DB1": "兵士:「海の向こうには我らが仲間が住んでいる。いざとなったら海に逃げるさ」",
    "08DB3=08E2C": "兵士:「東のバルシアの台地から、恐ろしい煙があがっているのが見えます。不氣味な音も響いてくる。一■何が行われているのやら」",
    "08E2E=08E93": "兵士:「バルシアの北にあるのがセバ-ト城。城の中には、どこかの砦へ通じる道もある、と言われております」",
    "08E95=08ECA": "兵士:「セバ-ト城は强固な城でなかなか攻められません」",
    "08ECC=08F0F": "兵士:「セバ-ト城に補給をしているのはモロシア城だと言うウワサです」",
    "08F11=08F40": "サグ:「おのれっ!_我らが最期を見るがよい!!」",
    "08F42=08F87": "サグ:「モロシアの守りある限り、バルシアもこの城も決して落ちはせん!」",
    "08F89=08FBE": "サグ:「セバ-ト王たるこのわしが..._む、無念じゃ」",
    "08FC0=0901F": "兵士:「わ-っ、許して下さい。なんでも言います。オルニック砦への瞬間移動口は左の下ですよ-っ!」",
    "09021=0905C": "エレイン:「遲かったじゃない、何をしていたの!_早く中へ!」",
    "0905E=090B9": "エレイン:「アレス、御免なさい、あなたが捕まってしまったと聞いてじっとしていられなかったの。",
    "090BB=09108": "バルシアに來て初めてあなたが脫出した事を知ったのよ。だからここで待っていたの」",
    "0910A=0916D": "エレイン:「この城の地下から[オルニックの砦]の中へ移動できるらしいの、いっしょに行きましょう!!」",
    "0916F=091D6": "カ-ラ:「先生にあいに來たのね。先生、人嫌いだから、會えるかどうかわからないわよ。勝手にさがすといいわ」",
    "091D8=0923B": "カ-ラ:「でも、その前にあなた達の腕前を見せてもらいたいわね。ちょっと、この化物を倒してみなさいよ」",
    "0923D=092C0": "ガラ-ド:「ようやく來たか。ガイア大陸にいるマ-サと言う魔法使いにたのまれて、陰ながらおまえさん達の手助けをするのがわしの役目じゃ」",
    "092C2=09327": "ガラ-ド:「不出來な弟子がおるで連れて行きなさい。實戰で修業をする方がためになるし、わしも樂ができる」",
    "09329=09378": "カ-ラ:「まあ!_先生ったら、どういう事よ。いいわよ、私が力をかしてあげるわ!」",
    "0937A=093C9": "ガラ-ド:「[龍]よ、さあこっちへ來い!_お前にはしばらく消えていてもらおう!」",
    "093CB=09424": "ガラ-ド:「[龍の台地]には、ゼネルが復活させた龍がおる。一匹は、わしにまかせてもらおう」",
    "09426=0943F": "「__...痛いっ!!!」",
    "09441=09452": "「落とし穴だっ!」",
    "09454=094C7": "「私、エレインさんの護衛をしていた者です。なぜかはぐれちまいまして、こんな所に..よければ、ごいっしょさせて下さい」",
    "094C9=09524": "ガラ-ドの聲:「[アレス]はどうした?_妖精王が尻■みしてはならんぞ。ここは開けてやらん!」",
    "09526=0954D": "「卵はなくなった。でもこれでよいのです」",
    "0954F=09580": "「今度生まれ■わる時は、やさしい母から生まれたい」",
    "09582=095AF": "「[川の砦]に弓兵を置けば防衛據点になります」",
    "095B1=095E0": "「もうだめかと思いました。ありがとうございます」",
    "095E2=09619": "「バルシア軍に包圍された時は生きた心地がしませんでした」",
    "0961B=09642": "「ああ、ありがとうごぜえましたあぁぁぁ」",
    "09644=09683": "子供:「ぼく怖くなかったよ。助けに來てくれるってわかってたもん」",
    "09685=096E2": "賢者シモン:「敵はマ-シアの城の周圍に强力な軍を置いています。このまま北へ向かうのは危險です。",
    "096E4=09731": "マルドンの洞窟には行かれましたか?_あそこには、ノ-ムと土の王フレイアがいる。",
    "09733=09774": "妖精達の力をかりれば、ゼネルの人造人間に立ち向かえるかも知れない」",
    "09776=097AD": "町長:「私がいながらこんな事になって申し譯ありません。」",
    "097AF=0980C": "水の王ニミュ-:「私は水の精靈ニミュ-、妖精の女王。このログリスにも災厄の時がやってきました」",
    "0980E=098B1": "ニミュ-:「ガイア大陸での戰いの話しはご存知でしょう。異世界の魔物ガロアは、この土地に再生の場を求め、ゼネルをそそのかし、大きな[熱]を開放しようとしているのです」",
    "098B3=0990E": "ニミュ-:「私達も神の使いとして、ゼネルを倒さねばならないのですが、今はその力がありません。",
    "09910=099B1": "_ゼネルはスリフト、オ-グ、マクガイア、モルドレッドのバルシア四將に、それぞれ_[風]、[水]、[土]、[火]の力を■え、我らが配下の精靈を封じ■めているのです」",
    "099B3=09A32": "ニミュ-:「ノ-ム達が無事なのは幸いでした。バルシア四將から精靈を開放すれば、精靈たちの王はその力を最大限に發揮できるでしょう」",
    "09A34=09A71": "ニミュ-:「私は[再生]の時が近く、あまりお力にはなれません。",
    "09A73=09AFC": "アレス王がやがて私の役目を■ぐでしょうが、その時まで私の力が續くかどうかわかりません。一刻も早く、ログリスをゼネルの手から取り■すのです」",
    "09AFE=09B63": "ニミュ-:「[水の精靈]を開放していただき、感謝いたします。いずれ、おちからになれる時が來るでしょう」",
    "09B65=09B84": "妖精:「ようこそ、妖精の泉へ!」",
    "09B86=09BC1": "妖精:「お疲れですか?_泉の力で、いやして差し上げましょう」",
    "09BC3=09C24": "ドルトン:「わしは土の精靈、ノ-ムの長ドルトンと言う。わしらは、ず-っと昔からこの地に住んでおる。",
    "09C26=09C81": "バルシアのやる事はケンタウロスよりも野■じゃ。やつらは聖なる土を魔物に■えてしまいおった!」",
    "09C83=09CD4": "ドルトン:「フレイア樣の行く所、土の精靈は共にある。勇者に神の惠みのあらん事を!」",
    "09CD6=09D21": "ノ-ム:「ケンタウロスは油斷のならない連中さ。戰いが好きで、亂暴なやつらだ」",
    "09D23=09D56": "ノ-ム:「ヨコシマな心で精靈の力を使ってはならない」",
    "09D58=09DA1": "ノ-ム:「魔法の力で精靈を越えようとするゼネルは、とんでもないヤツですよ」",
    "09DA3=09E2A": "土の王フレイア:「このわしの力をかりたいと言うのはお前たちじゃな?_手をかさんでもないが、妖精の女王[ニミュ-]の許しを得て來るのじゃ」",
    "09E2C=09E97": "妖精王に會いたければ[湖の北]に行き、南の行き止まりをよく調べるのだ。女王のいる所へ通じる道を造っておこう」",
    "09E99=09EE0": "土の王フレイア:「妖精王に會って來たか!_そうか、ならばわしも力をかそう",
    "09EE2=09F17": "いつの日か、この國はアレス王の元に一つになるであろう」",
    "09F19=09F76": "町長:「ご苦勞樣でございます。わたしらが商いできますのも、みんな兵隊さんのおかげでございます。",
    "09F78=09FAF": "およばずながら、できる事ならなんでも協力いたしますです」",
    "09FB1=0A01E": "ロレンス:「私は、大陸で武器鎧のチェ-ン店を■營しております。大陸ではあきたらず、ログリスへもやって來ました。",
    "0A020=0A06B": "すでに仲間は各地に散らばっています。武器屋へ寄られたらよろしくお願いします」",
    "0A06D=0A0B8": "酒場の男:「えらく强そうな騎士がきて、カ-リオンの方向を聞いて行きましたよ。",
    "0A0BA=0A0EF": "何を考えているのか、ルロイの方へ北へ北へと行きました」",
    "0A0F1=0A156": "「よう、兵士を募集しているんだってなあ。命知らずの男が10人。雇ってみねえかい?_200ゴ-ルドだぜ」",
    "0A158=0A1CF": "200ゴ-ルド拂いますか?____________安い!_拂います。___________うさんくさいから止めておく。_",
    "0A1D1=0A21A": "「なに?_いやかい。俺たちの腕を信用しねえなら、敎えてやろうじゃねえか!」",
    "0A21C=0A255": "「いや、命をかけるんだ、もう200ゴ-ルドださねえかい?」",
    "0A257=0A2A6": "「ありがとよ、こいつでまた酒が飮めらあ。もっと持っていそうだな。全部だしなよ!」",
    "0A2A8=0A2EF": "「ありがとよ、人は信用しなくちゃいけねえぜ。俺たちはきっと役に立つぜ!」",
    "0A2F1=0A338": "男:「ここは港町ケント。戰いが始まって以來、外國船がぱったりと來ません」",
    "0A33A=0A3C3": "男:「バルシア王ゼネルの魔法科學は、かなり進んでいます。この國では彼に對抗できるのは、アルカナイヤの魔法城にいる[ガラ-ド]だけでしょう」",
    "0A3C5=0A424": "男:「ログリスの北西にあるミュルトンもここと同じ港町だが、あっちには海のならず者が大勢いるんだ」",
    "0A426=0A47B": "男:「この町の北にあるレスタ-の王は評判が惡いぜ。戰爭を口實に領地を廣げる魂■なんだ」",
    "0A47D=0A4D2": "男:「今までの平和は各國の思惑の上で支えられていた。それが少し傾いただけでこの有樣だ。",
    "0A4D4=0A545": "どの國も自分の事しか考えていない。カ-リオンの王一人が、危險をかえりみずにゼネルに立ち向かったと言うじゃないか!」",
    "0A547=0A5A8": "女:「北東の港町リンカ-は大丈夫かしら?_あそこはヒュリアから自警■を雇っているらしいけど...」",
    "0A5AA=0A5E7": "女:「東の島ハ-ベで人影を見たの。あそこは無人島のはずなのに」",
    "0A5E9=0A660": "女:「レスタ-がエルフの土地を狙うから、エルフ王はバルシアと戰わないのよ。エルフがいればこの町は安心だと思っていたのに」",
    "0A662=0A6BF": "男:「酒場に兵士達がたむろしているぜ。雇主を探しているようだが、酒が入って荒っぽくなっている。",
    "0A6C1=0A6F4": "入るなら覺悟をするか、お金を用意しておいた方がいい」",
    "0A6F6=0A757": "森の王フェンリル:「わしらはアレスの手助けをせねばならんのだが、■調が惡く■が思うように動かせん。",
    "0A759=0A7A8": "フェンリル:「わしの氣に入った者を連れてくれば、魔力のある毛皮をかしてあげよう」",
    "0A7AA=0A7E9": "フェンリル:「むっ!_お前の名は何と言うのだ?_[カ-ル]君か!",
    "0A7EB=0A842": "_...何とかわいい子じゃ!_わしの毛皮[■說の着グルミ]を着てみい。きっと似合うぞ!!",
    "0A844=0A86F": "魔法と同じように、使えば助けが來るじゃろう」",
    "0A871=0A8CC": "ガイグリフ:「我らの力を借りたいのか?_殘念じゃ、若い者は皆、バルシアに洗腦されてしまった。",
    "0A8CE=0A907": "ゼネルの魔力は恐ろしい。彼らはカ-リオンの敵となるだろう」",
    "0A909=0A944": "ガイグリフ:「殘った連中もゴロツキばかりで、わしも頭が痛い」",
    "0A946=0A985": "ケンタウロス:「アレスはゼネルを殺そうとして失敗したそうだな。」",
    "0A987=0A9D6": "ケンタウロス:「俺たちは精靈と違う。アレスにだってこれっぽっちの義理もないんだ」",
    "0A9D8=0AA25": "ケンタウロス:「タダでここを通れると思うなよ。通行料100ゴ-ルドを拂いな!」",
    "0AA27=0AA6C": "ケンタウロス:「俺たちとやり合うつもりか?_いいだろう、覺悟しな!!」",
    "0AA6E=0AAB7": "「道に迷ったのですが、ケンタウロスどもが恐ろしくて、ここから出られません。",
    "0AAB9=0AB16": "えっ!_大丈夫なのですか!_そいつはありがたい!_こんな物でよければ、お■に差し上げましょう」",
    "0AB18=0AB8D": "町長:「正直な所、この國の稅金は高くて困っておりました。カ-リオンが統治していただければ、もっと住みよくなるでしょう」",
    "0AB8F=0ABCE": "男:「大■だな、この世にエルフなんぞがいるから爭いが起こるのだ」",
    "0ABD0=0AC27": "男:「今日この土地の繁榮があるのは我が國のお陰なのだ。エルフは遠慮ってものを知らない!」",
    "0AC29=0AC7C": "男:「エルフだのなんだのは霞でも食ってればいいんだ。人間樣の土地を荒しちゃいけねえ」",
    "0AC7E=0AD0B": "男:「エルフなんかにかまっている場合じゃないんだ!_俺はバルシアの人造人間を見たんだ。あんな恐ろしいものがやってこられたんじゃタマンナイぞ!」",
    "0AD0D=0AD64": "男:「この國の者ときたら、自分の事しか考えていないのです。今度の事はいい反省材料ですよ」",
    "0AD66=0ADA7": "男:「わしは、レスタ-王のやり方は間違ってると思っておったんじゃ」",
    "0ADA9=0AE16": "男:「この北の方にある[サンリスの塔]には古くから[風の王]が住んでいるらしいだ。もちろん見た奴がいないがな」",
    "0AE18=0AE6F": "女:「サンリスの砦には[ワイルド]と言う人がいるの。バルシアに不滿を持っているらしいわ」",
    "0AE71=0AEB8": "町長:「助けを待っていたんですよ。バルシアには散■な目にあわされました」",
    "0AEBA=0AF3F": "男:「北のマ-シアの台地にある城は[■子の城]と呼ばれる强固な城です。近づくからには充分兵士を鍛え上げてからのほうがいいと思いますよ」",
    "0AF41=0AF98": "男:「バルシアの化け物の中には、人を石にしたり、毒をあびせたりするものもいるそうです!」",
    "0AF9A=0B01F": "男:「ここからずっと西の[魔の森]は魔物が澤山います。やつらを動かしているのは、[森の王]だともいいますが、どうなのかはわかりません」",
    "0B021=0B07A": "男:「强い敵を無理に倒そうとすると、消耗が激しいです。動かない部隊をかわす事も作戰ですよ」",
    "0B07C=0B0FF": "男:「コンウォ-ルの砦の中にいる敵將は、バルシアに反感を持っているらしいのです。話し合うなら、押しかけて行ってからでは遲いでしょう」",
    "0B101=0B15E": "男:「バルシアの兵士はいったいナンナンですか?_まるで化物のような連中がいるじゃないですか!」",
    "0B160=0B1D7": "男:「ここから北へ進むのは大■です。バルシアがベニック、マ-シア、ノ-フォ-クを抑え、强力な防衛線を張っているからです」",
    "0B1D9=0B250": "男:「マ-シア城の領主ルシアスは、とても勇敢な人だそうです。ゼネルの將軍にあんな人たちがいるんじゃ、とっても恐ろしい!」",
    "0B252=0B2A3": "男:「エドウィンの城には、秘密の拔け穴があるそうです。どこにあるかはわかりません」",
    "0B2A5=0B306": "女:「うちは女ばかりで、逃げるに逃げられず難義をしておりました。何と言ってお■を言ったらよいやら」",
    "0B308=0B35D": "女:「[ノ-フォ-クの瀧]にはデルスミスと呼ばれる不思議な種族が住んでいるそうですわ」",
    "0B35F=0B3A4": "女:「バルシアの軍にもいい人はいるわ!むやみに殺さないでちょうだい!」",
    "0B3A6=0B433": "町長:「姬樣が出步かれるのはいつもの事ですが、この村においでの後、行方が判らなくなったそうなのです。私の責任問題にもなりますよ、えらい事だ!」",
    "0B435=0B472": "町長:「ありがとうございました!_なんとお■を申したらよいか」",
    "0B474=0B4C9": "町長:「我が國は狹いながら物が豊富、お手■いできる事があれば、なんなりと言って下さい」",
    "0B4CB=0B534": "男:「■山に化物が住みついて仕事ができなくなりました。グレイス王にたのんだのですが、とりあってくれません」",
    "0B536=0B56F": "男:「ありがとうございます。これでまた■山で■けますよ!」",
    "0B571=0B5F4": "男:「ミュルトンに係わっているより、ベニックを始めとする、バルシアの動向に注意しなければならないのに、王の考えはわしらにはわからん」",
    "0B5F6=0B635": "男:「ベニックの王は惡魔を呼出したと言う■がある。本■だろうか」",
    "0B637=0B686": "兵士:「ベニック城の王は、魔法の力によってリザ-ドマンを從わせているらしいです」",
    "0B688=0B6E1": "男:「グレイスの王女樣は皆美人ぞろい。王女樣のためならば、どんな苦勞もたえてみせますゥ!」",
    "0B6E3=0B72C": "男:「えらい事です!_我が國の王女樣が、行方不明になってしまったのです!」",
    "0B72E=0B78F": "男:「ああ、姬樣!_バルシアに捕らえられたやら、ミュルトンに捕まったやら、一■どうなされたのか!」",
    "0B791=0B7BE": "男:「まさか、お姬樣があの坑道にいようとは!」",
    "0B7C0=0B7F5": "男:「姬樣をお助けいただき、ありがとうございました!」",
    "0B7F7=0B82C": "男:「ここが坑道の入口です。崩れて奧まで行けませんよ」",
    "0B82E=0B85F": "女:「お願いします。王女樣を助けてあげて下さい!」",
    "0B861=0B8AE": "女:「王女樣を助けていただいたそうですね。ウチの男どもとちがって賴もしいわ!」",
    "0B8B0=0B911": "女:「ベニックにトカゲ男が澤山いるのよ!_ゼネルが大陸から連れてきたって■だけど、氣持ち惡いわあ」",
    "0B913=0B970": "妖精:「勇者よ。あなたにこの劍をさずけましょう。一刻も早く、ログリスに平和を取り■して下さい」",
    "0B972=0B9CD": "長老:「我らはこの地に古くよりありて、今は靜かに滅び行く種族。ただ神の聲を聞き、日■を送る。",
    "0B9CF=0BA34": "なんじらが、我が助けを求めに來るのわかっていた。しかし、神は何もおっしゃらない。殘念だがお引取願おう」",
    "0BA36=0BA57": "長老:「神のご加護のあらんことを」",
    "0BA59=0BAA4": "デルスミス:「まったく、[腹話術]も使わん事には腰をあげないんだから...」",
    "0BAA6=0BB1F": "どこからかの聲:「デルスミスよ。お前たちは、カ-リオンと共にあれ。バルシアを倒すため、最期の力をログリスにささげよ...」",
    "0BB21=0BB72": "長老:「おお、ついに神は我らに道をお示しになった!_我らも共に戰う時が來たのだ!」",
    "0BB74=0BBDB": "デルスミス:「私たちは、あなた方とは[造られ方]が違うため、あなた方の魔法の影響はあまり受けないのです」",
    "0BBDD=0BC3E": "デルスミス:「私たちの最高の劍は、ある者に委ねてあります。それを使う者には神の祝福があるでしょう」",
    "0BC40=0BC85": "リ-ダ-:「おお、長老の許可が得られたか、しからば、我らも共に戰おう」",
    "0BC87=0BCD6": "リ-ダ-:「我らもあなた方に手をかしたいのだが、奧にいる長老の許可が必要なのだ」",
    "0BCD8=0BD29": "デルスミス:「ここの押しボタンで、水の流れを■える事ができます。試してみて下さい」",
    "0BD2B=0BD96": "デルスミス:「リスレイ城は攻める事がむずかしい。ベルダ城、マ-シア城を完全に落とせば城主はきっとネをあげる。",
    "0BD98=0BDE5": "しかし、リスレイ城には土の魔物が、ベルダ城には火の魔物がいる。氣をつけなされ」",
    "0BDE7=0BE30": "町長:「遠い所をようこそ。山國で大した物はありませんが、協力させて下さい」",
    "0BE32=0BE9F": "男:「誰もがこのウェルズの町をほしがっている。戰いが始まれば、どこかの國に屬さなければならないのは仕方がない」",
    "0BEA1=0BEC4": "男:「俺たちは政治には感心はないね」",
    "0BEC6=0BF21": "男:「バルシアのゼネルが、殺人人形を造ったって本■ですか?_あいつは狂った魔法使いですよ!」",
    "0BF23=0BF80": "男:「海賊はいやだね。戰爭のどさくさでこの町をとろうとしているんだ。グレイスの方がまだましさ」",
    "0BF82=0BFFB": "「ベルダの城はなかなか强固じゃ。3つの砦には[火の魔物]を呼ぶ騎士がひかえておる。しかも、城には强い魔法使いがいると聞く」",
    "0BFFD=0C034": "女:「ミュルトンの海賊にだけはこの町に來てほしくないわ」",
    "0C036=0C06F": "女:「こんな山奧にまで軍隊が來るなんて、大■な戰爭なのね」",
    "0C071=0C0B0": "女:「ここは[ウェルズの町]。山から木を切出して生活しているの」",
    "0C0B2=0C0CB": "「ヒヨコは全部賣切れだよ」",
    "0C0CD=0C102": "「每度!_連れて行ってやりなよ。置いて行かないでくれ」",
    "0C104=0C1A3": "町長:「我が國の王ライオス樣は立派な方。いつもわしらの事を思って下さる。今度の戰爭の事だって、バルシアから大きな援助があるので、ゼネル樣のお味方をされたのです」",
    "0C1A5=0C1DE": "男:「ライオス王はどうなさった?_生きておられるのか??」",
    "0C1E0=0C23B": "男:「本來、ライオス王はこの戰いには贊成されなかった。カ-リオンの王もそれはご存じのはずだ」",
    "0C23D=0C26A": "男:「ああ、リスレイはこれからどうなるのだ!」",
    "0C26C=0C2AD": "男:「グレイスと違って、同じ山國でもここには何もありませんのです」",
    "0C2AF=0C2F6": "女:「この國は貧しい國。何とかやっていかれるのはライオス王のおかげです」",
    "0C2F8=0C34B": "女:「まあ!_異國の兵隊さんが來るなんて、リスレイのお城はどうなったのでしょう!?」",
    "0C34D=0C388": "女:「あなた方は何?_ここには盜るものなどありませんわよ!」",
    "0C38A=0C3E5": "ゴライアン:「わしらはわしらの神のいいつけ守るゴブ。わしらの神、あんたらと戰えと言ったゴブ。",
    "0C3E7=0C446": "だから戰った。だが、あんたら强かった。强い者と戰ってはいかんと神が言った。わしら戰いやめたゴブ」",
    "0C448=0C499": "ゴライアン:「わしらの神、[世界征服]が目的。いずれの日にか[世界征服]するゴブ」",
    "0C49B=0C4BE": "ゴブリン:「他所者は歸れ、ゴブッ!」",
    "0C4C0=0C4D9": "ゴブリン:「ゴブゴブッ!」",
    "0C4DB=0C54C": "町長:「よくぞ來てくれた!_だが、殘念だが、戰いのため町には金がなくなってしまった。今は、たたいても鼻血も出ない」",
    "0C54E=0C585": "男:「我が町の城壁は簡單に破られるものではありませんぞ」",
    "0C587=0C5E4": "男:「ゴブリンなんかほっておけばいいんですよ。どうせ、自分の穴からそう離れる事もないでしょう」",
    "0C5E6=0C647": "「この町の人間は皆、やることがセコイんじゃ。せっかく助けに來たのに、町長は■をする氣もないらしい。",
    "0C649=0C682": "なんの、金はどこかに隱してある。見つけてもって行きなされ」",
    "0C684=0C6AB": "「それからなゼムには安易に行くでないぞ」",
    "0C6AD=0C6EE": "女:「この町の男達は腰拔けぞろいよ。自警■だってあてにならないわ」",
    "0C6F0=0C73F": "女:「ゼムはゴブリンの巢よ。一匹見たら、百匹いるって話よ。わきだして來るのよね」",
    "0C741=0C7CC": "町長:「わしらはミュルトンに稅を納めておるが、なあに、國が■ろうが王が■ろうが、稅さえ納めりゃしっかり保護はしてもらえる、そうでしょうな?」",
    "0C7CE=0C83B": "男:「この國の東の山には[魔法城]と言うのがあって、偉い魔法使いが住んでいるってそうだい。行ってみりゃいいや」",
    "0C83D=0C8B2": "男:「[魔法城]の魔法使いが動けば、ゼネルの橫暴にも少しは齒止めが利いたはずだが、あの魔法使いは[世間が嫌い]らしい」",
    "0C8B4=0C8FF": "男:「おおよ、俺っちは誰の味方もしたかないけどよ、曲った事はキレエなんだよ」",
    "0C901=0C94E": "男:「俺たちは氣が短けえんだ。バルシアだろうがなんだろうが、來たら逃げるぜ!」",
    "0C950=0C9C7": "男:「グレイスの連中ときたら、さんざんモノを一人占めしやがってよ。おまけにこの土地まで狙っているんだから、欲がフケエよ」",
    "0C9C9=0CA56": "女:「東の山奧には[アルカナイヤ]と言う國があると聞きます。何でも、翼の生えた人間が住んでいるらしいのですが、そんなのは信じられませんわねえ」",
    "0CA58=0CAD7": "女:「わたしら、海から來てここに住みついた。回りのモンは[海賊]だなんて言うけどね、みんな同じ事をやっているんじゃないのかい?」",
    "0CAD9=0CB52": "女:「あたいたち、自分の身は自分で守るって事ぐらい知ってんのさ。世話やきたいなら、グレイスの心配でもしてやったらどうだい」",
    "0CB54=0CB8D": "村長:「遠路遙■ご苦勞樣ですが、ここには何もありませんよ」",
    "0CB8F=0CBBE": "男:「あれま-、こんな田舍までよく來ただな-!」",
    "0CBC0=0CBFB": "男:「漁をしているとたまにめずらしい物が上がる事があるだよ」",
    "0CBFD=0CC46": "男:「おらこの前、デカイ物を釣り上げちまった。うちのカミサンが持っとるだ」",
    "0CC48=0CC8B": "女:「ここは[レフトの漁村]。船で向こうに渡れば[ライトの村]だよ」",
    "0CC8D=0CCB0": "女:「こんな小さな村までようこそ!」",
    "0CCB2=0CD05": "女:「うちの人が釣った物をみてくんろ!_デカイだろ!_よかったら持って行って下せえ」",
    "0CD07=0CD4C": "村長:「せっかくおいでいただいても、この村には差上げる物はないのです」",
    "0CD4E=0CD8D": "男:「今、船は向こう岸の村に行ったままだ。渡る事は出來ねえだね」",
    "0CD8F=0CDD8": "男:「こんな田舍にまで軍隊が來るとは、えらい戰爭がおっぱじまったモンだ!」",
    "0CDDA=0CE11": "男:「この村は戰爭にゃ關係ねえだ。そっとしといてくれろ」",
    "0CE13=0CE56": "女:「ここは[ライトの漁村]ですわ。ここには魚以外何もないですのよ」",
    "0CE58=0CEBD": "女:「この入り江を船で渡った所が[レフトの村]。ここと同じ漁村です。その北にはグレイスの國があります」",
    "0CEBF=0CEE2": "「物騷で、外にはあまり出られないの」",
    "0CEE4=0CF0D": "「ぼくね、小さいけれど、一應ドラゴンなの」",
    "0CF0F=0CF7C": "「ぼくね、强くなるために[シュギョウ]しているの。バルシアの王樣って惡い奴なんだってね。ぼくも手■ってやるよ」",
    "0CF7E=0CFEF": "ユリア:「私はアマゾネスの戰士[ユリア]。[神託]に從い、ログリスのゼネルを倒すために、仲間とともにやって來たの。",
    "0CFF1=0D022": "しかし、嵐にあって私一人がこの島に流れついたのよ」",
    "0D024=0D085": "ユリア:「あなた方がゼネルと戰っているのですって!?_これぞ神の引合せね。私もいっしょに行くわ!」",
    "0D087=0D0DA": "ユリア:「ここには、海賊の隱した■があるけど、奧には■な怪物がいるの。氣をつけてね」",
    "0D0DC=0D121": "ガイコツ:「おおおぉ、もう少しで完全に消化されちまう所だったあああぁぁ",
    "0D123=0D170": "たのむぅ、おれも連れて行ってくれえぇ、一人にしないでぇ、おねがいぃぃぃ...」",
    "0D172=0D1B1": "男:「島に渡りたいのか?_金を拂うならこのイカダに乘せてやるぜ」",
    "0D1B3=0D22A": "500ゴ-ルド拂って乘せてもらいますか___________高いけど拂う______________乘らない______",
    "0D22C=0D24F": "「歸るのかい?_イカダを出そうか?」",
    "0D251=0D26A": "男:「氣をつけて行きなよ」",
    "0D26C=0D2AF": "男:「こんな粗末なイカダしかないが、向こうに渡るなら、乘せてやるぜ」",
    "0D2B1=0D328": "イカダに乘りますか?____________________乘る。_________________今はやめる。____",
    "0D32A=0D371": "母:「この子は■った子で、小さい時から兵隊さんにあこがれていたんですよ」",
    "0D373=0D3EC": "カ-ル:「戰爭が始まったんでしょう?_僕も連れて行ってよ!_僕ね、自分でバトルス-ツを作ったんだけど、實戰で役立てたいの」",
    "0D3EE=0D417": "「バトルス-ツって、その[パンダ]の事?」",
    "0D419=0D4B6": "カ-ル:「そうだよ、かっこいいでしょう。趣味でこんなバトルス-ツを作っている人が他にもいるし、■では[■說の着グルミ]ってのがあるらしいの。それも探すんだ!」",
    "0D4B8=0D4F1": "母:「カ-ルがご迷惑をかけてなければよいのですけど...」",
    "0D4F3=0D52C": "「やあ、同じ趣味の人がいる!_この着グルミも使ってくれ!」",
    "0D52E=0D591": "ロビン:「俺たちのアジトに乘■んで來ようとはいい度胸だ。だが、あいさつに來るなら、一人で來るんだな」",
    "0D593=0D5F6": "ロビン:「もし、お前が俺に勝てば、俺たちもお前たちに協力してやろうじゃないか。さあ、かかって來な!」",
    "0D5F8=0D62B": "「まだまだだな。殺しはしないから、とっとと歸りな!」",
    "0D62D=0D696": "ロビン:「ててっ!_なかなかやるな。あんた達なら少しは見■みがあるってもんだ。俺たちにも協力させてくれ!」",
    "0D698=0D6D7": "ウイリアム:「なんだい、今のが本氣かね?_手を拔いちゃいかんな」",
    "0D6D9=0D760": "「初めっからカ-リオンに手をかしたいなら、面倒な事は止める事じゃが、なめられても困る。ビッグ.ベン!_わしらの實力を見せてやるがええ!」",
    "0D762=0D7AB": "ビッグ.ベン:「オレ戰いたくない。けどあんたが戰いたいのなら戰ってもいい」",
    "0D7AD=0D824": "ビッグ.ベンと戰いますか?____________怖いから止めておく。__________戰おうって言うのなら戰う。__",
    "0D826=0D88F": "ロビン:「どっちみち、俺たちはあんた達に協力するつもりさ。バルシアのやつらに俺たちの怖さを見せてやるぜ!」",
    "0D891=0D914": "シェイキイ:「わらわは[きとう]をよくする者なり。[卦]によれば、大いなる災い大陸より來たりて、ログリスの奧深くにひそめり、とある。",
    "0D916=0D991": "また、この國を救うる者、妖精と共にあり、と。わたしはまだ未熟の者なれど、なんじらの一助とならん。どこへでも連れて行くがよい」",
    "0D993=0D9D6": "アルシンプ:「いやはや、やつらに捕まり、こんな所に隱れておりました。",
    "0D9D8=0DA29": "わたしは神の下部、まだ修業の身ですが少しの傷なら治す事ができます。これは私の息子」",
    "0DA2B=0DA58": "シンプソン:「私たちも、ぜひお役立て下さい!」",
    "0DA5A=0DADB": "看護婦:「戰場で傷ついた人をいやすのが私の使命と思っております。できれば私もごいっしょさせて下さい。私の名はクリスティといいます」",
    "0DADD=0DB44": "兵士:「私はクリスティの看護のおかげで命をすくわれました。彼女を牢屋に入れるだなんて、できるわけがない!",
    "0DB46=0DBA7": "この國の王を殺したのも、バルシアの仕業だ。そこのレバ-を動かせば、離れた部屋の扉が開くはずです!」",
    "0DBA9=0DC14": "アポロン:「わたしは歌の力で人■を勇氣づけ、はげます事を仕事にしております。わたしもお役に立てれば幸いです」",
    "0DC16=0DC59": "ギルフォ-ド:「ちょっと聞きたいのだが、カ-リオンの城はどちらだ?」",
    "0DC5B=0DC94": "ギルフォ-ド:「そうか、では、一眠りしてから行くとしよう」",
    "0DC96=0DCC1": "ギルフォ-ド:「おお!_父上、おなつかしい」",
    "0DCC3=0DD38": "ラルフ:「大馬鹿者!_いままで何をしていたのだ!_ネボケているとしょうちせんぞ!_早く、カ-リオンの部隊に合流しろ!」",
    "0DD3A=0DD71": "ギルフォ-ド:「アレスじゃないか。こんな所で會うとは!」",
    "0DD73=0DE00": "アレス:「どこをさまよっているのかと心配したよ!_戰場で寢ていられるのは君だけだから、大丈夫とは思ったけれどね。しかし、君がいれば百人力だ!」",
    "0DE02=0DE61": "ギルフォ-ド:「何の、一騎■千と言ってもらいたいね。まかしてくれ、强いヤツはオレが引き受けるぜ」",
    "0DE63=0DEB4": "トリスラム:「ラルフ殿のご依賴により、フランクよりまいった。領主トリスラムと申す。",
    "0DEB6=0DF17": "途中、いざこざがあり、152人程切り捨ててまいったので遲くなった。以後よろしくおつきあい願いたい」",
    "0DF19=0DF46": "「おお、助けに來てくれたのか!_ありがたい!」",
    "0DF48=0DFC1": "「我らは、諸國行脚修業の騎士にてござる。カ-リオンのお力添えになればと思い參上した次第。ぜひ、お仲間に加えてもらいたい!」",
    "0DFC3=0E03E": "バツ:「[トニ-]は普段はトロクて、役に立たないと言われるのだが、逆上すると見境がなくなるのです。まあ、勘弁してもらいたい」",
    "0E040=0E08F": "ケイシ-:「いけね!_見られちまったか?_へへ、俺はどうも性分で手癖が惡いんだ。",
    "0E091=0E106": "えっ?_あんたちはこの家の人間じゃねえのか?_[軍]の連中か!_どうだ、俺を雇ってみねえか?_役に立つかもしれねえぜ」",
    "0E108=0E15B": "男:「かわいいヒヨコはいらんかね?_こいつが最後のイッピキだ!_可愛がっておくれよ」",
    "0E15D=0E1D4": "買いますか?________________100ゴ-ルドで買う。_________どうせロクなもんじゃない。買わない。",
    "0E1D6=0E1E1": "「ピヨッ!」",
    "0E1E3=0E1FA": "「ぴぴ、ぴぐしゅん..」",
    "0E1FC=0E265": "エスカル:「おお、あたなこそ■說の勇者!_長い事待っておりました。ぜひ、あなたの元で修業をさせて下さい!」",
    "0E267=0E29C": "「わたしで良ければ、どうかお役に立てていただきたい!」",
    "0E29E=0E2F3": "役人:「兵士の補充をしたいのならどうぞ。兵舍に20人以上の人がいると補充できませんよ」",
    "0E2F5=0E342": "武器屋:「クラスチェンジはここでできます。武裝を■えるのでお金がかかりますよ」",
    "0E344=0E373": "酒場の主人:「うちの酒はうまいよ。飮んで行きな」",
    "0E375=0E39E": "宿屋:「うちに泊まれば、疲れがとれますよ」",
    "0E3A0=0E417": "500GOLDです__________________疲れているので泊まる。_________高いからやめる。_____",
    "0E419=0E42C": "「お金がたりません」",
    "0E42E=0E463": "道具屋:「アイテムがご入用ですか?_見てって下さい!」",
    "0E465=0E498": "買取屋:「余った道具は無いかい?_いい値で買うよ!」",
    "0E49A=0E4D5": "魔法屋:「魔法を使える能力のある人に、魔法をおゆずりします」",
    "0E4D7=0E524": "魔法屋:「兵士に魔法をおかけします。四元素に對する强さを上げて差上げましょう」",
    "0E526=0E571": "馬番:「馬は[矢]に弱いです。弓兵の多い戰場では馬から降りた方がいいですよ」",
    "0E573=0E59E": "馬小屋主人:「いい馬がいるよ。でも高いよ!」",
    "0E5A0=0E5DD": "鑑定師:「持ち物の■果をお知りになりたければ■見させて下さい」",
    "0E5DF=0E650": "馬小屋主人:「うちには神馬アルケイオンがいるんだ。ある身なりをした人に渡すように、旅の老人からたのまれているんだ」",
    "0E652=0E6B7": "馬小屋主人:「あんた方の中にはいないね。まあ、[■說の勇者]でなくても、立派なナイトなら馬を賣るよ!」",
    "0E6B9=0E718": "馬小屋主人:「おお、その身なりは!_あなたこそ[神馬]に乘るにふさわしい!_ぜひ買って下さい!」",
    "0E71A=0E759": "「あなた方ならログリスをまとめられるでしょう。そんな氣がします」",
    "0E75B=0E770": "「どうぞお氣をつけて」",
    "0E772=0E797": "「この地に平和の■る日を待ち望みます」",
    "0E799=0E7B4": "「いつかは勝利の日が來ます」",
    "0E7B6=0E7E5": "「カ-リオンは、妖精も味方をしているそうですね」",
    "0E7E7=0E822": "「バルシアに踏みにじられたこの地に平和を取り■して下さい!」",
    "0E824=0E853": "「勇者よ、なんじらに神のご加護のあらんことを!」",
    "0E855=0E88C": "「ありがとうございます!_逃げる準備をしていた所ですよ」",
    "0E88E=0E8A9": "「ご武運をお祈りいたします」",
    "0E8AB=0E8C0": "「お役目ご苦勞樣です」",
    "0E8C2=0E8E7": "「なあに、誰が國をおさめようが同じだ」",
    "0E8E9=0E93A": "「バルシアの砦にはまだ多くの兵が殘っています。數を集めてあたった方が良いでしょう」",
    "0E93C=0E96F": "女:「わたしの願いは早く平和になってほしってだけよ」",
    "0E971=0E990": "兵士:「カ-リオンに榮光あれ!」",
    "0E992=0E9B9": "兵士:「前線の樣子はいかがでしょうか?」",
    "0E9BB=0E9EC": "兵士:「助かった!_共に戰っていただけるのですね」",
    "0E9EE=0EA05": "兵士:「王はこちらです」",
    "0EA07=0EA22": "兵士:「ここは通せません!」",
    "0EA24=0EA4F": "武將:「あなた方と共に戰えるとは光榮です!」",
    "0EA51=0EA84": "兵士:「王に會わせる事はできん!_歸ってもらいたい」",
    "0EA86=0EA97": "「ウ-ン、眠い-」",
    "0EA99=0EACE": "「..なンら、と、_せんソ-ら、と、オラしらんぞ、と」",
    "0EAD0=0EAF7": "「飮んで醉って全てを、忘れましょ-っ!」",
    "0EAF9=0EB34": "「今この町ではこの位いのお金しか出せませんが、お納め下さい」",
    "0EB36=0EB6F": "「戰況は予斷を許さないものがあります。どうかお氣をつけて」",
    "0EB71=0EBC2": "「我が家にはろくなものはありませんが、こんなものでよかったら、どうぞお持ち下さい」",
    "0EBC4=0EBE3": "「ど-お、この服。かっこいい?」",
    "0EBE5=0EC24": "「やあ!_君は同じ趣味の人!_これと同じのでよければあげるよ!」",
    "0EC26=0EC57": "「これを、差上げます。どうか命ばかりはご勘弁を!」",
    "0EC59=0EC80": "「よろしければこれを持って行って下さい」",
    "0EC82=0ECA9": "カ-ル:「わ-い!_もらっちゃったぁ-」",
    "0ECAB=0ECD0": "「カ-リオンの戰士よ、武運を祈るぞ!」",
    "0ECD2=0ECFD": "「あなた方を通す事はできない。お返り願おう」",
    "0ECFF=0ED50": "「ここを通すわけにはいかん。戰う事も命ぜられていない。あきらめて返るがよかろう!」",
    "0ED52=0ED8F": "「いきなり兵を進めて來るとは!_我らの國を敵にするつもりか!」",
    "0ED91=0EE08": "相手の國を敵に回しますか?____________いいえ、引き下がります。________どんな國だろうがつぶす!!__",
    "0EE0A=0EE41": "「我らと戰うつもりか?_ここを通りたくば、相手になろう」",
    "0EE43=0EEBA": "相手の部隊と戰いますか?_____________引き下がる。______________邪魔は許さない。戰いあるのみ!",
    "0EEBC=0EF33": "仲間にしますか?_________________仲間にする。______________いらない。お引き取り願う。__",
    "0EF35=0EFAC": "1000ゴ-ルド拂いますか?___________拂います。_______________冗談じゃない。絶對拂わない。_",
    "0EFAE=0EFD3": "「我らと同盟を結ぼうと言われるのか?」",
    "0EFD5=0F04C": "相手の國と手を結びますか?________________手を結ぶ。_______________もう一度考えなおす。_",
    "0F04E=0F091": "「わざわざ、おいで頂いたが、今はお話する事はない。お引取り願いたい」",
    "0F093=0F0D0": "「この情勢では、カ-リオンと手を結ぶしかないと思っていた所だ」",
    "0F0D2=0F107": "「あなたの協力依賴を斷るわけにはいかない。手を結ぼう」",
    "0F109=0F14C": "「いきなり軍を乘■ませて來るとは、不■きな!_話す事など何もない!」",
    "0F14E=0F1A7": "「カ-リオンに我が部隊をあずけよう。殘りの部隊は引き上げさせる。存分に使ってもらいたい!」",
    "0F1A9=0F1D8": "「用があるなら、ミュルトンに使者をたてるんだな」",
    "0F1DA=0F229": "「この國に、バルシアの脅威は迫っておらん。セバ-ト城が兵をあげでもすれば別だが」",
    "0F22B=0F262": "「何をあわてておられるか。あせらず、またおいで頂きたい」",
    "0F264=0F2AF": "「お話があるなら、ノ-フォ-クのブタどもを片付けてから、おいでいただきたい」",
    "0F2B1=0F2F0": "「いきなり軍を乘■ませて來るとは、不■きな!_話す事などない!」",
    "0F2F2=0F305": "「話す事などない!」",
    "0F307=0F32E": "「人數が一杯だよ。減らしてから來てくれ」",
    "0F330=0F34D": "「あんた、お金が足らないよ!」",
    "0F34F=0F368": "「わかった。さよならだよ」",
    "0F36A=0F385": "_____[仲間がふえた!]",
    "0F387=0F3A8": "「いい度胸だ、相手になってやる!」",
    "0F3AA=0F3D1": "「無■だ!_この城には入れない!_歸れ」",
    "0F3D3=0F418": "兵士:「申上げます!_ただ今、カ-リオンの王より、使者がまいりました」",
    "0F41A=0F441": "「ビッグ.ベ-ン!!_助けてくれ-っ!」",
    "0F443=0F466": "「おお、神よ!_我らに救いの手を!」",
    "0F468=0F485": "「ピ-ピピピピ、ピヨピヨッ!」",
    "0F487=0F4AC": "「トニ-ッ!!_やばい事になったあ!」",
    "0F4AE=0F4D5": "「助けてくれ、國をやる。助けてくれぇ!」",
    "0F4D7=0F4F2": "_____敵が仲間になった!",
    "0F4F4=0F515": "「なんの、我らは最後まで戰うぞ!」",
    "0F517=0F538": "「ひるむな!_皆、突擊するぞ!!」",
    "0F53A=0F55D": "「よくも隊長をっ!_カタキは擊つ!」",
    "0F55F=0F584": "「隊長がやられた!_皆、逃げるぞ-!」",
    "0F586=0F5AB": "「引け!_引けぇ-!_退却しろっ!!」",
    "0F5AD=0F5C8": "____レスタ-城を落とした",
    "0F5CA=0F5E7": "____エドウイン城を落とした",
    "0F5E9=0F606": "_____グレイス城を落とした",
    "0F608=0F625": "_____ベニック城を落とした",
    "0F627=0F644": "____西マ-シア城を落とした",
    "0F646=0F663": "____東マ-シア城を落とした",
    "0F665=0F684": "____ノ-フォ-ク城を落とした",
    "0F686=0F6A3": "_____ヒュリア城を落とした",
    "0F6A5=0F6C2": "_____リスレイ城を落とした",
    "0F6C4=0F6DF": "_____ベルダ城を落とした",
    "0F6E1=0F700": "____アルカナイヤ城を落とした",
    "0F702=0F71F": "_____ミュルトンを落とした",
    "0F721=0F73E": "_____セバ-ト城を落とした",
    "0F740=0F75B": "_____サネットを落とした",
    "0F75D=0F77A": "_____モロシア城を落とした",
    "0F77C=0F795": "_______鎖を外した!",
    "0F797=0F7B0": "______材木を押した!",
    "0F7B2=0F7CD": "_____スイッチを押した!",
    "0F7CF=0F80C": "ルシアス:「この地を支配したつもりかアレス?_まだまだだぞ!」",
    "0F80E=0F84B": "ガ-ビン:「ルシアス!_もう戰いは終わったのだ。劍を納めよ!」",
    "0F84D=0F87A": "ルシアス:「ガ-ビン!_生きておったか裏切者!",
    "0F87C=0F8BD": "...いまさら貴樣を成敗しても劍のけがれ。生き恥をさらすがよいわ!",
    "0F8BF=0F914": "ルシアス:「アレス、わしは貴樣を許さん。いつか貴樣を倒す!_その日までわしは死なん!」",
    "0F916=0F92D": "________谷間の道",
    "0F92F=0F968": "オラシラン:「誰が天下をとろうが、やっぱり平和がいいわい」",
    "0F96A=0F9B3": "オラシラン:「...と言えるわけもない。ま、どうなろうと知らんわい...」",
    "0F9B5=0F9E2": "オラシラン:「えっ!_早く城から出て行けとな?",
    "0F9E4=0FA41": "ノ-フォ-ク領主のこのわしに城を出ろとは、何事か!_アレスはもっと痛い目にあいたいようだな!」",
    "0FA43=0FA68": "「殿、ついに、バルシアが落ちました!」",
    "0FA6A=0FAC7": "「そうだろうな。アレス王は人間の王にして精靈の王。今のログリスをまとめられるのは彼しかいまい」",
    "0FAC9=0FB18": "「ええ、ついては、この領地はエルフに明渡すようにとの命令が出ておりますが...」",
    "0FB1A=0FB67": "「そうだろうな。敗戰の將、いさぎよく去らねばならん。なんと、非情な世の中よ!」",
    "0FB69=0FBA2": "「バルシアから妖氣が去った..._皆の衆、戰いは終わった」",
    "0FBA4=0FC0D": "「そうだろうか?_大陸から來た魔物は姿を消したようだが、完全に消滅したとも思えん。いつ復活するやら...」",
    "0FC0F=0FC4A": "「神■は異界におもむき、その根源を斷ち切ろうとしておられる。",
    "0FC4C=0FCA7": "それがうまく行かなければ、たとえ、あれが滅びても、いつ第二、第三の魔物が現れんとも限らん!」",
    "0FCA9=0FD4A": "「アレス王健在のうちは大丈夫じゃ。が、わしの[卦]によれば、いずれこの地はまたばらばらになる。眞の平和はまだまだ先、そう、人間の女王が誕生するまで待たねばならん」",
    "0FD4C=0FD8B": "「いずれ人■の心の隙間に魔が入りこむ。その時のために備えねばな」",
    "0FD8D=0FDB2": "「見張りは眠らせました。さあ、早く!」",
    "0FDB4=0FDDF": "「ここは、魔物の氣配がする!_■りましょう」",
    "0FDE1=0FE06": "「こんな所でぐずぐずしていられないわ」",
    "0FE08=0FE25": "「中の樣子を見てまいります!」",
    "0FE27=0FE46": "「皆、ブタのように寢ている樣子」",
    "0FE48=0FE7D": "「オ-クなんかにかまっていられない。皆!_行くわよ!」",
    "0FE7F=0FE8C": "「待て、女!」",
    "0FE8E=0FEB5": "「人數が一杯なのでベルダ城兵舍にいます」",
    "0FEB7=0FED2": "______味方が混亂した!",
    "0FED4=0FEF1": "_____混亂から立ち直った!",
    "0FEF3=0FF1A": "_水底に穴が見える。ここからは潛れない_",
    "0FF1C=0FF41": "「おのれ!_我らの最期を見よっ!!!」",
    "0FF43=0FF62": "____鎖がなかなかはずれない!",
    "0FF64=0FF81": "____中からしめられている!",
    "0FF83=0FFA8": "「人數が一杯なので部隊に入れません!」",
    "0FFAA=0FFBF": "______開きません",
    "0FFC1=0FFD4": "「何も入っていない」"
}