{
    "0x7=0x1c": "лвлєл╕лзлъ-л╩кЄ╙юк╗!",
    "0x2a=0x49": "к╔к│к└?бдбдбдк╔к│к╦кдкыкєк└!?",
    "0x4b=0x58": "лилъл╖лв!!б╣",
    "0x6a=0x7f": "бдбдбдбдл░льлдбдбдбдб╣",
    "0x8d=0xac": "квк╬бдбдбд█·к╬·╛к│кжклкщ┌дк│кик╞",
    "0xae=0xbd": "кпкы!!бдбдбдб╣",
    "0xcb=0xd8": "лилъл╖лв!!б╣",
    "0xf3=0x112": "бдбдбдл░льлдбдбдбдЁ╛к▒к╞бдбдбдб╣",
    "0x11b=0x150": "к╜к│кл?к╜к╬ёщк╦кдкык╬клбвлилъл╖лвбдбдлилъл╖лв-!!б╣",
    "0x159=0x18c": "бдбды╢юц╥о▌╗с▀╬╒бдЎ╒ь¤э║кЄ№мьубг█╔Ё╢Єж╓╡бдбдк╣к┘к╞к╬",
    "0x18e=0x1ad": "с·√▐Ї╕▐┼кЄЇ╕═гк╬┌жк╦яосъбдбдбдб╣",
    "0x1c7=0x1e8": "квкьк╧!?бдбдбдквкькмбвс·√▐Ї╕▐┼бв",
    "0x1eb=0x200": "лвлєл╕лзлъ-л╩бдбдбдб╣",
    "0x208=0x227": "к╩кєк╞бвк╨клк╟клкдкєк└бдбдбд!!",
    "0x22a=0x23f": "ун▌╢к╦к╩кщк═кибдбдбдб╣",
    "0x248=0x25b": "бдбдбдкдкфбв·╝кпк╡б╣",
    "0x264=0x26f": "л░льлд!?б╣",
    "0x277=0x296": "бдбдбдквкдк─к╧бвлилъл╖лвк╧ї╠¤нк╦",
    "0x298=0x2b7": "б║Ё╛к▒к╞б╗к├к╞хык├к┐бгк└клкщбдбд",
    "0x2ba=0x2d3": "хякмбвя╛╙▀к╦Ё╛к▒к╞кфкы!б╣",
    "0x2db=0x2fa": "бдбдбдкфк├к╤к╜кжк└кшк╩!к│к╬к▐к▐",
    "0x2fc=0x31b": "л╖л├л▌╧щкпкшкжк╕кубвхяк┐к┴кщк╖кп",
    "0x31e=0x329": "к═кик╖к╩!б╣",
    "0x331=0x350": "лклдлщкт·╝кплщлъ!бдбдбдлдл╟лв!",
    "0x352=0x371": "бдбдбдк╔кжк╖к╞ктл└лск├к╞кдкжкєк╩",
    "0x374=0x38d": "кщбв▐╫к╞к┴к▐кжлщлък╛!!б╣",
    "0x395=0x3b4": "к╒кє!ф▓кщк╧ктк╧кфьщуєьщбсбгк╔кж",
    "0x3b6=0x3d7": "квкэкжк╚▄мкьк╧к╗кєбдбдбдкфкькфкьбв",
    "0x3d9=0x3f8": "кфк├клкдк╩э║кЄщ╕э║к╦р╘кєк╟к╖к▐к├",
    "0x3fb=0x406": "к┐кшкжк└к╩б╣",
    "0x40e=0x42d": "кшк╖!!·╝кпк╛!лилъл╖лвкЄбвЎвкъ",
    "0x430=0x43b": "бск╖к╦!!б╣",
    "0x447=0x468": "л░льлд!!бдбдЁ─кп2к─к╬яё╓─р┤кЄбв",
    "0x46b=0x48c": "квкдк─к╬¤н╘щ▌╗к╦л╓л┴бскркєк└!!б╣",
    "0x495=0x4b6": "хякм╓зкьк╞кдк├к╞кфкы!Ё─кпк╖кэ!б╣",
    "0x4c5=0x4d8": "бдбдбдл░льлдбдбдбдб╣",
    "0x4f3=0x514": "∙╝к╞к│к╚!?бдбдбды╢юцк╬уъбс╪╤к╚бв",
    "0x517=0x528": "ы╫∙ък╖к╞кдкы!?б╣",
    "0x531=0x544": "бдбдбдлилъл╖лв!!б╣",
    "0x54c=0x56b": "л░льлдбдбдэлк╡к▐бдбдк╜кьк╦к▀кєк╩",
    "0x56d=0x58c": "бдбдбд▌шк╖к▐к╩кдк╟бдбдбдквкыыЄ┌л",
    "0x58e=0x5ad": "к╟к╧бвк│кькмуък╬┘у╥│к┐кы▐чк╬бдбд",
    "0x5b0=0x5c1": "квкык┘кнэмбдбдбдб╣",
    "0x5c9=0x5e8": "ктк╧кфквк╬┘у╥│к╬Ёэюдк╧бвы╢юц╧╪к╬",
    "0x5ea=0x609": "щъбск╦к▐к╟╬╞кмк├к╞кдкыбгквк╜к│к╦",
    "0x60b=0x62a": "╠╕кик╞кдкык╬к╧бвк█кєк╬ьщ°╕к╦╬жко",
    "0x62d=0x638": "к╩кдбдбдбдб╣",
    "0x640=0x65f": "к╜кєк╩бдбдбдлклдлщуск╕к╩кдлщлъ!",
    "0x661=0x680": "элк┴кукєк╬бск╦╒йк▀к─кдк╞кы╥┐к╩кє",
    "0x683=0x6a4": "кллклдлщкмк╓к├к┐є╓к├к╞кфкылщлъ!б╣",
    "0x6aa=0x6c9": "бдбдбдкяк┐к╖к╧бдбдк│к╬к▐к▐бвк│к╬",
    "0x6cb=0x6ea": "ы╢юц╧╪к╦э╤к╡кьк┐бвб║уъбск╬ы╢▀зб╗",
    "0x6ec=0x70b": "кЄ╠╕с·к├к╞·╝кнк▐к╣бгк╜к╖к╞бдбдбд",
    "0x70e=0x72f": "к│к╬ы╢юц╧╪кЄ▄ць╘к╖к▐к╣бдбдч╡ъ└к╦б╣",
    "0x738=0x749": "л└лск└!лилъл╖лвб╣",
    "0x74f=0x76e": "ккъ├кд!!▐чк╬хыкжк│к╚кЄ┌дкдк╞бв",
    "0x770=0x78f": "л░льлдбгк╕кук╩кдк╚бдбдбдкяк┐к╖к╧",
    "0x792=0x7a5": "квк╩к┐к┐к┴кЄбдбдбдб╣",
    "0x7ad=0x7cc": "бдбдквкнкщкскыкткєклбгкфк├к╚Ўвкъ",
    "0x7cf=0x7e4": "бск╗кык├к╞к╬к╦бдбдбдб╣",
    "0x7ed=0x80a": "╘▒к▓к═кикш!бдбдбдя╛╙▀к╦!!б╣",
    "0x812=0x831": "к╖клк╖к│к╬к▐к▐к╟к╧бдбдбдкикикд!",
    "0x834=0x84d": "к╔кжк╦клк╩кщкєк╬клк├!?б╣",
    "0x855=0x874": "бдбдбдбды╢юцк╚ы╫∙ък╖к┐лилъл╖лвк╬",
    "0x876=0x895": "б║▌╗▌┬б╗кЄєв∙ък╡к╗к╞бдбдбдбдюв▀ц",
    "0x898=0x8a1": "к╟кнкьк╨б╣",
    "0x8a9=0x8c8": "к│к╬к▐к▐ю·кик╨бвлилъл╖лвкЄ▀┐к─к▒",
    "0x8cb=0x8d8": "к┴к▐кжбдбдбдб╣",
    "0x8e1=0x8f4": "бдбдбдяё╓─р┤бдбдбдб╣",
    "0x8fd=0x914": "к╔кжк╖к┐к║кщ?лслдл╖лвб╣",
    "0x91d=0x93e": "у┴к╚═Ў╩ркЄЁ├кыбв2к─к╬р┤кЄ▐┼кик╨б╣",
    "0x946=0x965": "бдбдбдїє╒╬кыклктк╖кьк╩кдбгы╢юцк╬",
    "0x967=0x986": "ёщк╦ы╫∙ък╖к┐лилъл╖лвкЄбвкткжьщ╙°",
    "0x989=0x99e": "ь┌кн╫юк╣к│к╚кмбдбдбдб╣",
    "0x9a6=0x9c5": "к╖клк╖бв▀╙твк╬═Ї╠ккмк│кєк╩к╦╠нк╖",
    "0x9c7=0x9e6": "кдкєк╕кубвк╜кєк╩ъээ■к╩к│к╚кфк├к╞",
    "0x9e9=0x9f6": "кщкьк═кик╛!б╣",
    "0x9ff=0xa1e": "∙╝к╚клбв╘╤кнкмЄнк▐кык▐к╟бдбдбдб╣",
    "0xa26=0xa45": "лпл├бдбдбдлилъл╖лв!кткжс┤к╖к└к▒",
    "0xa48=0xa57": "╥▒кик╞кпкь!!б╣",
    "0xa6f=0xa84": "╘╤кнкмЄнк▐к├к┐кя!!б╣",
    "0xa8c=0xaab": "яё╓─р┤кЄбвс·√▐Ї╕▐┼к╬¤н╘щ▌╗к╦╪╪кс",
    "0xaad=0xacc": "бскєк╟!!к╜кжк╣кьк╨бву┴═Ўк╬┌жкм",
    "0xacf=0xae4": "к╜к╬бс╥ок╦╦╥кпкя!!б╣",
    "0xaed=0xafa": "хякм·╝кп!!б╣",
    "0xb02=0xb21": "л░льлд!╤икЄк─к▒кэ!бдбдбд╘╤кнк╧",
    "0xb24=0xb3f": "Єнк▐к├к┐кмбв═Ї╠кк╧╒╬кык╛!б╣",
    "0xb47=0xb66": "л░льлд!╘щк╬ъ╚Ў╟к▐к╟бвхякмъбкєк╟",
    "0xb68=0xb87": "кфкыкшбгккюёк┐к┴Євк┘к┐хп╒═к╦кубв",
    "0xb8a=0xba9": "к╚к╞ктквк╜к│к▐к╟кдк▒к╩кдклкщк╩б╣",
    "0xbd9=0xbe4": "кфк├к┐!!б╣",
    "0xbed=0xc06": "ы╢юцкмбдбдбд▄ць╘к╡кькыкяб╣",
    "0xc0e=0xc2d": "лилъл╖лвк╧!?бдбдбдл░льлдк╧к╔кж",
    "0xc30=0xc3b": "к╩к├к┐к╬?б╣",
    "0xc44=0xc5f": "кпк╜!▌┌кьк╞кнкфкмк├к┐!!б╣",
    "0xc67=0xc86": "л░льлд!!∙╝кЄл░л║л░л║к╖к╚кы!!",
    "0xc89=0xc9c": "Ё─кп╒╬кєклкб!!!б╣",
    "0xcb6=0xcc3": "лилъл╖лв!!б╣",
    "0xcc8=0xcfd": "╨ск▓!кткжк╣к░к│к│к╧бвы╢юцк┤к╚юц√бктк╩кпс╝киуўк╗кы!б╣",
    "0xd02=0xd1d": "╙▐бс!к╧кфкп╘▒к▓к╩кдк╚!!б╣",
    "0xd5d=0xd6c": "льл╟лг!Ё─кп!б╣",
    "0xd75=0xd92": "кяк┐к╖к╧бвк│к│к╦э╤кыкябдбдбдб╣",
    "0xd9b=0xdb6": "льл╟лг!∙╝к╨клк╩к│к╚кЄ!!б╣",
    "0xdbe=0xddd": "2к─к╬яё╓─р┤кмбвлвлєл╕лзлъ-л╩к╬",
    "0xddf=0xdfe": "бс╥ок╦▄ць╘к╡кьк┐╨╤бдбдэ╤кысббск╧",
    "0xe00=0xe21": "к│к╬кяк┐к╖к└к▒бдбдбдкяк┐к╖к╧ювк╙бв",
    "0xe24=0xe45": "к│к╬уєкЄр┤к╦бскик╩к▒кьк╨к╩кщк╩кдб╣",
    "0xe4e=0xe67": "к╩!∙╝к╟лщлъкл!?╥│уъх╞б╣",
    "0xe6f=0xe8e": "квкъкмк╚кжбдбдк▀кєк╩бдбдбд▄ць╘кЄ",
    "0xe90=0xeaf": "·░клкьк╞бвьщ▀¤к╦╒щкЄк╖к╞кдкы╩рбд",
    "0xeb2=0xecf": "бдбд▄тбск╦ф┼к╖клк├к┐кябдбдбдб╣",
    "0xed7=0xef6": "к└кскшльл╟лг!▐чк╚ьщ▀¤к╦лщл│л╦лв",
    "0xef9=0xf08": "к╦╧¤кык╬кш!!б╣",
    "0xf10=0xf31": "лв-л╫бдбдбдбдкяк┐к╖к╧к│к│к╦э╤къбв",
    "0xf33=0xf52": "к│к╬Ўшк┴сяклкьк┐█·к╬╙█кякък╦┌жкЄ",
    "0xf54=0xf75": "╠╕с·к├к╞кцкпк╬бдбдбдбдк╜кьк│к╜кмбв",
    "0xf78=0xf99": "Ї╕▀╛к╬уък╬▐╓к╖спк╖к└к╚▐╓к├к╞бдбдб╣",
    "0xfc4=0xfcf": "льл╟лг!!б╣",
    "0xfd8=0xfef": "к└кск└!кткжу┴╩ркмк╩кдб╣",
    "0xff8=0x1007": "льл╟лг-!!!б╣",
    "0x1020=0x102f": "льл╟лгбдбдбдбдб╣",
    "0x1038=0x1059": "к▐к┐бв╥│уъх╞к╦бск├к┐к┴кжц╗к║кщк╩б╣",
    "0x1062=0x1083": "уъбск╬ы╢▀зктквк╬ы╢юцк╬∙╗бвклбдбдб╣",
    "0x108b=0x10ac": "лклдлщк╧к│к╬лдл╟лвкмтвк╦ь¤к├к┐к╖бв",
    "0x10af=0x10c0": "кткжїЎ▌┬лщлъкш!б╣",
    "0x10c8=0x10e7": "к│кьклкщк╧Є╪к╬щ╕э║к╦к╩кык┘кнсє·╝",
    "0x10ea=0x1109": "к╬╒щк└к╩!л╙л╖л╨л╖к╖к┤кпк╛!!б╣",
    "0x1112=0x1127": "к╜!к╜лък╧к╩кдлщлъ~б╣",
    "0x112f=0x114e": "к╡к╞бдбдбдк│кьк╟бвк╚к╦ктклкпк╦кт",
    "0x1151=0x116c": "ьщ╦ь╒кє╖к╚хыкжц╗кл!бдбдбдб╣",
    "0x1175=0x118a": "кфк┘кик╛!кккдбдбдбдб╣",
    "0x1193=0x11ae": "кябвкяк┐к╖к╧╬╝╠їк╩кдкякшк═б╣",
    "0x11b6=0x11d5": "кккщк╧бвкккскзкщкЄ╘▒кмк╖к┴к▐к├к┐",
    "0x11d8=0x11e5": "к║кщк╖бдбдбдб╣",
    "0x11f9=0x1218": "ккбсбдбдбдк╬╩╞чЎк╧їє╒╬к╚кык└кэкж",
    "0x121b=0x122e": "к╩!ккюёк┐к┴бдбдбдб╣",
    "0x1237=0x1248": "кжбдбдбдкєбдбдбдб╣",
    "0x1264=0x127f": "лилъл╖лв!╤ик┼кдк┐к╬к═!!б╣",
    "0x1287=0x12a6": "кк?бдбдбдкрбвкркркрбг▐┬█░к╩кдбг",
    "0x12a8=0x12c7": "к╜кьк╩кък╦▐╓кдктквкык└кэкжклкщбв",
    "0x12c9=0x12e6": "▄мкьк╬бсбск░кщкдк╧к╡к╗к╞кфкы!",
    "0x12e9=0x1308": "¤нкэ·╛кдк╚кыклкщЁ─кпк╣к▐к╗кэ!б╣",
    "0x1323=0x1334": "бдбдбдл░льлдбдбдб╣",
    "0x133d=0x134c": "лилъл╖лвбдбдбдб╣",
    "0x1355=0x1368": "л░льлдбдбдбдкяк┐к╖б╣",
    "0x1370=0x138f": "кдкдкшбдбдбдкдк▐к╧∙╝ктхыкяк╩кпк╞",
    "0x1392=0x13a9": "кдкдкєк└бдбдбдлилъл╖лвб╣",
    "0x13b0=0x13b7": "бдбдбдб╣",
    "0x13c0=0x13db": "бдбдбдхяк╚ьщ▀¤к╦бв╒╬кыкл?б╣",
    "0x13e4=0x13f3": "бдбдбдбдкики!б╣",
    "0x13fc=0x140b": "кшк╖бв·╝к│кж!б╣",
    "0x141c=0x1451": "л░бдбдльлдбдбдл└лсбдбдбдл└бдбдлскшбдбд╒╬к╩кдк╟бдбдбдб╣",
    "0x145c=0x147d": "∙╝к╚клквк╬ёщклкщїєк╗к╩кдлщлъкл?б╣",
    "0x1485=0x14a4": "┘э╫тк└к╩бдбдбдктк╧кфбвквк╬┘у╥│к╬",
    "0x14a6=0x14c5": "ыЄу█к╧бв┌тк╨ы╢юцк╬╤└хук╚ы╫∙ък╖к╞",
    "0x14c8=0x14d3": "кдкыбдбдбдб╣",
    "0x14dc=0x14fd": "кпк╜кк!∙╝к╚клк╩кщк═кик╬клкш!?б╣",
    "0x1505=0x1524": "л░льлдбдбдлслдл╖лвбгбдбдлилъл╖лв",
    "0x1526=0x1545": "к╦к╧бдбдкткж∙и╥│к╬ыЄ▐╓к╧к█к╚кєк╔",
    "0x1547=0x1566": "э╤к├к╞кдк╩кдк╟к╖кчкжбдбдбдкяк┐к╖",
    "0x1569=0x1582": "к┐к┴к╦їє╒╬кык│к╚к╧бдбдбдб╣",
    "0x158b=0x1596": "бдбдбдбдбдб╣",
    "0x159e=0x15bd": "ккк╜кщкпбвкдк▐кфы╢юцёщкЄЇ╕▐┼к┐к┴",
    "0x15bf=0x15de": "км┘ёк├к╞кдкык└кэкжбгк│к╬к▐к▐к╟к╧",
    "0x15e0=0x15ff": "ф▓кщкм╪■к╙кык│к╚∙▒я╥бгктк╧кфў▄кп",
    "0x1602=0x1617": "к│к╚ктклк╩кяк╠бдбдбдб╣",
    "0x1620=0x162f": "бдбдбдлилъл╖лвб╣",
    "0x1638=0x1645": "л░льлдбдбдбдб╣",
    "0x164d=0x166c": "бдбдбдбдк╜кжк╣кык╖клк═кик╬кл!?",
    "0x166f=0x168a": "к╜кжк╩к╬кл!?лилъл╖лв!?б╣",
    "0x1693=0x16b2": "бдбдбдл╡лшбдбдл╩лщбдбдбдл░льлдб╣",
    "0x16d5=0x16f4": "ш╛╘╤цЁъ╣╨┐╙▐!!бдбдбдбдк▐к└▀╛у░",
    "0x16f7=0x1714": "к╖к╞кыкя!бдбдбдбдбдбд╒╬кы!б╣",
    "0x171d=0x1730": "кпк╜кккккккккк!!б╣",
    "0x1748=0x1763": "╘╤кнкмбдбдбдЄнк▐к├к┐бдбдбдб╣",
    "0x176b=0x178c": "бдбдбдхяк┐к┴кмбдбдлилъл╖лвкЄбдбдбд",
    "0x178f=0x179e": "∙╝к╟к│кєк╩!?б╣",
    "0x17a6=0x17c5": "к╧квбдбдбдк╧квбдбдбдк╔кжк╖к╞кш!",
    "0x17c8=0x17e7": "к╔кжк╖к╞к│кєк╩к│к╚к╦!!бдбдбдб╣",
    "0x17ef=0x180e": "лилъл╖лвэлк┴кукєбдбд▐▌кєк╕кук├к┐",
    "0x1811=0x181e": "лщлъклбдбдбдб╣",
    "0x1826=0x1845": "бдбдбдф▓кщкм╦№р╗к╧бв№мклк╦·╖у¤кЄ",
    "0x1847=0x1866": "я╖къ╓окдк┐бдбдбдбдк┐к╚кибвЇ╕▐┼к╟",
    "0x1868=0x1887": "квкэкжк╚ктквк╬ьщ╠ккЄсЇк▒к╞бв┘э▐└",
    "0x188a=0x18a3": "к╟к╣крэ║к╩к╔кдк▐кдбдбдбдб╣",
    "0x18ac=0x18c9": "бдбдбдк╜кєк╩бдбдбд╪й╓ук╩!!б╣",
    "0x18d8=0x18f7": "к▀кєк╩бдбдбд┌дк│кик▐к╣клбдбд?б╣",
    "0x1913=0x1920": "лилъл╖лв!?б╣",
    "0x1928=0x1949": "к╜кєк╩к╚к│кэк╦кдк┐к╬к═!лилъл╖лв!",
    "0x194c=0x195d": "Ё─кпк│к├к┴к╪!!б╣",
    "0x1965=0x1984": "к▀кєк╩бдбдЁ─кпк│к╬ы╢юцклкщ╘▒к▓к╞",
    "0x1986=0x19a5": "бдбдбдк│к│к╧бвкткжк╣к░▌┌кькыбдбд",
    "0x19a7=0x19c8": "ы╢▀зкЄс·кык┘кнтвк└к╞кЄуўк├к┐кдк▐бв",
    "0x19cb=0x19ec": "уък╧к│к╬ы╢юц╧╪кЄэўкъ╦█кэкжк╚бдбдб╣",
    "0x19f5=0x1a0c": "к╣бдбдбдЇвкдшЇкьк└кя!б╣",
    "0x1a15=0x1a34": "ё║к╦л╥л╙км!!бдбдбдъ╦к╩кд!!б╣",
    "0x1a3a=0x1a59": "бдбдбдл░льлдбгквк╩к┐к╚їє№хкик╞бв",
    "0x1a5b=0x1a7a": "кшклк├к┐бгл╔лнл╔лнк╖к╞бвл╧лщл╧лщ",
    "0x1a7c=0x1a9b": "к╡к╗кщкьк┐к▒к╔бвкяк┐к╖кмуък╬┘у╥│",
    "0x1a9d=0x1abc": "к╩кєклк╕кук╩кпк╞бвк┐к└к╬╥│к╬энк└",
    "0x1abf=0x1ada": "к╚бв▐╓кжк│к╚кмїє╒╬к┐бдбдбдб╣",
    "0x1ade=0x1afd": "к╜к╖к╞бдбдк╜кькмбвкдк▐к▐к╟к╟ьщ█у",
    "0x1b00=0x1b19": "¤Ёк╖кдк│к╚к└к├к┐кябдбдбдб╣",
    "0x1b22=0x1b3d": "лилъл╖лв!бдбдбдхяк╧бдбдбдб╣",
    "0x1b46=0x1b5d": "свкм┌дк│кикыбдбдбд╩░?б╣",
    "0x1b63=0x1b82": "к╡кшк╩кщбвк▀кєк╩бдбдбдкяк┐к╖к╧бв",
    "0x1b84=0x1ba3": "уък╦спк╡кьЇ╕═гк╪к╚у░кък▐к╣бдбдбд",
    "0x1ba5=0x1bc6": "л░льлдбдбдкяк┐к╖к╧бвщлклЇ╕▀╛клкщбв",
    "0x1bc9=0x1be6": "квк╩к┐кЄ╠╕с·къс┘к▒кыкябдбдбдб╣",
    "0x1bee=0x1c0d": "!?бдбдбдбд·╝кпк╩!лилъл╖лв!!",
    "0x1c10=0x1c23": "·╝клк╩кдк╟кпкь!!б╣",
    "0x1c29=0x1c4a": "к╡кшк╩кщбдбдбдл░льлдбвэлк╡к▐бдбдбд",
    "0x1c4d=0x1c68": "к╡кшк╩кщбдбдбдк▀кєк╩бдбдбдб╣",
    "0x1c7e=0x1c9d": "бдбдбд·╝к│кжк╝л░льлдбгк│кььд▀╛к╧",
    "0x1ca0=0x1cad": "кфк┘кибдбдбдб╣",
    "0x1cb6=0x1cd1": "бдбдбдквквбвк╜кжк└к╩бдбдбдб╣",
    "0x1cda=0x1cf7": "к╡кшк╩кщбдбдбдлилъл╖лвбдбдбдб╣",
    "0x1d00=0x1d1b": "бдбдбдквк╨кшбдбдбдлилъл╖лвб╣",
    "0x1d54=0x1d71": "л┴лпл╖лчлж!╩рк╦∙ъкяк═кз!!б╣",
    "0x1d79=0x1d98": "к▀кєк╩!!Ё─кп╘▒к▓к╞!!бдбдбдбд",
    "0x1d9b=0x1dba": "кяк┐к╖кмбв∙╝к╚клу┴╩ркЄ╩│к░кя!б╣",
    "0x1dc3=0x1dde": "льл╟лг!∙╝к╨клк╩к│к╚кЄ!!б╣",
    "0x1de6=0x1e05": "кяк┐к╖к╧бвуъбск╬ы╢▀зкЄ╬╖╫тк╣к┘кп",
    "0x1e07=0x1e26": "є▄кщкьк┐бдбдбдк└клкщбвк│к╬ы╢юцкЄ",
    "0x1e28=0x1e47": "╠╕с·к├к╞·╝кпкябдбдбдк│кьклкщбдбд",
    "0x1e4a=0x1e57": "к║к├к╚бдбдбдб╣",
    "0x1e60=0x1e79": "к└!к└кслщлъкш!!╥│уъх╞б╣",
    "0x1e81=0x1ea0": "квкъкмк╚кжбдбдк▀кєк╩бдбдбд▄ць╘кЄ",
    "0x1ea2=0x1ec1": "·░клкьк╞бвьщ▀¤к╦╒щкЄк╖к╞кдкы╩рбд",
    "0x1ec4=0x1ee1": "бдбд▄тбск╦ф┼к╖клк├к┐кябдбдбдб╣",
    "0x1ee9=0x1f08": "к└кскшльл╟лг!▐чк╚ьщ▀¤к╦лщл│л╦лв",
    "0x1f0b=0x1f18": "к╦╧¤кык╬!!б╣",
    "0x1f20=0x1f41": "лв-л╫бдбдбдбдкяк┐к╖к╧к│к│к╦э╤къбв",
    "0x1f43=0x1f62": "к│к╬Ўшк┴сяклкьк┐█·к╬╙█кякък╦┌жкЄ",
    "0x1f64=0x1f85": "╠╕с·к├к╞кцкпкябдбдбдбдк╜кьк│к╜кмбв",
    "0x1f88=0x1fa9": "Ї╕▀╛к╬уък╬▐╓к╖спк╖к└к╚▐╓к├к╞бдбдб╣",
    "0x1fcc=0x1feb": "бдбдбдквквк╩кык│к╚кмбв∙и╥│к╬▐┼┘д",
    "0x1fee=0x1fff": "к└к├к┐к╬клк╖кщ?б╣",
    "0x2008=0x2029": "к▐к┐бв╥│уъх╞к╦бск├к┐к┴кжц╗к║кщк╩б╣",
    "0x2032=0x2053": "уъбск╬ы╢▀зктквк╬ш┐╒°к╬∙╗бвклбдбдб╣",
    "0x205c=0x2073": "бдбдбдлилъл╖лвк╧бдбдбдб╣",
    "0x207c=0x2097": "Ї╕к╦бву░к├к╞кдк├к┐кябдбдбдб╣",
    "0x20a0=0x20b9": "Ї╕▐┼к╡к▐к╦к╩к├к┐лщлъкл?б╣",
    "0x20c1=0x20e0": "бдбдбдк╜кжк╟к╖кчкжк═бгу¤к╬┌╕к╖кд",
    "0x20e2=0x2101": "э║кЄуък╧Ї╕к╦спк╖▀╛к▓бвк╜к╬х┘▐┼кд",
    "0x2104=0x211d": "к╚к╩к╡кыкщк╖кдклкщбдбдбдб╣",
    "0x2126=0x213b": "бдбдбдлилъл╖лвбдбдбдб╣",
    "0x2148=0x217b": "╪╬кьк╩кдк╟бвл░льлдбдбдбдкяк┐к╖к╧бвкдк─к▐к╟ктк║к├к╚бв",
    "0x217e=0x21b3": "квк╩к┐кЄ╠╕с·къс┘к▒кыкябгбдбдкдк─к▐к╟ктбвк║к├к╚бдбдбдб╣",
    "0x21d2=0x21f7": "к╖бвк╖к├клкък─клк▐к├к╞кэкш!лилъл╖лвб╣",
    "0x21fc=0x222f": "к│к╬р╗к╦кнк├к╚квкык╧к║кш!ъ╔╙▐к╩кыуъбск╬ы╢▀зкм!!б╣",
    "0x2234=0x225b": "к╜бвк╜кжкл!бдбдбдк╟ктбвкдкдк╬клк╩кв?б╣",
    "0x225f=0x2292": "╙▐э█▄¤!!ы╢юцк╩кєклк╟╪∙к├к╞кдкыкшкъ╧▐къїєк╖к╞▐┼к├к╞",
    "0x2295=0x22b4": "квк▓к┐█░кмб║ы╢▀зб╗кт¤ьк╓кякш!б╣",
    "0x22b9=0x22ec": "∙╝к└клбвквкьклкщрї╠лбскяк├к╞к╩кдкл?лилъл╖лвбдбдбдб╣",
    "0x22f0=0x2331": "ы╢юцклкщлилъл╖лвкЄЁ╛к▒їєк╖к┐¤нкнк├к╤кък╚╘июф╩│хЎклкщЁыкЄсйкдбв╨╤к╧",
    "0x2333=0x2374": "л╚льл╕лу-л╧лєл┐-к╚к╖к╞бвлилъл╖лвк╚к╚ктк╦сж═гкЄ╧╠к▒кск░кыл░льлдбг",
    "0x2376=0x23b7": "Ї╕▐┼к╚к╖к╞к╬╒ЇкЄЁэ▌┬к╦█б¤╞к╣кылилъл╖лвк╬ккклк▓к╟бврў═¤к╬█░к╧клк╩къ",
    "0x23b9=0x23fc": "к╬ктк╬к└кмбдбдбдквк▐кък╦ктк╧къкнкъ╬жкокылилъл╖лвк╦╙▀к╖б║с┤к╖к└к▒б╗бв",
    "0x23ff=0x2428": "клк─к╞к╬∙и╥│кЄ№уклк╖крл░льлдк╟квк├к┐бдбдбд",
    "0x242d=0x2450": "квк├!!квк├к┐!!к█кщбвл░льлд!!б╣",
    "0x2455=0x2462": "ккккккккк├!б╣",
    "0x246a=0x2485": "бдбдбдк╟ктбв·╣к╗к╜кжк╟квкыбг",
    "0x2499=0x24ce": "л░льлдбвэлк╡к▐бдбдлилъл╖лвк╧к║к├к╚квк╩к┐к┐к┴к╚ьщ▀¤кшбг",
    "0x24d1=0x24f2": "╨╤к▐к╟ктбвк│кьклкщктк║к├к╚бдбдбдб╣",
    "0x250b=0x2532": "Ё─кдлтлєк└к╩бгквкьклкщкткж┌т╥┤клбдбдбдб╣",
    "0x2537=0x255e": "к╜кжк═бдбдбдк▀кєк╩к╔кжк╖к╞кык╬клк╖кщ?б╣",
    "0x2579=0x25a0": "к█кєк╚кшк═кибдбдбдк╔кжк╖к╞кык╬клк╖кщ?б╣",
    "0x25a5=0x25d8": "к╜кжк└к╩квбдбдбдк├к╞!∙╝к╟ккюёкмк│к│к╦кдкыкєк└кш?б╣",
    "0x25dc=0x260f": "кв!бдбдбдк╥к├к╔~кд!!к╗к├бдбдклкпкяк╢кяк╢Ї╕═гклкщ",
    "0x2612=0x262b": "кфк├к╞кнк╞квк▓к┐к╬к╦!!б╣",
    "0x2630=0x2659": "кяк╢кяк╢к├к╞бвк█к╚кєк╔╪▀ьэк╕кук╩кдкл!?б╣",
    "0x265d=0x2690": "кдкдк╕кук╩кдк╬бвл░льлдбдбдбдк╟ктбвк█к╔к█к╔к╦к╖к╞кккн",
    "0x2693=0x26a6": "к╩к╡кдкшбвлилъл╖лвб╣",
    "0x26aa=0x26eb": "лилъл╖лвк╧Ї╕═гк╦бскъбвЄ╪к╬Ї╕▐┼к╚к╩к├к┐бгк╖клк╖бвЇ╕═гк╟к╧к╡к╖к╞к╣кы",
    "0x26ed=0x272e": "к│к╚ктк╩кдбдбдбд╩мкЄЄек╞х∙к╖к╞▐║█хк╦∙╗═гк╪к╚█╛кькылилъл╖лвк╦╙▀к╖к╞",
    "0x2731=0x2768": "¤Ёк╖кд┌у╪№бвк╔к│клквкнкьф╘к╬л░льлдк╚лслдл╖лвк└к├к┐бдбдбд",
    "0x2782=0x27b5": "л█-л█л├л█!к╩кык█к╔к╬кжбдбдбдбдквк╬ыЄ╤иЄвк╩к╖кмщ╕э║",
    "0x27b8=0x27c1": "к╚к╩!?б╣",
    "0x27c6=0x27f1": "╥┐к╩кък╦бвк╩клк╩клш╫эхк├к╞кдкыкшкжк╟бдбдбдб╣",
    "0x27f5=0x2828": "к╜кьк╧∙╝кшкък╕кук╩бгбдбдбдбдк╖к╞бвккюёк╡кєк╧к│кьклкщ",
    "0x282b=0x2836": "к╔кжк╣кы?б╣",
    "0x283b=0x2848": "бдбдбдўхк╦к╧б╣",
    "0x284c=0x2881": "л█лжбдбдбдккюёк╡кєк╡кикшк▒кьк╨к│к╬ї╜к╦кккъкуквкшклкэбг",
    "0x2883=0x28b6": "ф▓кщл░лъл├лпк╬┌┼ктбвккюёк╡кєкщ▐лЁщктр╗к╧к╜кжэ■кпк╩кд",
    "0x28b9=0x28c2": "ъб┘дк╕куб╣",
    "0x28c7=0x28e8": "квкъкмк╚кжк┤к╢кдк▐к╣бдбдбдк╖клк╖б╣",
    "0x28ed=0x28fe": "бдбдбд∙╝клк╩?б╣_",
    "0x2903=0x2924": "кдк▐р┤кЄ╘╤клк╡кьк▐к╗кєк╟к╖к┐кл?б╣",
    "0x2929=0x2952": "л█л├л█лжбдбдбд∙╝кЄ╨╞╦рк╦к╜к╬кшкжк╩бдбдбдб╣",
    "0x2957=0x2982": "╨╞╦рктлпл╜ктк═ки!к┴кукєк╚╠╕к╞к┐кєк└кш!!б╣",
    "0x2986=0x29b9": "л█л█л├!?ккл╠л╖бв╥┤э■э║к╦·╛клк├к╞∙╝к╚кдкж╧вкЄк├!!",
    "0x29bc=0x29d3": "▐лЁщк╬бскЄ╪╬кьк┐кл!?б╣",
    "0x29d8=0x2a07": "л║лыкфк├к╚кдк╞╥┤э■э║ктлпл╜ктквкыклкш!к▐к├к┐кпб╣",
    "0x2a0c=0x2a3f": "л╨лькєклк├к┐кщкяк╖к╬унк┴к╕кук├к┐к╬к╦!л█л█л█лж!!б╣",
    "0x2a43=0x2a84": "л█л█хмк╬╥╜╒Їк╬╦г▌ьктквк├к╞бвкшкжкфкпл╒лглвл╩кЄуўк├к┐фюк╖к▀клкщ╪бк┴",
    "0x2a86=0x2ac7": "Є┴кък─к─квкылолулълкбдбдбдї╠╨╬к╧лдлєл┴лнун▌╢к╟л█л█хмк╚л▒лєллк╨клкъ",
    "0x2aca=0x2ad5": "к╖к╞кдкыкмбв",
    "0x2ad7=0x2afa": "к╜кьк╩кък╦°┴ш▒к╩ьэбскЄф┼к╖кєк╟кдкыбг",
    "0x2aff=0x2b2c": "кккдк├!!к▐к┐кшк╜╠╕к╖к╞кы╨└к╦╘╤клк╖к┐к└кэ!б╣",
    "0x2b30=0x2b63": "л█л├л█-!!▌╢к▒к╞кыклкщк├к╞бвхыкдкмклкъкЄк─к▒кык╬к╧",
    "0x2b66=0x2b73": "кшкпк╩кдк╬кйб╣",
    "0x2b78=0x2b93": "к│лєк╬бдбдбдкпк╜л╕л╕лд!!б╣",
    "0x2bad=0x2be0": "к╡кв!лвлєл╪лылр╙▐у▌кдр╘тв╧э╠╜ун╙▐№хкткдкшкдкш╙▐¤■кс",
    "0x2be3=0x2c14": "к╦к╩к├к╞к▐кдкък▐к╖к┐!!╥│уък╬ч┤╬ок╧т┴к╬твк╦!?б╣",
    "0x2c18=0x2c4b": "бдбдбдк├к╞квк╬╙▐╤√к╦╠╜к▐к├к╚кык╕кук╩кдкллнл▀!бдбдбд",
    "0x2c4d=0x2c80": "к╜бвк╜кьк╦к╖к╞ктбдбдбд∙╝к╩кєк└квк╬╤√к╧бгкткж10у┴╩р",
    "0x2c83=0x2ca2": "кты┐к▐кєк╨клкъу▌кдс┘к▒к╟бдбдбдб╣",
    "0x2ca6=0x2cd9": "бдбдбд∙╝к└клбв╠╕к╞кык│к├к┴к╬█░к▐к╟бв¤╪кмбвф┬кпк╩к├к╞",
    "0x2cdc=0x2ceb": "кнк▐к╖к┐бдбдбдб╣",
    "0x2cef=0x2d0a": "бдбдбд√∙к▒┌кк└к╩бвквкъкуквб╣",
    "0x2d0e=0x2d41": "бдбдбдк╡бвк╡кв!кдкшкдкшл┐лдлрлъл▀л├л╚к╟к╣!!3бдбд",
    "0x2d43=0x2d78": "2бдбд1бдбдбдл╧л├л░р╘твщ╨унк╟к╣!!к╓к├к┴кокък╟к╣!!",
    "0x2d7b=0x2daa": "к╚кєк╟ктк╩кдк╟к╣!!бдбдбдк╡к╞у╝э■бвк┤╩я▀╠к╧?б╣",
    "0x2daf=0x2dd8": "2╙°к╚╒╬кык╩!бдбдбдк╚хык├к╞кфкък┐кд!!б╣",
    "0x2ddc=0x2e1d": "эр╙▐к╩┘│·╧к╬╒щкЄЁ√кибв╨╤╙°к╧╤ик▐к▐к╩°щу▌к╬╒щк╪к╚кпкъїєк╖к┐л╧л├л░бг",
    "0x2e1f=0x2e60": "╩└Євк╬ыцу▌я┴кф▀┬я┴╩╢кЄу▌кдк─к╓к╖к╩кмкщквк╞к╔ктк╩кп╒щкЄс┘к▒кы∙икЄбв",
    "0x2e63=0x2e84": "Єнкскщкькыэ║к╧к╔к│к╦кткдк╩кдбдбдбд",
    "0x2e9e=0x2ed3": "бдбдкфк├к╤къб║ъ▐кжб╗кякшк═кибг╨╤к▐к╟╩│кдк└кк╤╤кЄъкк╦бв",
    "0x2ed6=0x2f09": "к│к╬я┴кЄ╦╥кдк┐к╧кдкдк▒к╔бдбдбд╦╘к├к╞╒╬к╩кдктк╬к═киб╣",
    "0x2f0e=0x2f2b": "б║ъ▐кжб╗к├к╞∙╝кмк╟к╣кл?я┴э■б╣",
    "0x2f2f=0x2f62": "кє-к╚к═бдбд╓╟кик╨бвкяк┐к╖к┐к┴кмк│кжк╖к╞╤╗╒Єк╦▀┬∙бкЄ",
    "0x2f65=0x2f96": "бск┘к╞ктбв∙▒к║кк╦╘км╒╬кык╚к╧∙┌кщк╩кдц╗к╕кук╩кд?б╣",
    "0x2f9b=0x2fb2": "к╜кжк╟к╣к═кзбдбдбдк╧квб╣",
    "0x2fb6=0x2fe9": "кдкпкщьщ▀ц·╪┘дкфк├к┐к╚к│кэк╟бвщыкм╦╜кьк╨л╔лєк╚╦╘Ёык╧",
    "0x2feb=0x301e": "╒кк┴кык╖бдбдбдк└клкщбвкткжк│к╬ккя┴к┐к┐кєк╕кукккжклк╩",
    "0x3021=0x3040": "бдбдбдк╩кєк╞═┼кик┐къктк╣кык╬кшб╣",
    "0x3045=0x3076": "к╜!бдбдбдк╜кєк╩ю╓к╖кдк│к╚хыкяк╩кдк╟∙╗к╡кдкшя┴э■б╣",
    "0x307b=0x30aa": "к╒кжбдбдбдкфк├к╤къ╘июф╩│хЎк╦бскэкжклк╩квбдбдбдб╣",
    "0x30af=0x30cc": "ки?бдбдбд╨╤∙╝клхыкдк▐к╖к┐?б╣",
    "0x30d1=0x30e8": "кдкдкибвк│к├к┴к╬№е!!б╣",
    "0x30ec=0x312d": "ю·кдк╬к╔к╡кпк╡к╦▌╤кьк╞ь¤твк╖к╞кдк┐бвы╢юцк╬бс┌ккЄъктвк╦лвлєл╞лг-лп",
    "0x312f=0x3170": "л╖лчл├л╫кЄ╦╥я┴к╖к┐лЇлзл╣л╤бглнл╞кыл╗лєл╣к╚бвк╜кьк╩кък╬╦╘квк╖кщкдк╬",
    "0x3172=0x31b3": "╒▐к╡к╟к╜кэк╜кэ▀╚╓зк╬╦╘ктк─кну╖кск╞кдкык╚кдкжк╬к╦бв▀ц╒╬к╬ўятв√┐кнк╚",
    "0x31b5=0x31f6": "╥╜╒Ї·юкдкмюмкдк╖к╞клбвЁ─кпктъкк╬╩│хЎк╦бскэкжклк╩бдбдбдк╩к╔к╔═┼кик╞",
    "0x31f9=0x320c": "кдкылЇлзл╣л╤к└к├к┐бг",
    "0x3226=0x3259": "лклдлщк╧лплы~л├лп!╦нкпк╞бвклкб~к├к│кдкдбвщ╕э║к╡к▐",
    "0x325b=0x328e": "лщлъкш~!!бдбдбдл╓лєл╓лє~лє!к╔кєк╩ф┬кд╥┐км╒╬к╞кт",
    "0x3291=0x32be": "к│к╬лдл╟лвл╜-л╔к╟к╓-к├к┐є╓к├к╞кфкылщлъ!!б╣",
    "0x32c3=0x32e2": "бдбдбдкяк╖к╧є╓кщк╠к╛бвлплыл├лпб╣",
    "0x32e7=0x331a": "к▐кбк┐к╜кєк╩к│к╚хыкж!л█лєл╚к╦ш╫═│лклфл╕лщлък═!!б╣",
    "0x331e=0x3353": "кшкдкл?лплыл├лпбдбдбдЄ╪к╬щ╕э║к┐кыэ║бв╠╜к╖к╞ккк┤кщк║бв",
    "0x3355=0x3388": "╠╜к╖к╞√укяк║бв╠╜к╖к╞▌йклкьк║бдбдбдк▐к╖к╞кфсє·╝ёщк╬ує",
    "0x338b=0x33b2": "к╟квкък╩кмкщ╩░кЄ°жкжк╩к╔ктк├к╞к╬Ўт!!б╣",
    "0x33b6=0x33e9": "кв!бдбдбдкяклк├к┐бглклдлщк╡к├кн°жкдк╩кмкщбвлдл╟лвкЄ",
    "0x33ec=0x341b": "л╓лє№▐к╖к╞к┐лщлъклкщбвк╜кьк╟╥┴к├к╞кылщлък═!?б╣",
    "0x341f=0x3452": "бдбдбд╘╤┌кк╬тэт╢к╡к╦ь╤╫╛к╬ч╚Є▒кЄ∙ъкяк╗Єек─л░лъл├лпЁщ",
    "0x3454=0x3487": "к╬к│к╬х┤э║кЄщ╕э║к╚к╖к╞р╘кєк└к╬к╧бвкфк╧къ╩ръ▐кдк└к├к┐",
    "0x348a=0x3495": "к╬клбдбдбдб╣",
    "0x3499=0x34da": "щ╕э║к╬э└ЄїкЄк╡кщк╦╙┤ки▀╛к▓кык┐кск╦бвЁ│╧╨кЄ█п╒╚к╬╒щк╦їєк┐лплыл├лпк╚",
    "0x34dc=0x351d": "сб╦№лдл╟лвл╜-л╔бдбдбд1∙пк╚ьщЄ╔кък╬╒щк╧к╔к│кл╨Ї┘╪к╩ккклк╖к╡кЄ╬▀ки",
    "0x351f=0x3560": "к─к─бв═ЎкЄ·╝кпъгк╬кшкжк╦Єфкєк╟·╝кпбдбдбдк│к╬л│лєл╙кмбвкфкмк╞▐ўф┬к╩",
    "0x3563=0x3598": "╪кш▌кЄў╨к┴╪■к▄к╣к│к╚к╩к╔бвт┴км▀╠▀└к╟кнк┐к└кэкжбдбдбдбд",
    "0x359d=0x35b4": "кє?∙╝клхык├к┐лщлъкл?б╣",
    "0x35b9=0x35dc": "кдкфбв∙╝к╟ктк╩кдлщлъбдбдбдл╧л├!?б╣",
    "0x35f6=0x3637": "ф┬э║ктбвък╤ик╩┘│·╧э║╙╣кт╦█къбвювк╙Ёбклк╩╪∙кък╦к─кпы╢юцк╬╧╪бдбдбдбд",
    "0x363a=0x3669": "╙┐кд┘╙к╬ёщк╟бвльл╟лгк╧∙╝кЄ▐╓кжк╬к╟квкэкжклбдбдбд",
    "0x366e=0x3687": "бдбдбдбдбдбд╩мк└кябдбдбдб╣",
    "0x368f=0x36ac": "бдбдбдбдбдбдбдбдбдбдбдбдбдбдбд",
    "0x36c3=0x36f8": "к╡кв!ккєнк╧к╚к├к╞кт·чкпк╞╩жфёкдкщк╖кдлдлыллл╖лч-к└!",
    "0x36fa=0x372d": "к▀кєк╩км√╝к┘к╨бвлдлыллк╬л╔лык┐кєкмл╕лулєл╫к╣кыкш!!",
    "0x3730=0x3765": "к╡кв!!к▀кєк╩к╟кдк├к╖кчк╦√╝к▄кжк═!л╔~лык┐~кє!!б╣",
    "0x376d=0x377c": "л╨л├л╖лу~лє!!",
    "0x3798=0x37ab": "лнлулв----!!б╣",
    "0x37b0=0x37bf": "к╦бвь╤хрк└!?б╣",
    "0x37c4=0x37d5": "ь╤хрк└к╛--!?б╣",
    "0x37d9=0x381a": "┘│·╧к╬¤нбвьщ╙°к╧лщл│л╦лвк╪к╚бск├к┐лв-л╫к└к├к┐кмбв№дкфклк╩яыбск▀км",
    "0x381c=0x385d": "╪╬кькщкьк║бвювк╙лвлєл╪лылрк╪бдбдк╜к│к╟к┐к▐к┐к▐ў╫къклклк├к┐╘╤┌къок╬",
    "0x3860=0x3895": "лдлыллл╖лч-к╦▐лк╙ь¤кък╟є╤╩ек╖бвьщх╕╩╢к╬ь╤╤иэ║к╚к╩кыбг",
    "0x389a=0x38ad": "лнлул├л█----!б╣",
    "0x38c1=0x38f4": "к╒кжбдбдбдл░льлдк╬╥┐кски!к▐к╡кл╘июф╩│хЎклкщЁыкЄсйкж",
    "0x38f7=0x3928": "к╚к╧!бдбдбдхяк╬бвхяк╬▀цкн╦г▌ькЄк╔кжк╖к╞кпкькы!б╣",
    "0x392d=0x3960": "кк╦╘к╡кєбдбдбдбвкткжкфкск╚кдк┐█░кмкдкдкєк╕кубдбдбдб╣",
    "0x3964=0x3997": "кжкык╡кбкд!!хяк╬╤╤к╟хяк╬ё╨кЄхякмыцкркєк└!кдк├к┐кд",
    "0x399a=0x39ad": "∙╝к╬┘■╧гкмквкы!?б╣",
    "0x39b2=0x39c5": "к▐кдк├к┐к╩квбдбдбдб╣",
    "0x39ca=0x39d3": "╠э▌╗!!б╣",
    "0x39d8=0x3a03": "бдбдбд∙╝к└бгкткжхяк╦╧░кжк╩бдбдбдхяк╧бдбдбдб╣",
    "0x3a07=0x3a3a": "ыцкєк└кпкьк╞кыэ▐∙ък╟к╧квкък▐к╗кєк╛╠э▌╗!!л░льлдкмбв",
    "0x3a3d=0x3a54": "л░льлдкм·▐кьк▐к╖к┐кв!б╣",
    "0x3a59=0x3a78": "к╩бв∙╝к└к╚!л░льлдкм·▐кьк┐!?б╣",
    "0x3a7d=0x3a88": "к╧бвк╧кд!б╣",
    "0x3a8c=0x3abf": "л╨лллт-лє!∙╝кЄл░л║л░л║к╖к╞кккыкл!!к╡к├к╡к╚юя▀■к╦",
    "0x3ac1=0x3af4": "╠э╠№бсЁдкЄк╚кщк╗кэ!╦■┘¤к╧к╚к├кпк╦тв█╒к╟кнк╚кык└кэкж",
    "0x3af7=0x3b1c": "к╩!бдбдбдкккфк╕!╓┼те▀ЎкЄкпкьк├!!б╣",
    "0x3b34=0x3b75": "л░льлдкм╘июфкЄкфкск┐к╚┌дкдк╞ь╤▀цк╬┘═ю▄кЄуўк├к╞к╖к▐к├к┐лмлыл╨-л╦бг",
    "0x3b77=0x3bb8": "к╣к├клкъ╓╒к▒бскєк╟кдкпьщ█░к└к├к┐кмбв╙▐╘июфл░льлд▄╓№└к╬№екЄ┌дкдк╞бв",
    "0x3bbb=0x3be2": "клк─к╞к╬цЁ·ь·¤▐└к╓къкЄс╠кщк╗кык╬к└к├к┐бг",
    "0x3be7=0x3c1c": "л░ль-лд!╨╤╙°к│к╜╧■х╞кЄк╥к├°┌кщкик╞кфкыклкщк╩кб!!б╣",
    "0x3c36=0x3c6b": "бдбдбдк│к╬кшкжк╦лщл│л╦лвьд▌┴к╬═╘▀гЄв╙склкщкфк├к╞╒╬к┐бв",
    "0x3c6d=0x3ca2": "кдк▐кфб║уъбсб╗флЁщк┐к┴к╚√╝к╨кькыфлЁщк┐к┴к╧бвл┐лылсл╔бв",
    "0x3ca5=0x3ccc": "лвл▒лэлєкЄбск╞к│к╬лвлєл╪лылрк╦бдбдбдбдб╣",
    "0x3cd1=0x3cf2": "л╝лэ╬чтгк├к╞клк├к│кдкдкяк═бдбдбдб╣",
    "0x3cf6=0x3d29": "квк╬х┤к╡к╟кткжлвлєл╪лылр╙▐∙╩═┼═п∙╩╬бк╬╬чтгк╟к╖кч!?",
    "0x3d2b=0x3d5e": "к╜кьк└к▒к╕кук╩кплсллк╦кт╦нкпк╞бвк╡кщк╦к╡кщк╦!!╠┐╧░",
    "0x3d61=0x3d7e": "лвл░льл├л╖л╓к╩рї╠лк└к├к╞!!б╣",
    "0x3d82=0x3db5": "бдбдбдквк┐к╖кткж╠╜кск┐кя!!я╛╙▀бвл╝лэ╬чтгкЄ╒кк╚к╖к╞",
    "0x3db8=0x3dc3": "╠╕к╗кы!!б╣",
    "0x3dc7=0x3dfa": "бдбдбдэ╤╥╖к└к▒к╔к╜кьк╧┘э╫тк═бгбск╦кшкык╚л╝лэ╬чтгк╦к╧",
    "0x3dfc=0x3e2f": "б║лслдл╖лвб╗к├к╞┘гюёк╬чєк╡кєкмкдк╞к═бв╬чтгк╧чєк╡кєк╦",
    "0x3e31=0x3e64": "л╛л├л│лєк╩кєк└к├к╞бдбдбдбд∙╝к╟ктбвЇ╕▐┼к▀к┐кдк╦╤╗╒Єк╩",
    "0x3e67=0x3e76": "ь╤кщк╖кдкякш!б╣",
    "0x3e7b=0x3eac": "к│кщк├бвк╜к│!!к╡к├кнклкщ∙╝кЄ№ек╖к╞кдкыкєк└!!б╣",
    "0x3eb0=0x3ef1": "╥·▄ъ(ы╢юцюЎ┌ж)у┴╙█к╦╘Ёк┐∙е▌гк╩Є▒у█кЄ▀цклк╖к╞бвлвлєл╪лылр╙▐∙╩╥ок╬",
    "0x3ef3=0x3f34": "═┼═п∙╩▌╗к╦яс╬чтгк╚к╖к╞▌╣ьЄк╖к┐л╝лэк╧бвл╚л╣ллклкщ╧¤к├к┐¤н▐╓кдя╖к├к╞",
    "0x3f36=0x3f77": "лслдл╖лвк╦л╫лэл▌-л║!!∙╝№▐ктл╒лщкьк┐х└к▓╧гбвфук╖к╬ьщтвк╟к╚кжк╚кж",
    "0x3f79=0x3fba": "╠┐√цк╖к╞к╖к▐к├к┐бг╠┐√цк╖к╞┌т╥┤кмк┐к├к┐╨╤к╟ктлслдл╖лвк╦л┘л┐л┘л┐к╟бв",
    "0x3fbd=0x3ffc": "╦╗ы∙¤нк╧╨Ўкъ╘│кЄк╗к║к▐к├к╣к░╩лк╦╧¤кык╚кдкжл▐лдл█-лрл╤л╤к╟квкыб╣",
    "0x4017=0x4038": "л╗лєл╗-!кк№ек╖к╖к╞!кк№ек╖!!б╣",
    "0x403d=0x4066": "л╗лєл╗-бвквк╬к═!л▄лпк═!э╞ьэк═!бдбдбдб╣",
    "0x406b=0x40a0": "к╧кдк╧кд!бдбдбдк▀кєк╩к╟ьщ╙°к╦№ек╖к┴ку┌дк│кик╩кдкякшб╣",
    "0x40a5=0x40c0": "л╗лєл╗-!кк№ек╖к╖к╞кш!!б╣",
    "0x40c5=0x40ea": "кяклк├к┐кябдбдбдк╔кєк╩кк№ек╖кмкдкд?б╣",
    "0x40ef=0x411e": "кдк─ктк╬лфл─--!!кдк─ктк╬кк№ек╖кмкдкд-!!б╣",
    "0x4123=0x413c": "бдбдбдк▐к┐квк╬кк№ек╖!?б╣",
    "0x4140=0x4173": "к╜--!л░льлдк╚л╝лэк╬лфл─-!л░льлдк╚л╝лэк╬кк№ек╖кЄ",
    "0x4176=0x4181": "к╖к╞-!!б╣",
    "0x4185=0x41b8": "к╧квбдбдкдкдкябвк╔кжк╖к╞к╜кєк╩к╦╪№█▄кдк╬клк╖кщбдбдбд",
    "0x41ba=0x41ed": "к╜кьк╕кукв№ек╖к▐к╣клкщбвЁбклк╦к╖к╞к═бгквкык╚к│кэк╦бв",
    "0x41ef=0x4222": "л░льлдк╚л╝лэк╚кдкжёък╬╒▐кдс┤╥┤кмкдк▐к╖к┐бгл░льлдк╧бв",
    "0x4225=0x4248": "█▄ы▐к╦¤╩кп┌╕к╖кд█екЄк╖к╞кдк╞бдбдбдб╣",
    "0x424c=0x428d": "л╙лпл╚лык┐к┴к╦═║·┴л╚л╣ллл╩кЄс└клкьк╞к╖к▐к├к┐лслдл╖лвк╧бв∙╝к╚кл▀цкн",
    "0x428f=0x42d0": "э╤к├к┐эн═ък┐к┴кЄєвксбв═╡фоъ┬кЄ╦як╞бвьщьэктЁ─кпквк╬°┴√·к╩л╚л╣ллл╩кЄ",
    "0x42d2=0x4313": "с╠кщк╗кшкжк╚бв▄¤к╚к╩к├к┐л╝лэк╚к╚ктк╦╥¤╪╧к╩╪▀ьэкЄсък├к╞кдкыбгл░льлд",
    "0x4316=0x4347": "к┐к┴к╚╬жк┤к╖к┐квк╬┘│·╧к╬ьэбскЄ▐╓кдїєк╖к╩кмкщбдбдбд",
    "0x435f=0x437a": "лмлыл╨-л╦к╬ккк├к╡кєк╪бдбдбд",
    "0x437e=0x43bd": "__ък╤иклкд?бдбдбд∙╝кфкщбвї╠╨╬кск├кнкъ╓╒к▒к┐к├к╞∙жк╬бск╦┌дкдк┐",
    "0x43bf=0x43fe": "__кткєк╟к═бгк╣к│к╖у¤█╒к╦к╩к├к╞бвк│к╬твЄ╡кЄ▀Ўкдк┐кєк└бдбдбдбдбд",
    "0x4400=0x443f": "__хяк╬█░к╧бвк╜кьк╩кък╦кжк▐кпкфк├к╞кыбг╘июф╩│хЎклкщЁыкЄсйк├к┐к╬",
    "0x4442=0x4483": "__к╧Є▒к├к╞кык└кэкж?╨╤к╧бвк╜кькшкъс┤к╖к╧к▐к├к╚кжк╩▐┬▐└кЄк╖к╞кыбг",
    "0x4487=0x44c8": "__б║ы╢юц█б╧▐хЎб╗к╚кдкжклбдбдбдклк├к│кшкпхыкик╨л╚льл╕лу-л╧лєл┐-",
    "0x44ca=0x450b": "__к├к╞кфк─к╡бгк▐кв·╣кл▄Ї·╣клэ▐тжк└к▒к╧ь╤ьщ█├╙╬кєк╟кыкєк╟к═бв╩│ко",
    "0x450d=0x454e": "__к╬█░к╧клк╩къ▀╛бсбгьэбс╤иф┼к╩▀ц№└кЄф┼к╖крк╦к╧їЎ▌┬к├к╞к╚к│кэк└бг",
    "0x4551=0x4592": "__бдбдбдк┐к└к═бвї╠╨╬к╜кєк╩к╬кєк╙кък╖к┐▀ц№└к╦к┴кчк├к╚°щкнк╞кнк┐бг",
    "0x4596=0x45d7": "__к╜к│к╟к┴кчк├к╚▀╙╙╚к╖к┐кдкєк└к▒к╔бдбдбду∙к╧к▐к┐╘июф╩│хЎк╦бскэкж",
    "0x45d9=0x461a": "__к╚▐╓кжкєк└бдбдбдбдк╔кжклк╩?бдбдбдбдкфк├к╤къбвккк├к╡кєк╚ї┌кдк─",
    "0x461d=0x465e": "__ї┌кякьк─кфк├к╞кы█░кмбв╪▀ьэф┼к╖кдкшкжк╩╤икмк╣кык╬к╧хяк└к▒клкд?",
    "0x4662=0x46a3": "__к╚к╦клкпбв╩│хЎюв╦╥к╬▐└у╖кск╚к╖к╞к╡к├кнккк├к╡кєк╬╩лклкщккэнк╡кє",
    "0x46a5=0x46e6": "__к╬▐╨Є╪кЄьщ╪▌бв╘ик▐к╗к╞кткщк├к┐кшбгк▐квбвкдк║кьк┴кукєк╚┌ўк╣клкщ",
    "0x46e8=0x4729": "__у¤█╒к╖к╩кпк╞кдкдбдбдбдк╜кьк╕кубвк│кьклкщкткшкэк╖кпк╩!ккк├к╡кє",
    "0x472d=0x476a": "___________________л░льлдбдл╒лщл├л╖лхл╧лєл╔",
    "0x476f=0x47a4": "бдбдбдбдбдбдбдбдбдбдбдбдбдбдл░бвл░льлдк╬хп╒═кйбдбдбдб╣",
    "0x47bc=0x47ef": "квк╬у┴бв╠╕╘▒к╖к╞кфк├к┐ы┌кЄ╪╬кькфкмк├к╞!╩╞чЎк╖кэкш!",
    "0x47f2=0x481d": "╨╤╙°к│к╜щ╗▐їк╗кє!я╛╙▀к╦щ╗▐їк╗кєклкщк╩!!б╣",
    "0x4821=0x4862": "╥┴кък╬квк▐къбвк╜к╬¤нкэк╟к█кпк╜с┼крл░льлдк╦╤ик┼кпк│к╚к╣кщк╩кпяыёщк╦",
    "0x4865=0x489c": "·┬кпл╔лщсвк╟б║л░льлдЇї°┌б╗кЄ╠▒кпрекжлмлыл╨-л╦к╟квк├к┐бг",
    "0x48b4=0x48c9": "лвлєл╪лылр═┼═п∙╩№х№хэ▐",
    "0x48dd=0x48f2": "лялдлялдлмлфлмлфбдбдбд",
    "0x48f6=0x4929": "бдбдл╚л╣ллы╢юц╧╪к╧к╜кьэ╗бскмьщк─к╬▀ц┘дбск╚к╡кикдкикы",
    "0x492c=0x4961": "▄▄∙ъ╧░Ёубск╟бвк╜к╬█┴ъ█╥Ў╒Їкккшк╙э╗╨∙сє▄╓╤ж╥Ўк╧бдбдбдб╣",
    "0x4966=0x498f": "к█кжбвквк╬х┤к╡к╟к╩клк╩кл╙▐к╖к┐ктк╬к╟к╣к╩б╣",
    "0x4993=0x49c6": "к╩к╦бвк┐к▐к┐к▐л╚л╣ллы╢юц╧╪кЄ█б╠╕к╖к┐к└к▒к└бглщл├лн-",
    "0x49c9=0x49d4": "к╦╬жкокєкшб╣",
    "0x49d8=0x4a0b": "бдбдбдк┐к╚кик╜кжк└к╚к╖к╞ктбвквк╬л╚л╣ллы╢юц╧╪к╟к╣к╛!",
    "0x4a0e=0x4a41": "э■кд╩рбвфск╬л┘-лык╦°╨к▐кьс┘к▒к╞кнк┐бсрук╬ы╢юц╧╪!б╣",
    "0x4a45=0x4a78": "бдбдк┐к└бвк│кьк╧квкпк▐к╟ктбск╩кєк╟к╣кмбвк╔кжкфкщ∙ик╧",
    "0x4a7b=0x4aae": "ьдюёк▒к╖клкщк╠▐┬▐└к╦твкЄц°кск╞кдк┐к╜кжк╟к╣к╩бдбдбдб╣",
    "0x4ab3=0x4acc": "б║к▒к╖клкщк╠▐┬▐└б╗к╚к╧?б╣",
    "0x4ad1=0x4ae8": "к▒к╖клкщк╠▐┬▐└к╟к╣!!б╣",
    "0x4aec=0x4b1f": "бдбдбдкккфкккфбвл╝лэ╬чтгк╬╦╗ц╤кмЁ√кяк├к┐кшкжк╟к╣к╛!",
    "0x4b22=0x4b3f": "бдбдл╓лщл▄-!!л╓лщл▄-!!б╣",
    "0x4b47=0x4b66": "л╤л┴л╤л┴л╤л┴л╤л┴!!бдбдбдбдбдбд",
    "0x4b6a=0x4b9d": "(кв~квбвллл├л┐къкдк╩кббдбдбдкдкнк╩къл░льлдк╬╥┐кмбв",
    "0x4b9f=0x4bd2": "б║╘июфклкщЁыкЄсйкж!б╗к╩кєк╞хыкдїєк╣кткєк└клкщбв╩мкЄ",
    "0x4bd4=0x4c07": "Єек╞х∙к╖к╞▀Ўкдк┐лтлєкмбвк▐к╡кл∙╩№х▀█кЄсЇк▒кык╚к╧к═кз",
    "0x4c09=0x4c3c": "бдбдбдк╜кьк╦к╖к╞ктбвк│к╬б║∙╩т·═гб╗к├к╞к╬к╧к╔кжктрїк╦",
    "0x4c3f=0x4c4c": "∙ъкяк═кик╩)б╣",
    "0x4c50=0x4c91": "квк╬ьщ╦ьк╬¤нбв╘июфклкщЁыкЄсйк├к┐ктк╬к╬ўхк╦кфкык│к╚ктк╩кпбв╩мкЄЄек╞",
    "0x4c93=0x4cd6": "х∙к╖к╞кдк┐л╝лэкмк┐кякркьк╦▀Ўкн▀╛к▓к┐б║л╚л╣лл┘■┘еы╢юц╧╪к╬ъє╤ж╧░Ёубсб╗",
    "0x4cd8=0x4d19": "к╧∙╩═гк╦╙▐кнк╩┌у·┬кЄ√╝к╙бвлвлєл╪лылр═┼═п∙╩№х▀█к▐к╟тгбск╡кькык│к╚к╦",
    "0x4d1b=0x4d5c": "к╩к├к┐бгк┐кмбвЇ°кск╞к╬╦╗ц╤к╦л╣-л─эмк╟к╬к╛кєк└ктк╬к╬бвЁ─кпктклк─к╞",
    "0x4d5f=0x4d9a": "к╬э╗ыж╤ик▐к▐к╩╘июф╩│хЎк╦▐╓кдкЄё╦кщк╗к╞кдкыл╝лэк╟квк├к┐бдбдбд",
    "0x4de5=0x4e18": "л▀-к╧л╕лч-лл-бдбдбдлпл╜▀цыЄ╤ик╩Ї╕▐┼╙╣к╬┘═кЄ╘икєк╟",
    "0x4e1a=0x4e4d": "к│к│к╟лнлх-л╚к╩ккя┴кЄ╦╥кдк╞кдкыл╢л▐л╣!!бдбдбдк▐бв",
    "0x4e4f=0x4e82": "ккя┴к╚кдк├к╞кт╪ук├к╞кык╬к╧л┐лэл├л╚лл-л╔к└к▒л╢л▐л╣км",
    "0x4e85=0x4e9a": "бдбдбд╪ткжл╢л▐л╣кл?б╣"
}