{
    "0x7=0x16": "デ-モンを倒せ!",
    "0x23=0x44": "うう···寒い···結構冷えるな」",
    "0x4d=0x6e": "それだけ着■んで、まだ寒いのか?」",
    "0x77=0x98": "···若いようでも結構ジジイずら」",
    "0xa0=0xbf": "へっ!勝手なこといいやがって!!",
    "0xc1=0xe0": "それより、何でお前はそんな格好で",
    "0xe3=0xf4": "平氣なんだよ!!」",
    "0xfd=0x112": "每日鍛えてるずら!!」",
    "0x11a=0x139": "いくら鍛えてるっても、異常だぞ!",
    "0x13c=0x14b": "その格好は!!」",
    "0x154=0x169": "ゼロは寒がりなんだな」",
    "0x172=0x18b": "お前達が異常なんだよ!!」",
    "0x194=0x1b7": "でも、本■に寒いわね。何でかしら?」",
    "0x1bf=0x1de": "みんな!氣をつけて··奧に空間の",
    "0x1e0=0x1ff": "歪みが集中しているところがあるわ",
    "0x202=0x209": "···」",
    "0x212=0x21f": "空間の歪み?」",
    "0x227=0x246": "おそらくヘブンズラダ-のせいだわ",
    "0x248=0x267": "···異なった空間だけじゃない·",
    "0x269=0x288": "異なった時間に住むモンスタ-まで",
    "0x28b=0x2a8": "この時空に召喚している···」",
    "0x2b0=0x2cf": "またロクでもないモンが出てきそう",
    "0x2d1=0x2f0": "だな···こっちを選んで失敗した",
    "0x2f3=0x2fa": "かな?」",
    "0x302=0x321": "今さら言ってても始まらねぇさ··",
    "0x324=0x337": "とっとと行こうぜ!」",
    "0x33f=0x35e": "エリシア、待っててね!もうすぐ、",
    "0x361=0x370": "會えるから!!」",
    "0x37d=0x38e": "こいつは何だ!?」",
    "0x396=0x3b5": "デ-モン!魔界でも高位に位置する",
    "0x3b7=0x3d6": "魔王までもがこの世界に召喚されて",
    "0x3d9=0x3e6": "いるなんて!」",
    "0x3ef=0x404": "蹴散らしてやるさ!!」",
    "0x410=0x42f": "ぶわっくしょい!···う\"う\"。",
    "0x432=0x449": "風邪を引きそうだ···」",
    "0x452=0x465": "■しかったずらな?」",
    "0x46d=0x48c": "そこまでいくと···何だか薄氣味",
    "0x48f=0x49e": "惡いぜ、ハッグ」",
    "0x4a6=0x4c5": "なんか、まわりの風景が妙に歪んで",
    "0x4c8=0x4df": "見えるような氣がするな」",
    "0x4e7=0x506": "(間違いない···ヘブンズゲ-ト",
    "0x508=0x527": "とラダ-が共振して、歪みを增幅さ",
    "0x529=0x548": "せている···この世界全■が、大",
    "0x54b=0x560": "きく軋み始めている)」",
    "0x569=0x58a": "どうしたの?レディ。何か感じる?」",
    "0x592=0x5b1": "···ハッ··い、いいえ····",
    "0x5b4=0x5d1": "大丈夫よ。今は特に何も···」",
    "0x5d9=0x5f8": "何だか不思議ね、あなたがボンヤリ",
    "0x5fb=0x60c": "するなんて···」",
    "0x614=0x633": "女神といえども、たまには氣を拔く",
    "0x635=0x654": "ことくらいあるさ···俺はそんな",
    "0x657=0x66c": "レディの方が好きだね」",
    "0x675=0x694": "まったく、氣の多い男だな···」",
    "0x69c=0x6bb": "··女神樣を口說くとは、すンゲ-",
    "0x6be=0x6d1": "罰■たりずら···」",
    "0x6da=0x6f5": "バカ!な、何言ってやがる!」",
    "0x6fe=0x71f": "フフフ···さあ、行きましょう!」"
}