{
    "0x7=0x18": "손을_쓰러트려라!",
    "0x36=0x55": "드디어_와주었군.기다리고_있었",
    "0x58=0x5b": "다」",
    "0x63=0x80": "허튼소린_들을_시간이_없다.",
    "0x83=0x98": "엘리시아는_어딨나?」",
    "0xa0=0xbf": "서두르지마라.나도_기쁨을_느끼",
    "0xc1=0xe0": "게_해달라구.지금_천계의_문을",
    "0xe2=0x101": "여는_신들의유산이_다_갖춰졌다",
    "0x104=0x11d": "는_위대한_기쁨을...」",
    "0x125=0x144": "기쁨?손,당신에게_전해줄_말이",
    "0x146=0x165": "있어요..바이퍼가...죽었어요",
    "0x168=0x16f": "...」",
    "0x178=0x183": "...!!」",
    "0x18b=0x1aa": "바이퍼는_마지막까지_당신을_불",
    "0x1ac=0x1cb": "렀어요..당신과_함께_파랜드에",
    "0x1cd=0x1ec": "갈_수_있다고...그것만을_믿",
    "0x1ef=0x1fa": "으며...」",
    "0x203=0x210": "...그래?」",
    "0x218=0x237": "그래라뇨!...그것뿐!?다른_",
    "0x23a=0x255": "무슨_할말이_없는건가요?」",
    "0x25d=0x27c": "이제_막_신들의유산을_손에_넣",
    "0x27e=0x29f": "으려고_하는_나에게_죽음따윈__",
    "0x2a1=0x2c0": "아무런_의미도_없다.모든_것은",
    "0x2c3=0x2d8": "내_손안에_있다..」",
    "0x2e1=0x2f4": "너,너무해라리!!」",
    "0x2fc=0x31b": "이봐,손!우리가_간단히_헤븐즈",
    "0x31d=0x33c": "게이트를_넘겨줄거라_생각하나?",
    "0x33f=0x350": "_________",
    "0x358=0x377": "헤븐즈게이트?..후후,이제_그",
    "0x379=0x39a": "런건_별로_중요하지_않다.내가_",
    "0x39c=0x3bb": "말하는_신들의_유산은_엘리시아",
    "0x3be=0x3d1": "와_메이시아...」",
    "0x3da=0x3e7": "......」",
    "0x3f0=0x405": "엘리시아와...나?」",
    "0x40d=0x42c": "그렇다.신의_무녀인_엘리시아와",
    "0x42e=0x44d": "메이시아..즉,한쌍의_엔젤리나",
    "0x44f=0x46e": "가_세계를_지배할_힘을_가지고",
    "0x471=0x490": "있는_신들의_유산이다」____",
    "0x499=0x4b4": "!?...엔젤..뭐라구?」",
    "0x4bc=0x4db": "엔젤리나...거점의_수호,대_",
    "0x4dd=0x4fc": "요마전투,종족의_방어등을_위해",
    "0x4ff=0x516": "태어난_수호천사...」",
    "0x51e=0x53f": "무슨_말을_하는지_모르겠어!__",
    "0x542=0x55b": "메이시아가..천사라고?」",
    "0x563=0x582": "이전에_내가_엘리시아를_붙잡았",
    "0x584=0x5a3": "을때,메이시아가_뭔가로_변했었",
    "0x5a5=0x5c4": "지.그것이_무한한_위력을_가진",
    "0x5c7=0x5de": "엔젤리나의_전투형태다」",
    "0x5e6=0x605": "거짓말!그런거_안믿어요!대체_",
    "0x608=0x623": "...당신은_누구죠?!?」",
    "0x62b=0x64a": "냉정하군..잊었나?영원의_소녀",
    "0x64c=0x66b": "여.불과_4500년전에_너희와",
    "0x66e=0x687": "아는_사이였었는데...」",
    "0x694=0x6ab": "년,전이라고!?...」",
    "0x6b3=0x6d2": "천계의_문을_넘은_이유로_하늘",
    "0x6d4=0x6f3": "에서_추방당한_날,이_세계에_",
    "0x6f5=0x714": "적응할_수_있도록_도와준게_다",
    "0x717=0x72a": "름아닌,너희들이다」",
    "0x733=0x746": "타천사라는_건가?」",
    "0x74e=0x76d": "난_천사다!그것도_여기있는_가",
    "0x76f=0x78e": "짜가_아닌_신의_사도인_진짜_",
    "0x791=0x79c": "천사...」",
    "0x7a4=0x7c3": "그래서...이_곳_수호천사의_",
    "0x7c6=0x7d5": "궁전에....」",
    "0x7dd=0x7fe": "과연_여신답군..난_이미_강력한",
    "0x800=0x821": "천사의_군단을_손에_넣었다.신들",
    "0x823=0x842": "의_힘을_온몸으로_느껴봐라!」",
    "0x845=0x85e": "_____________",
    "0x873=0x892": "포기해라.상대가_천사던_신이던",
    "0x894=0x8b5": "우린_물러서지_않는다.엘리시아_",
    "0x8b8=0x8cb": "는_어디에_있지?」",
    "0x8d3=0x8f2": "후후..어리석군.타천사인_나의",
    "0x8f4=0x913": "날개는_검지만_힘은_금색날개를",
    "0x915=0x936": "가진_천사와_똑같다!진짜_천사의",
    "0x939=0x94a": "힘을_보여주마!」",
    "0x956=0x975": "역시...이것이_신의_뜻인가_",
    "0x978=0x981": "....」",
    "0x98a=0x9a3": "엘리시아는_어디있나!?」",
    "0x9a9=0x9c8": "엘리시아는_이미_이_유적군의_",
    "0x9ca=0x9e9": "일부로_변했다.말하자면_너희_",
    "0x9eb=0xa0c": "주위에_있는_이_유적자체이지..",
    "0xa0f=0xa2c": "곧,유적의_일부가_될것이다」",
    "0xa35=0xa4a": "...말도_안돼!?」",
    "0xa50=0xa6f": "이_궁전의_천사들을_각성시키기",
    "0xa71=0xa90": "위해_필요_했었다.이_유적군의",
    "0xa92=0xab1": "분신이라고도_할수_있는_엘리시",
    "0xab4=0xad3": "아를_천사각성의_촉매로...」",
    "0xadc=0xafb": "무슨_짓을...해버린거야!!」",
    "0xb0c=0xb19": "뭐!뭐지??」",
    "0xb22=0xb29": "지진?」",
    "0xb31=0xb50": "『공명』이다..본래_있어야_할",
    "0xb52=0xb71": "곳이_아닌곳에서_정령석과_여신",
    "0xb74=0xb95": "그리고_무녀가_모여버렸다...」",
    "0xb9d=0xbbc": "그래서..시공의_왜곡에_의해서",
    "0xbbe=0xbdd": "『천계의문』이_나타나려_하고_",
    "0xbe0=0xbed": "있어요...」",
    "0xbf5=0xc14": "아,아까부터_말하고_있는_천계",
    "0xc17=0xc30": "의_문이란게_뭐야라리?」",
    "0xc38=0xc57": "모든_시공,모든_세계로_통하는",
    "0xc59=0xc78": "문이다.이_세계를_지배했던_종",
    "0xc7a=0xc99": "족에_의해_만들어지고_그들과_",
    "0xc9c=0xcaf": "함께_봉인되었지.」",
    "0xcb7=0xcd6": "그러나_이런_상태로_왜곡된_채",
    "0xcd8=0xcf7": "나타나면_어떤_곳으로_연결될지",
    "0xcf9=0xd18": "모릅니다.잘못하다간_이_세계마",
    "0xd1b=0xd2c": "저_잃게_됩니다」",
    "0xd34=0xd53": "올바른_일에_썼다면_천계의_문",
    "0xd55=0xd74": "을_통해서_아득한_신들의_대지",
    "0xd76=0xd95": "파랜드로_인도했을_테지..._",
    "0xd97=0xdb6": "하지만_이젠_그것도...」__",
    "0xdb9=0xdc6": "_______",
    "0xdd3=0xdea": "이것을...넘겨주겠다」",
    "0xdf3=0xe08": "헤븐즈래더...로군」",
    "0xe0e=0xe2d": "천사군단을_이끌고_나를_추방했",
    "0xe2f=0xe4e": "던_천상을_공격하려던_계획은_",
    "0xe50=0xe6f": "이루지_못했다...이곳은_역시",
    "0xe71=0xe90": "너희들의_세계다..있는_힘껏_",
    "0xe93=0xea8": "지키길_바란다...」",
    "0xeb1=0xec4": "손...당신...」",
    "0xecc=0xeeb": "나는_바이퍼가_있는_곳으로_가",
    "0xeed=0xf0c": "겠다.그_아이는_외로움을_잘타",
    "0xf0e=0xf2d": "니...지금쯤_쪼그려서_울고_",
    "0xf30=0xf3d": "있겠지...」",
    "0xf5a=0xf77": "있는_힘껏..지키라고...」",
    "0xf80=0xf93": "엘리시아누나...」",
    "0xf9c=0xfb5": "엘리시아는_내가_구한다」",
    "0xfbe=0xfd7": "구하다니...어떻게!?」",
    "0xfdf=0xffe": "나도몰라!...하지만_무슨_방",
    "0x1001=0x1014": "법이_있을거야!!」",
    "0x101c=0x103b": "그렇다면_그전에_세계를_구해야",
    "0x103d=0x105e": "하지_않을까..뭘_하려고_해도,",
    "0x1060=0x107f": "이_세상이_없어지면_아무런_소",
    "0x1082=0x1091": "용없잖아...」",
    "0x1099=0x10ba": "정령석들을_원래_위치로_돌려놓읍",
    "0x10bc=0x10db": "시다.그렇게하면_적어도_왜곡이",
    "0x10de=0x10f7": "커지는_일은_없을겁니다」",
    "0x10ff=0x111e": "이곳에선_시간의_신전쪽이_가까",
    "0x1121=0x1126": "워요」",
    "0x112f=0x114e": "늦지_않았으면_좋을텐데...」"
}