{
    "0x8=0x23": "квквбвкфк├к╚ї┌кдк─кнк▐к╖к┐б╣",
    "0x2a=0x41": "лвлъл╖лв!к╔кжк╖к┐кєк└?",
    "0x44=0x59": "к╜кьк╦л╟лг-л╬к▐к╟!б╣",
    "0x60=0x79": "к╜кьк╧к│к┴кщк╬л╗лъл╒к└кшбг",
    "0x7c=0xa1": "╙у╬оу╥к╔к│кэк╕кук╩кпк╩к├к╞кыкшкжк└кмб╣",
    "0xa8=0xcb": "ш▌╘┤к╦є╖кдк╞к▀кьк╨бв∙╝к└кл╙▐бск╩к│к╚",
    "0xcd=0xf0": "к╦к╩к├к╞кык╖бв№╦к╞к╞ї┌кдклк▒к╞╒╬к┐кє",
    "0xf3=0xfa": "к╟к╣кшб╣",
    "0x101=0x11e": "квк╩к┐км╒╬к╞кпкькык╚у¤╦нкдкябг",
    "0x121=0x132": "ї╜к╬█░к╧╙▐э█▄¤?б╣",
    "0x139=0x15c": "кикибвлслыкмкфк├к╞кпкьк╞кдк▐к╣клкщб╣",
    "0x163=0x186": "квкєк▐кък╬кєк╙кък╚№ектк╖к╞кдкщкьк╩кд",
    "0x189=0x1a6": "кшкжк└бгю╪к╡кєк╬ккїєк▐к╖к└к╛б╣",
    "0x1b2=0x1d1": "кшкп╒╬к┐к╩бгбск▒кщк╔ктксбдбдбдб╣",
    "0x1d9=0x1e8": "л╨лєл╤лдлвкл!б╣",
    "0x1ee=0x20b": "к╜кжк└!ф▓км┘гк╧лллдл╝лы█╫э╔!",
    "0x20e=0x22f": "╧■х╞кщк╦▀пк╡кьк┐л╧лдл╝лєк╬Ёйк└!б╣",
    "0x236=0x259": "р╗к╦ю·кЄ▐┬╬╨к▒к╞╒╬к┐к╬к╧бвквк╩к┐к┐к┴",
    "0x25c=0x269": "к╬█░к╟к╖кч!б╣",
    "0x26f=0x28c": "ю·к╟к╧к╩кдбгуък╦▐┬кик╖с┤╥│кшбг",
    "0x28e=0x2b1": "к╜к╬╤ьклкд·ьЁ═к╧бвф▓бск╦▄щк▓кщкькык┘",
    "0x2b3=0x2c0": "кнктк╬к╩к╬к└!",
    "0x2c3=0x2de": "к╡квбвф▓кмктк╚к╪╒╬кыкм╒▐кдб╣",
    "0x2e4=0x307": "к╔кжк╖к╞¤х·ь╨бк├к╞к╬к╧к▀кєк╩╘╥к╕к│к╚",
    "0x30a=0x321": "к╖клхыкяк╩кдк╬клк╖кщ?б╣",
    "0x32c=0x34f": "лпл├бдбдл╧л╧л╧бдбдбдъб╒▐кпбв╪кш▌х╞кЄ",
    "0x351=0x374": "ў▄к▒к┐к╚к╧кдкибвс╢ям╧■х╞кщк╦унк┴┘═к╧",
    "0x376=0x399": "к╩кдк╬к└бдбдбд╪к═гк╬╒Їк╧бдбдбдк│кєк╩",
    "0x39c=0x3b9": "ктк╬к╟к╧бдбдбдк╩бдбдкдбдбдбдб╣",
    "0x3c1=0x3da": "к╜кьк╧к╔кжкдкжк│к╚к└!?б╣",
    "0x3e0=0x403": "Є▒кък┐к▒кьк╨бв▌┴к╪·╝к▒бдбдбд╧■х╞кщкм",
    "0x405=0x428": "ўок╖к╞кдкыктк╬ктбвк╜к│к╦квкыбдбдбдбд",
    "0x42a=0x44d": "к└кмбдбдбдк╜к│к╟╧■х╞кщкЄ╙тк├к╞кдкыкт",
    "0x450=0x473": "к╬к╧бв▐▌бвк└к▒к└бдбдбдлмл╧л├бдбдбдб╣",
    "0x47a=0x49d": "кдк├к┐кдбв▌┴к╦∙╝кмквкык╚кдкжк╬к└кэкж",
    "0x4a0=0x4a9": "бдбдбд?б╣",
    "0x4b0=0x4d3": "к╚к╦клкпбв▌┴к╪·╝кпк╖клк╩кдкшкжк└к╩б╣",
    "0x4de=0x4f5": "к┐к├бвЁ╛к▒к╞~~~к├!!",
    "0x4f8=0x50f": "бдбдбдк╞бвквкь?ю№∙╗?б╣",
    "0x517=0x536": "лдлялє!?лдлялєк╕кук╩кдкл!?б╣",
    "0x53c=0x55f": "ю№∙╗!квк├к╖кЄЁ╛к▒к╦╒╬к╞кпк└к╡к├к┐кє",
    "0x562=0x583": "к╟?кп~~к├бв╩я╠нк├!ки?ъ▐кж?б╣",
    "0x58b=0x5a4": "к╔кжк╖к╞к│кєк╩к╚к│кэк╦?б╣",
    "0x5aa=0x5cd": "кдкфквбвквк├к╖к╬┘ыщ╕бскЄ№ек╖к╞№▐к├к╞",
    "0x5cf=0x5f2": "к┐кщбвкдкнк╩къ╪к┌кк╬╙▐╧╪км·▐кьк▐к╖к╞",
    "0x5f4=0x615": "к═бг№╦к╞к╞╘▒к▓к╞╒╬к┐к╚к│к╩кєл╣кшбг",
    "0x618=0x635": "кєк╟бвю№∙╗к╧к╔кжк╖к╞к│к│к╦?б╣",
    "0x63d=0x64a": "у∙к╧бдбдбдбдб╣",
    "0x656=0x66f": "бдбдбдк╚бвхыкжкяк▒к╩кєк└б╣",
    "0x676=0x695": "к╩кык█к╔к═бдбдкшкжкмк╣!квк├к╖кт",
    "0x697=0x6b6": "·Ё╒Їкдк┐к╖кфк╖кчкжбгквк├к╖кмь¤кь",
    "0x6b8=0x6d7": "к╨бвюё№▐к╬х╞к╦∙╝ктклкткжк▐кпкдкп",
    "0x6da=0x6ef": "к│к╚╩ръ▐кдк╩кдк├л╣!б╣",
    "0x6f7=0x712": "к╜бдбдбдк╜кжк└к═бгЁ╛клкыкшб╣",
    "0x71d=0x736": "ю№∙╗!ю№∙╗к╕кук╩кдк├л╣клб╣",
    "0x73d=0x75a": "лдлялє!?лдлялєк╕кук╩кдкл!?",
    "0x75d=0x776": "к╔кжк╖к╞к│кєк╩к╚к│кэк╦?б╣",
    "0x77c=0x7a1": "кдкфквбв╪к┌кк╬╙▐╧╪клкщ╘▒к▓№▐к├к╞к┐кщбв",
    "0x7a3=0x7c8": "ю№∙╗к┐к┴к╬эмкм╠╕кикык╕куквкък▐к╗кєклбг",
    "0x7ca=0x7e7": "№╦к╞к╞ї┌кдклк▒к╞╒╬к┐кєк╟к╣кшбг",
    "0x7ea=0x801": "ю№∙╗к╧к╔кжк╖к╞к│к│к╦?б╣",
    "0x809=0x816": "у∙к╧бдбдбдбдб╣",
    "0x821=0x850": "к╩к╝бвк▐к┐╪к┌кк┐к┴км·▐кькыкшкжк╦к╩к├к┐к╬к└кэкж?",
    "0x853=0x872": "╪кш▌км╙юк╡кьк┐к╚кдкжк╬к╦бдбдбдб╣",
    "0x87d=0x8a0": "э╞хибвк▐к┐∙╝ь╤клї╜к╬╥жкмк╡кщкякьк┐бг",
    "0x8a2=0x8d3": "ккрЄк╬√∙к▒┌кк╦к╡кщкякьк┐к╦ъ▐кдк╩кдбгквквбвк╔кжк╖к┐",
    "0x8d6=0x8e5": "кщкдкдкєк└кэкжб╣"
}