{
    "0x7=0x16": "ю╪кЄюя╪■к╡к╗кэ!",
    "0xc2=0xdb": "╩рк╦квк├к╞кшклк├к┐к╟к╣кебг",
    "0xdd=0xf4": "к╔кжк╩кык│к╚клбву¤█╒к╟бв",
    "0xf7=0x10c": "у¤█╒к╟бв▄тбск╦бдбдбдб╣",
    "0x114=0x129": "к┤кпкэкжк╟к╖к┐бвлълвбг",
    "0x12b=0x144": "к╜кьк╚тоь╤ьщЁщк╬к▀к╩к╡кєбв",
    "0x146=0x161": "ф▓кщк╬╧┤кск╦ыык╕к╞бвк│к│к▐к╟",
    "0x164=0x17b": "кшкп╒╬к╞кпк└к╡кдк▐к╖к┐б╣",
    "0x183=0x1a0": "═▌к├к╞кык╬кЄ█пк├к╞ккк▒к╩кдк╡бг",
    "0x1a2=0x1bf": "к╟бвф┬кдк▒к╔бвкккьк┐к┴╨скдк╟бв",
    "0x1c2=0x1dd": "ї╜к╪бскщк╩кнкук╩кщк╩кдкєк└б╣",
    "0x1e5=0x1f6": "ь╤╩рк┐к┴к╬уй╠кк╚бв",
    "0x1f8=0x211": "ф▐¤┘╫гл╒лблЇл╦-лыбдбдбдбг",
    "0x214=0x225": "кцкцк╖кн▐└ў╛к╟к╣б╣",
    "0x229=0x22c": "х┤╧╓",
    "0x22f=0x230": "бв",
    "0x232=0x247": "квк╩к┐к╬ю·кдк╧бвк─кщкп",
    "0x24a=0x263": "хёк╖кдктк╬к╦к╩кык╟к╖кчкжб╣",
    "0x267=0x27c": "б║┘у╥│к╬╬об╗к╧бвк╔кжк╛",
    "0x27e=0x293": "к╜к╬к▐к▐ккЄек┴∙╗к╡кдбг",
    "0x295=0x2ac": "к╜кькмквкы∙┌къбвквк╩к┐к╧",
    "0x2af=0x2ca": "л╩лщл╖лєл╧к╬╒ЇкЄ╘Ёкщкьк▐к╣б╣",
    "0x2d2=0x2db": "кшклк├к┐к═",
    "0x2de=0x2df": "бв",
    "0x2e1=0x2f2": "к│кьклкщктбвк║к├к╚",
    "0x2f5=0x30e": "л╩лщл╖лєл╧к╦бсуєк╟кнкыкшб╣",
    "0x316=0x323": "лълвбвккк▐кик╧",
    "0x325=0x336": "╦╦к╡кєк╚═ьк╦·╝кнбв",
    "0x339=0x350": "к│к╬х┘ы┌к╦кркпкдк╩к╡кдб╣",
    "0x358=0x365": "кяклкък▐к╖к┐бг",
    "0x368=0x37b": "кмкєк╨к├к╞кнк▐к╣кеб╣",
    "0x384=0x399": "к╡квбв·╝кнк▐к╖кчкж!б╣",
    "0x3de=0x3f5": "бдбдбдтоуък╬▄ць╘кЄсЇк▒к┐",
    "0x3f7=0x40e": "л╒лблЇл╦-лыкмбвк╔кжк╖к╞",
    "0x411=0x42e": "·░█пк╡кьк┐к╬к╟квкэкжклбдбдбдб╣",
    "0x432=0x449": "к╖клк╖бвк│к╬√ш╒пк╬сжк╦бв",
    "0x44b=0x468": "▐тэнуъш▌кмяо▀цк╖к╞кдк┐к│к╚кмбв",
    "0x46b=0x480": "к╗кск╞ктк╬ъ╨ксбдбдбдб╣",
    "0x48f=0x49e": "бдбдбдк╡к╞бдбдбд",
    "0x4a1=0x4b2": "к╜кьк╧к╔кжклк╩?б╣",
    "0x4c5=0x4d2": "к│к╬╤и█╒бдбдбд",
    "0x4d5=0x4e6": "л╒лблЇл╦-лы?!б╣",
    "0x503=0x516": "╬∙█░к╓кък└к╩бдбдбдб╣",
    "0x51e=0x537": "бдбдбд╫гш▌кшбвк╔кжкфк├к╞бв",
    "0x53a=0x555": "квк╬▄ць╘клкщ╘▒кьк┐к╬к╟к╣?б╣",
    "0x559=0x56a": "квкьк╧бв▐тэнуъш▌км",
    "0x56c=0x57f": "┘дкЄклк▒к╞°═к╕к┐ь╘бг",
    "0x581=0x59a": "╘╥╘їк╬╦нкн╒Їк╬уък╟к╩кпк╞к╧",
    "0x59d=0x5bc": "·░кпк│к╚к╬к╟кнк╩кдктк╬бдбдбд!б╣",
    "0x5c4=0x5df": "▐тэнуъш▌бвл╩лщл╖лєл╧клбдбдбд",
    "0x5e1=0x5fa": "№мклк╦бвквкфк─к╬╒Їк╧╦нкпбв",
    "0x5fd=0x61a": "кяк╖к╧бв╧▌щ┤к╬у┴кЄк╖кдкщкьк┐б╣",
    "0x61e=0x633": "бдбдбдк└кмк╩бв╥│ш▌кшбг",
    "0x636=0x655": "сж═гк╦кдкык╬к╧бвуък└к▒к╟к╧к╩кдб╣",
    "0x65d=0x674": "к╜кьк╧к╔кжхыкжыЄ┌лбдбдбд",
    "0x676=0x67d": "бдбдбд!",
    "0x680=0x699": "к▐к╡клбвл╒лблЇл╦-лы?!б╣",
    "0x6a1=0x6ba": "╥│ш▌кшбвккк▐кик╧бвк╣к░кьк┐",
    "0x6bc=0x6d5": "Є▒рїк╚╪к█Ў╒ЇкЄЄек├к╞кдкыбг",
    "0x6d8=0x6f5": "к╔кжк└бвкяк╖к╦╒ЇкЄ╙шк╡к╠кл?б╣",
    "0x6fd=0x71a": "бдбдбдкккэклк╩┘¤кдклк▒кЄбдбдбд",
    "0x71d=0x73a": "╙═кик╧ўўк├к╞кдкык╟к╖кчкжк╦!б╣",
    "0x742=0x753": "бдбдбдк╒к╒к╒бдбдбд",
    "0x756=0x75f": "к╜кжк└к╩б╣",
    "0x83e=0x85d": "к╩бвк╩кєкфбвЄв╪№кмшЇкьк┐к╛?!б╣",
    "0x865=0x870": "уъю№к╬█░к╦бв",
    "0x873=0x88c": "ц╒к▀к┐кдк╩к╬км╠╕кикыкш!б╣",
    "0x894=0x8a7": "лфл└!_уъю№кмбдбдбд",
    "0x8a9=0x8b8": "уъю№км▌┌кькы?!",
    "0x8bb=0x8ca": "к╔кжк╖к╞к├?!б╣",
    "0x9f8=0xa03": "к╜кєк╩бдбдбд",
    "0xa06=0xa13": "╥│ш▌х╞к├?!б╣",
    "0xa1c=0xa29": "їєк┴кул└лс!б╣",
    "0xa31=0xa40": "╫юк╖к╞∙╗к╡кд-бв",
    "0xa42=0xa4d": "╥│ш▌кмбдбдбд",
    "0xa50=0xa69": "ёъ╩рк╬к▀кєк╩кмбдбдбд!!б╣",
    "0xa71=0xa88": "квкькмл╒лблЇл╦-лыл├!!",
    "0xa8b=0xaa2": "бдбдбдк┴кпк╖кчккккк├!б╣",
    "0xabb=0xace": "лвл█лж!_їєк╞кдк├к╞",
    "0xad0=0xae7": "к╔к╩кдк╩кык├к┴кхкжкєкф!",
    "0xae9=0xafa": "╠╕к─клк├к╞№пс└кнк╦",
    "0xafd=0xb12": "к╡кькыкєкмлкл┴кфк╛!б╣",
    "0xb1a=0xb21": "кккьк╧бв",
    "0xb23=0xb3a": "л╩лщл╖лєл╧к╦к╩кькыкєк└!",
    "0xb3c=0xb49": "я╛╙▀к╦унк╞кы!",
    "0xb4c=0xb5d": "унк├к╞кфкык├!!б╣",
    "0xb65=0xb80": "лдл╞л├!_╬скркєк╕кук═кзк├!",
    "0xb83=0xb92": "лдл└л└л└л└л├!б╣",
    "0xb9a=0xbaf": "т┴клбвтвкз╙шк╖к╞кпкьбв",
    "0xbb1=0xbc2": "к│к╬л╨ллкЄтйлєёщк╦",
    "0xbc5=0xbd4": "█пкъбскркєкф!б╣",
    "0xbe8=0xc03": "кжкяк├?_кякякякякяк├?!б╣",
    "0xc1d=0xc36": "квк╬ш╫э█к╩уъю№кЄЎгкн▐лк╨к╣",
    "0xc38=0xc4f": "л╨л▒лтлєк╦бв╨╤к╬ккк▐кикм",
    "0xc51=0xc66": "унк╞кыкяк▒квкщк╪кєкя!",
    "0xc69=0xc7a": "кшк╖бвы▀кькэ!!б╣",
    "0xcc1=0xcd2": "л╤лык╧с│к╡кдклкщбв",
    "0xcd5=0xce6": "╠╕к─клкщк╩кдкшк═б╣",
    "0xcee=0xd0d": "л╪лзбвквкькмл╒лблЇл╦-лык╩к╬к═бг",
    "0xd0f=0xd26": "╙▐к├кнкд-!_к╣к┤-кд!",
    "0xd29=0xd40": "кв-бвк│к├к┴к╦╒╬кы-!б╣",
    "0xd61=0xd6e": "бдбдбдбдбдбдбд",
    "0xd71=0xd7e": "·╝к├к┴кук├к┐б╣",
    "0xd86=0xd8f": "к▀кєк╩-бв",
    "0xd92=0xda1": "кткж╙▐э█▄¤к└кшб╣",
    "0xe3e=0xe59": "к╥к╚к▐к║бвЁ╛клк├к┐кяк▒кфк╩б╣",
    "0xe61=0xe78": "бдбдбдк┤кскєк╩к╡кдбдбдбд",
    "0xe7a=0xe8f": "лял┐л╖бвкфк├к╤къуъю№к╪",
    "0xe92=0xea5": "ктк╔кък▐к╣кебдбдбдб╣",
    "0xead=0xec8": "╨╤бвктк╔кык╬к╧ъ╦·╧к└кмбдбдбд",
    "0xecb=0xee6": "бдбдбдЄнкскык│к╚к╧к╟кнк╩кдб╣",
    "0xeee=0xf07": "к│к┴кщкм╒кк┴є╖кдк┐кщбв∙▒к║",
    "0xf0a=0xf1f": "твЁ╛к▒к╦к▐кдкък▐к╣кяб╣",
    "0xf27=0xf38": "к│к╬б║┘у╥│к╬╬об╗к╧",
    "0xf3a=0xf53": "к▀к╩к╡кєкмккЄек┴кпк└к╡кдбг",
    "0xf56=0xf61": "к╟к╧бдбдбдб╣",
    "0xf7a=0xf8f": "кшк╖к├бвї╜к╪бскык╟!б╣",
    "0xf97=0xfa4": "к┴бвк┴кчк├к╚бв",
    "0xfa7=0xfa8": "кЄ",
    "0xfab=0xfc2": "Ў╟кдк╞·╝к├к┴кул└лскш!б╣",
    "0xfcb=0xfe0": "к╩кєкфбвЁ╛к▒кыкєкл?б╣",
    "0xffd=0x1012": "кпбдбдбдбвл╩л╕лхбдбдбд",
    "0x1015=0x1028": "к╞бдксбдки-к├!!б╣",
    "0x1031=0x1036": "к▓!б╣",
    "0x104a=0x1057": "╙тк┴кфкмкьк├!",
    "0x105a=0x1069": "к│к╬хп╒═к├!!б╣",
    "0x107c=0x1095": "к▐квбв∙╝к╧к╚ктквкьбв╨скдк╟",
    "0x1098=0x10af": "▐тэньщЁщк╬ї╜к╪·╛клкккжб╣",
    "0x10e4=0x10eb": "л▒лдлы!",
    "0x10ee=0x10ff": "┘э▐└к╟кшклк├к┐!б╣",
    "0x1107=0x110c": "л▐л▐!",
    "0x110e=0x1123": "к│кєк╩с╢к╟к╔кжк╖к┐к╬?",
    "0x1126=0x1137": "ї╜к╬к▀кєк╩к╧?!б╣",
    "0x113f=0x1150": "№ек╧квк╚бгк▀кєк╩бв",
    "0x1152=0x1169": "л╚лщ╓╒к╡к▐к╬с╢к╦кдкыкябг",
    "0x116c=0x117f": "квк╩к┐к┐к┴ктЁ─кп!б╣",
    "0x124a=0x1257": "л╚лщ╓╒к╡к▐к╦бв",
    "0x125a=0x1261": "к╬л╤л╤!",
    "0x1264=0x127f": "л▒лмкЄк╖к┐к╬?_╙▐э█▄¤?!б╣",
    "0x1287=0x128c": "Ў╤▌л!",
    "0x128e=0x12a9": "ь╤╩рк┐к┴к╬╧┌км╒╬к┐кєк└кэ?!",
    "0x12ac=0x12c3": "ї╜к╧к╔кжк╩к├к┐кєк└?!б╣",
    "0x12cb=0x12e0": "▄▓▐═к╔ктк╧ї┌кд▌┘к├к┐бг",
    "0x12e2=0x12f9": "к└кмбв╬╓к╖к▓к╩╪кт·кЄЁ├кы",
    "0x12fb=0x1308": "▐╔Ёок╦твк╥к╔кп",
    "0x130b=0x1324": "кфкщкьк╞к╖к▐к├к╞к╩бдбдбдб╣",
    "0x132c=0x1347": "ьщ╠╕к╣кык╚эн═ък╬кшкжк╕кукмбв",
    "0x1349=0x1356": "═Ёкэк╖кп╦нкдбг",
    "0x1358=0x1369": "▐┬█░к╩кпбвк│к┴кщк╪",
    "0x136c=0x137d": "╘▒к▓к╞кнк┐к╬к╕куб╣",
    "0x1385=0x139c": "▐тэнэ■к╡к▐бвл╒лблЇл╦-лы",
    "0x139f=0x13b8": "▄╓№└к╬лжлял╡к╧▄тбск╟к╖к┐б╣",
    "0x13c0=0x13d1": "л▐-лслдл╔к╬уъю№к╧",
    "0x13d3=0x13e6": "л╒лблЇл╦-лык╦кшк├к╞",
    "0x13e9=0x1404": "╬╒к╡кьк╞к╖к▐кдк▐к╖к┐бдбдбдб╣",
    "0x140c=0x1417": "к╩кєк└к╚?!",
    "0x141a=0x1431": "к╩кєк╚хыкжк│к╚к└бдбдбдб╣",
    "0x1439=0x1454": "Ў╤▌л!_кккьбвл╒лблЇл╦-лыкЄ",
    "0x1457=0x146a": "кфк├к─к▒к╞кпкык╝!б╣",
    "0x1472=0x1483": "к╨бдбдбдк╨клктк╬!",
    "0x1485=0x149a": "ккюёк╧бвл╒лблЇл╦-лыкЄ",
    "0x149d=0x14ac": "ўўк├к╞кккщкє!б╣",
    "0x14b0=0x14c3": "квкьк╧ї╠╦нк╬тош▌уъбг",
    "0x14c5=0x14d6": "ф▓кмЁ╙р╗к╬▐тэнуъш▌",
    "0x14d9=0x14ea": "л╩лщл╖лєл╧к╟к╣кщб╣",
    "0x14ee=0x1509": "┘дк╚ь┌кн№╡кик╦бв▄ць╘к╣кык╬км",
    "0x150b=0x151e": "яёьщ█╩к└к├к┐╪к┌кк└!",
    "0x1521=0x1534": "ккюёк╦∙╝кмк╟кнкы!б╣",
    "0x153d=0x155c": "кккьк╧л╩лщл╖лєл╧к╦к╩кькыкєк└!б╣",
    "0x1564=0x157f": "ккк╕к╡к▐бвк╜кьк╧▄тбск╟к╣кябг",
    "0x1581=0x159a": "к│к╬л▐-лслдл╔клкщкткщк├к┐",
    "0x159c=0x15af": "б║┘у╥│к╬╬об╗к╬╒Їк╟бв",
    "0x15b2=0x15cb": "бсуєк╟кнкыкшкжк╦к╩к├к┐к╬б╣",
    "0x15d3=0x15e8": "л▐-лслдл╔Ёщк╬Є╕бскл!",
    "0x15eb=0x1606": "к└кмбвк╜к╬╒Їк└к▒к╟к╧бдбдбдб╣",
    "0x160e=0x1623": "бдбдбдбдбдбдкяклк├к┐бг",
    "0x1628=0x163d": "бвьщь╤к╟к─кдк╞к│кд!б╣",
    "0x1646=0x1651": "ьщь╤к└к▒?б╣",
    "0x1659=0x1660": "▐тэнэ■бв",
    "0x1663=0x167a": "к╗кск╞бвтвбскЄк╖к╞клкщб╣",
    "0x16fa=0x170f": "к│кєк╩с╢к╪╓зкьк╞кнк╞бв",
    "0x1712=0x1721": "∙╝кмквкыкєк└?б╣",
    "0x1729=0x1740": "с┤к╖Ё─к▐к├к╞к╖к▐к├к┐кмбв",
    "0x1743=0x175a": "ккюёк╬рўь╤к╬ыЁу╥кЄ·╝кжб╣",
    "0x1762=0x1781": "к│кьклкщб║▐тэнк╬к█к│кщб╗к╦ь¤къбв",
    "0x1783=0x179e": "ю╪к╚ю·кдбвчєк╦квкы▐тэнуъ▀└к╦",
    "0x17a1=0x17b8": "╤╖къкЄк╡к╡к▓к╞кпкык╬к└б╣",
    "0x17c1=0x17da": "к╟бвк╜кькм∙╝к╦к╩кыкєк└?б╣",
    "0x17e2=0x17fd": "л░л└л░л└хыкяк║к╦·╝к├к╞к│кд!",
    "0x17ff=0x180c": "к╜к╬у┴к╦к╩кьк╨",
    "0x180f=0x1820": "ккк╬к║к╚ўўкэкж!б╣",
    "0x1828=0x1831": "ру┘ек░кщкд",
    "0x1833=0x1846": "к╖к┐к├к╞кдкдк└кэкжбв",
    "0x1849=0x185a": "к│к╬лпл╜Ў╤▌л!!б╣",
    "0x1863=0x1870": "к└к▐к├к╚кь!б╣",
    "0x1874=0x188d": "б║Ї╕кшкъ╒╬к┐кы╤╤▀фк╬ш▌кшбв",
    "0x188f=0x18a8": "═пк╬╪ях│к╦кшкъбвуцк┐к╩кыэ║",
    "0x18aa=0x18c1": "у╦╓гк╬┌жкЄкпк░кык╚щ░к╣бг",
    "0x18c4=0x18d1": "╙Їкнквкь!б╗б╣",
    "0x1917=0x1926": "·╝кпк╬к└лЇлблєбг",
    "0x1929=0x193e": "ккюёк╬╒ЇкЄ╠╕к╗к╞к▀кэб╣",
    "0x1947=0x1960": "бдбдбдк┴кзк├бвкяклк├к┐кшб╣",
    "0x19b0=0x19bf": "к╪кзбвк│к╬╘╫╧▀бв",
    "0x19c2=0x19df": "к│кєк╩∙жк╦к╩к├к╞к┐к╬клбдбдбдб╣",
    "0x19e7=0x19fe": "к▓к├бв╤и┌лкякыкд√∙к▒┌к!",
    "0x1a00=0x1a15": "к╟ктбвк╔к│клк╟╠╕к┐к│к╚",
    "0x1a18=0x1a33": "квкыкшкжк╩бдбдбдк▐бвкдкдклб╣"
}